Workbook

Sheet Guiding Questions
A1: S/N | B1: Question | C1: Focus | D1: Goal
A2: 1 | B2: What are the most important outcomes you are responsible for? | C2: (Could limit to 2 or 3) | D2: This question seeks to help you both establish a clear and simple objective for the role.
A3: 2 | B3: What evidence is there to show that you have done a great Job? | C3: A simple answer indicating a positive change | D3: The aim here is to visualize what success looks like for the role. Additionally you would want to take note if the outcome can be quantified.
A4: 3 | B4: What activities or behaviours lead to these outcomes? | C4: Role and department specific. | D4: Aims to understand what drives success
A5: 4 | B5: Are they existing metrics or numbers that show success in these area? | D5: The goal is to understand how success is already measured.
A6: 5 | B6: If there are existing data, where does it come from? | C6: A system or report that generates or shows these data. | D6: This question points us to the data source. Verifying for data integrity.
A7: 6 | B7: What is the timeframe for measuring sucess? | C7: Semester, Monthly, weekly, Block, etc. | D7: This is to understand how often their work would yield results and what progress looks like within that timeframe.

Sheet Overview
B1: Operational Outcomes | E1: Student Outcomes
B2: Speed | C2: Quality | D2: Cost | E2: Student Autonomy | F2: Student Satisfaction | G2: Completion
A3: Definition | B3: Operations are executed with promptness in order to maximize efficiency and satisfaction. | C3: Operations are conducted at a high rate of quality, maximizing satisfaction. | D3: Operations reduce and control costs, allowing for efficiency and scalability of services. | E3: The proportion of students not needing help from the home office in order to navigate the student experience. | F3: Student levels of satisfaction with their services experience--coupled with autonomy, students are delighted with their service experience without needing help from the home office. | G3: The proportion of students retained and completing a credential.
A4: Examples | B4: Resolution rate Completion time Response time Processing time | C4: QA measures Accuracy Number of bugs or issues Process C-Sat 1st contact resolution Throughput rate Usage rate | D4: Wages Contractual services budget Compute costs Licenses ITD/ITS Costs per [unit of measure] | E4: What proportion of students submits an issue or process ticket for your services each term/year? | F4: Surveys or other forms of objective feedback indicating C-Sat with your specific services. Also consider other clients' satisfaction, as applicable. | G4: Application funnel Retention C1 Completion
B19: Question | C19: Goal | D19: Focus
B20: What are the most important operational outcomes this role is responsible for? | C20: This question seeks to help you both establish a clear objective for the role. | D20: As these are established, begin assigning them among the Operational and Student Outcomes
B21: How does this role impact the 3 imperitives of Student Services? (Autonomy, Satisfaction, Completion) | C21: Understanding this help guide which categories are most appropriate for setting KPIs.
B22: Does this role support the organization in providing critical services? | C22: If a role contributes to a critical services, it is important to ensure those things are measured by their KPIs. | D22: Critical services' are the services which every university must provide as a tertiary institution. Not every role does contribute to critical services, but if they do then it is good to have this in mind for setting KPIs.
B23: What evidence is there to show that you have done a great Job? | C23: The aim here is to visualize what success looks like for the role and identify what can be quantified.
B24: What activities or behaviours lead to these outcomes? | C24: Aims to understand what drives success | D24: Role and department specific.
B25: Are they existing metrics or numbers that show success in these area? | C25: The goal is to understand how success is already measured.
B26: If there are existing data, where does it come from? | C26: This question points us to the data source. Verifying for data integrity. | D26: A system or report that generates or shows these data.
B27: What is the timeframe for measuring sucess? | C27: This is to understand how often their work would yield results and what progress looks like within that timeframe. | D27: Semester, Monthly, weekly, Block, etc.

Sheet Dean of Students
A1: Employee Information | E1: Operational Outcomes | H1: Student Outcomes
A2: Employee Name | B2: Role | C2: Employment Status | D2: Stewardship | E2: Speed | F2: Quality | G2: Cost | H2: Student Autonomy | I2: Student Satisfaction | J2: Completion
A3: Steven K. Thomas | B3: Dean of Students | C3: FTE | D3: > Dean of Students office oversight > Title IX coordintor, ADA/Section 504 coordinator | F3: No material audit findings attributable to Dean of Students governance No legal findings attributable to Dean of Students governance No accreditation findings attributable to Dean of Students governance | G3: Annual DOS budget | I3: Overall student satisfaction (primary) | Y3: =_xlfn.TEXTJOIN(CHAR(10), TRUE, E3:G3) -> No material audit findings attributable to Dean of Students governance No legal findings attributable to Dean of Students governance No accreditation findings attributable to Dean of Students governance Annual DOS budget | Z3: =_xlfn.TEXTJOIN(CHAR(10), TRUE, H3:J3) -> Overall student satisfaction (primary)
A4: Anne Marie Clark | B4: Associate Dean of Students | C4: FTE | D4: > DOS operational lead > Deputy Title IX and ADA/Section 504 coordinator | E4: Dean of Students response time Dean of Students resolution time | F4: Dean of Students services escalation rates Partner C-Sat | Y4: =_xlfn.TEXTJOIN(CHAR(10), TRUE, E4:G4) -> Dean of Students response time Dean of Students resolution time Dean of Students services escalation rates Partner C-Sat | Z4: =_xlfn.TEXTJOIN(CHAR(10), TRUE, H4:J4)
A5: Katelyn Ray | B5: Student Honor & Conduct Coordinator | C5: FTE | D5: > CES Honor Code > Student conduct | E5: Honor and Conduct response time Honor and Conduct resolution time | F5: Rate of repeat offenders | Y5: =_xlfn.TEXTJOIN(CHAR(10), TRUE, E5:G5) -> Honor and Conduct response time Honor and Conduct resolution time Rate of repeat offenders | Z5: =_xlfn.TEXTJOIN(CHAR(10), TRUE, H5:J5)
A6: Ana De Castro | B6: Student Belonging Coordinator | C6: FTE | D6: > Non-Discrimination > Student belonging | F6: Discrimination resolution rate Student sentiment on belonging CSAT for Student Belonging | Y6: =_xlfn.TEXTJOIN(CHAR(10), TRUE, E6:G6) -> Discrimination resolution rate Student sentiment on belonging CSAT for Student Belonging | Z6: =_xlfn.TEXTJOIN(CHAR(10), TRUE, H6:J6)
A7: Sandra Wurttele | B7: Student Accessibility Coordinator | C7: Contractor | D7: > Deputy ADA/Section 504 coordinator | E7: Accommodation determination processing rate Accommodation resolution rate | F7: ADA and Section 504 standard compliance rate ADA and Section 504 Audit compliance rate | Y7: =_xlfn.TEXTJOIN(CHAR(10), TRUE, E7:G7) -> Accommodation determination processing rate Accommodation resolution rate ADA and Section 504 standard compliance rate ADA and Section 504 Audit compliance rate | Z7: =_xlfn.TEXTJOIN(CHAR(10), TRUE, H7:J7)
A8: Helen Reboucas | B8: Student Grievance Coordinator | C8: Contractor | D8: > Student grievances | E8: Student grievance case resolution time | F8: Grievance QA | Y8: =_xlfn.TEXTJOIN(CHAR(10), TRUE, E8:G8) -> Student grievance case resolution time Grievance QA | Z8: =_xlfn.TEXTJOIN(CHAR(10), TRUE, H8:J8)
A9: Joseph Bentum | B9: Student Crisis Coordinator | C9: Contractor | D9: > Students-in-Crisis > High-need case monitoring | E9: Crisis response time | Y9: =_xlfn.TEXTJOIN(CHAR(10), TRUE, E9:G9) -> Crisis response time | Z9: =_xlfn.TEXTJOIN(CHAR(10), TRUE, H9:J9)
Y10: =_xlfn.TEXTJOIN(CHAR(10), TRUE, D10:F10) | Z10: =_xlfn.TEXTJOIN(CHAR(10), TRUE, G10:I10)
Y11: =_xlfn.TEXTJOIN(" | ", TRUE, D11:F11) | Z11: =_xlfn.TEXTJOIN(" | ", TRUE, G11:I11)
Y12: =_xlfn.TEXTJOIN(" | ", TRUE, D12:F12) | Z12: =_xlfn.TEXTJOIN(" | ", TRUE, G12:I12)
Y13: =_xlfn.TEXTJOIN(" | ", TRUE, D13:F13) | Z13: =_xlfn.TEXTJOIN(" | ", TRUE, G13:I13)
Y14: =_xlfn.TEXTJOIN(" | ", TRUE, D14:F14) | Z14: =_xlfn.TEXTJOIN(" | ", TRUE, G14:I14)
Y15: =_xlfn.TEXTJOIN(" | ", TRUE, D15:F15) | Z15: =_xlfn.TEXTJOIN(" | ", TRUE, G15:I15)
Y16: =_xlfn.TEXTJOIN(" | ", TRUE, D16:F16) | Z16: =_xlfn.TEXTJOIN(" | ", TRUE, G16:I16)
Y17: =_xlfn.TEXTJOIN(" | ", TRUE, D17:F17) | Z17: =_xlfn.TEXTJOIN(" | ", TRUE, G17:I17)
Y18: =_xlfn.TEXTJOIN(" | ", TRUE, D18:F18) | Z18: =_xlfn.TEXTJOIN(" | ", TRUE, G18:I18)
Y19: =_xlfn.TEXTJOIN(" | ", TRUE, D19:F19) | Z19: =_xlfn.TEXTJOIN(" | ", TRUE, G19:I19)
Y20: =_xlfn.TEXTJOIN(" | ", TRUE, D20:F20) | Z20: =_xlfn.TEXTJOIN(" | ", TRUE, G20:I20)
Y21: =_xlfn.TEXTJOIN(" | ", TRUE, D21:F21) | Z21: =_xlfn.TEXTJOIN(" | ", TRUE, G21:I21)
Y22: =_xlfn.TEXTJOIN(" | ", TRUE, D22:F22) | Z22: =_xlfn.TEXTJOIN(" | ", TRUE, G22:I22)
... Y24: =_xlfn.TEXTJOIN(" | ", TRUE, D24:F24) | Z24: =_xlfn.TEXTJOIN(" | ", TRUE, G24:I24)

Sheet Digital Ops
A1: Employee Information | E1: Operational Outcomes | H1: Student Outcomes
A2: Employee Name | B2: Role | C2: Employment Status | D2: Stewardship | E2: Speed | F2: Quality | G2: Cost | H2: Student Autonomy | I2: Student Satisfaction | J2: Completion
A3: Jacob Adams | B3: Director of Digital Operations | C3: FTE | D3: > Digital operations oversight > Application and implementation of emerging technologies > Strategy for Power BI, machine learning, agentic AI, and Companion teams > UX evaluation & impact review | F3: Overall Stakeholder CSAT | G3: Digital Ops budget Costs saved by customers due to Digital Ops technologies (secondary) | H3: Overall student autonomy (secondary) | I3: Overall student satisfaction (secondary) | J3: Application Rate Retention Rate Completion Rate (Secondary) | Z3: =_xlfn.TEXTJOIN(CHAR(10), TRUE, E3:G3) -> Overall Stakeholder CSAT Digital Ops budget Costs saved by customers due to Digital Ops technologies (secondary) | AA3: =_xlfn.TEXTJOIN(CHAR(10), TRUE, H3:J3) -> Overall student autonomy (secondary) Overall student satisfaction (secondary) Application Rate Retention Rate Completion Rate (Secondary)
A4: Ricky Kailiponi Jr. | B4: Senior Manager of Digital Ops | C4: FTE | D4: > Business Partner collaboration > Architect & Engineer engagement (IT/ICS) > Development & QA lead > AI Compliance & advancement | E4: Team meeting project deadlines rate | F4: Companion feature C-Sat | H4: Companion usage rates | I4: Companion C-Sat | J4: AI retention effect | Z4: =_xlfn.TEXTJOIN(CHAR(10), TRUE, E4:G4) -> Team meeting project deadlines rate Companion feature C-Sat | AA4: =_xlfn.TEXTJOIN(CHAR(10), TRUE, H4:J4) -> Companion usage rates Companion C-Sat AI retention effect
A5: Joshua Stafford Hadden | B5: Operational Research & Reporting Manager | C5: FTE | D5: > Registrar business solutions > Operational data & reporting > SIS support & configuration | E5: Team meeting project timelines rate | F5: Stakeholder CSAT on team's projects | G5: Cost reductions in service areas (secondary) | Z5: =_xlfn.TEXTJOIN(CHAR(10), TRUE, E5:G5) -> Team meeting project timelines rate Stakeholder CSAT on team's projects Cost reductions in service areas (secondary) | AA5: =_xlfn.TEXTJOIN(CHAR(10), TRUE, H5:J5)
A6: David Peck | B6: Operational Data Analyst | C6: FTE | D6: > Power BI report management & refresh | E6: Project delivery on time rate | F6: Stakeholder CSAT - communication, quality of work, impact | Z6: =_xlfn.TEXTJOIN(CHAR(10), TRUE, E6:G6) -> Project delivery on time rate Stakeholder CSAT - communication, quality of work, impact | AA6: =_xlfn.TEXTJOIN(CHAR(10), TRUE, H6:J6)
A7: Pelenatita Neiufi | B7: Reporting & Evaluation Coordinator | C7: FTE | D7: > NSC & Enrollment reporting (BYUI & EC) > Student record updates (Demographics, SSN) > Qualitative research | E7: Project delivery on time rate | F7: Stakeholder CSAT - communication, quality of work, impact | Z7: =_xlfn.TEXTJOIN(CHAR(10), TRUE, E7:G7) -> Project delivery on time rate Stakeholder CSAT - communication, quality of work, impact | AA7: =_xlfn.TEXTJOIN(CHAR(10), TRUE, H7:J7)
A8: Victor Lamôni Calado Ferreira | B8: System & Operations Associate Registrar (title change) | C8: FTE | D8: > Registrar services for MLP students | E8: Project delivery on time rate | F8: Stakeholder CSAT - communication, quality of work, impact | Z8: =_xlfn.TEXTJOIN(CHAR(10), TRUE, E8:G8) -> Project delivery on time rate Stakeholder CSAT - communication, quality of work, impact | AA8: =_xlfn.TEXTJOIN(CHAR(10), TRUE, H8:J8)
A9: John Ayinde | B9: D365 & Automation Manager | C9: Contractor | D9: > Mentor Portal > Predictive Model Data Pipeline | E9: Stakeholder CSAT - timeliness per project | F9: Stakeholder CSAT - communication, quality of work, impact | Z9: =_xlfn.TEXTJOIN(CHAR(10), TRUE, E9:G9) -> Stakeholder CSAT - timeliness per project Stakeholder CSAT - communication, quality of work, impact | AA9: =_xlfn.TEXTJOIN(CHAR(10), TRUE, H9:J9)
A10: Samuel Riveros | B10: Companion & Special Projects Manager | C10: Contractor | D10: > Companion Front-End Stability & Usability > Companion–Analytics Engine Integration | E10: Stakeholder CSAT - timeliness per project | F10: Stakeholder CSAT - communication, quality of work, impact | Z10: =_xlfn.TEXTJOIN(CHAR(10), TRUE, E10:G10) -> Stakeholder CSAT - timeliness per project Stakeholder CSAT - communication, quality of work, impact | AA10: =_xlfn.TEXTJOIN(CHAR(10), TRUE, H10:J10)
A11: Aitana Toscano | B11: Data Manager | C11: Contractor | D11: > Power BI reporting lead > Backend Data stability & cleaning | E11: Stakeholder CSAT - timeliness per project | F11: Stakeholder CSAT - communication, quality of work, impact | Z11: =_xlfn.TEXTJOIN(CHAR(10), TRUE, E11:G11) -> Stakeholder CSAT - timeliness per project Stakeholder CSAT - communication, quality of work, impact | AA11: =_xlfn.TEXTJOIN(CHAR(10), TRUE, H11:J11)
A12: Isaias Zuñiga | B12: AI Manager | C12: Contractor | D12: > AI/ML Architecture development > Data Model development > Azure Board, GitHub, & DevOps Pipeline management | Z12: =_xlfn.TEXTJOIN(CHAR(10), TRUE, E12:G12) | AA12: =_xlfn.TEXTJOIN(CHAR(10), TRUE, H12:J12)
Z13: =_xlfn.TEXTJOIN(" | ", TRUE, E13:G13) | AA13: =_xlfn.TEXTJOIN(" | ", TRUE, H13:J13)
Z14: =_xlfn.TEXTJOIN(" | ", TRUE, E14:G14) | AA14: =_xlfn.TEXTJOIN(" | ", TRUE, H14:J14)
Z15: =_xlfn.TEXTJOIN(" | ", TRUE, E15:G15) | AA15: =_xlfn.TEXTJOIN(" | ", TRUE, H15:J15)
Z16: =_xlfn.TEXTJOIN(" | ", TRUE, E16:G16) | AA16: =_xlfn.TEXTJOIN(" | ", TRUE, H16:J16)
Z17: =_xlfn.TEXTJOIN(" | ", TRUE, E17:G17) | AA17: =_xlfn.TEXTJOIN(" | ", TRUE, H17:J17)
Z18: =_xlfn.TEXTJOIN(" | ", TRUE, E18:G18) | AA18: =_xlfn.TEXTJOIN(" | ", TRUE, H18:J18)
Z19: =_xlfn.TEXTJOIN(" | ", TRUE, E19:G19) | AA19: =_xlfn.TEXTJOIN(" | ", TRUE, H19:J19)
Z20: =_xlfn.TEXTJOIN(" | ", TRUE, E20:G20) | AA20: =_xlfn.TEXTJOIN(" | ", TRUE, H20:J20)
Z21: =_xlfn.TEXTJOIN(" | ", TRUE, E21:G21) | AA21: =_xlfn.TEXTJOIN(" | ", TRUE, H21:J21)
Z22: =_xlfn.TEXTJOIN(" | ", TRUE, E22:G22) | AA22: =_xlfn.TEXTJOIN(" | ", TRUE, H22:J22)
Z23: =_xlfn.TEXTJOIN(" | ", TRUE, E23:G23) | AA23: =_xlfn.TEXTJOIN(" | ", TRUE, H23:J23)
Z24: =_xlfn.TEXTJOIN(" | ", TRUE, E24:G24) | AA24: =_xlfn.TEXTJOIN(" | ", TRUE, H24:J24)
... Z42: =_xlfn.TEXTJOIN(" | ", TRUE, E42:G42) | AA42: =_xlfn.TEXTJOIN(" | ", TRUE, H42:J42)

Sheet Enrollment & Retention
A1: Employee Information | E1: Operational Outcomes | H1: Student Outcomes
A2: Employee Name | B2: Role | C2: Employment Status | D2: Stewardship | E2: Speed | F2: Quality | G2: Cost | H2: Student Autonomy | I2: Student Satisfaction | J2: Completion
A3: Alison Cundiff | B3: Director of Enrollment & Retention | C3: FTE | D3: > Enrollment services & mentoring oversight > Student retention and completion | G3: Enrollment & Retention budget | H3: Overall student autonomy (secondary) | I3: Overall student satisfaction (secondary) | J3: Enrollment, retention, completion (primary) | Z3: =_xlfn.TEXTJOIN(CHAR(10), TRUE, E3:G3) -> Enrollment & Retention budget | AA3: =_xlfn.TEXTJOIN(CHAR(10), TRUE, H3:J3) -> Overall student autonomy (secondary) Overall student satisfaction (secondary) Enrollment, retention, completion (primary)
A4: Katelyn Graf | B4: Senior Manager of Retention | C4: FTE | D4: > Retention performance and execution lead > Mentoring performance, strategy, and innovation | J4: PC Completion Rate First Certificate Completion Rate
A5: Kelley Richardson | B5: Mentoring Manager | C5: FTE | D5: > Mentoring program lead | E5: Mentor required action completion rate | F5: Mentor interaction QA | I5: Mentor CSAT | J5: Retention rate contribution by mentors | Z5: =_xlfn.TEXTJOIN(CHAR(10), TRUE, E5:G5) -> Mentor required action completion rate Mentor interaction QA | AA5: =_xlfn.TEXTJOIN(CHAR(10), TRUE, H5:J5) -> Mentor CSAT Retention rate contribution by mentors
A6: Mandy Schwab | B6: Mentoring Content Coordinator | C6: Full-Time Contractor | D6: > Mentoring program development | F6: Mentor interaction QA | I6: Mentor CSAT | Z6: =_xlfn.TEXTJOIN(CHAR(10), TRUE, E6:G6) -> Mentor interaction QA | AA6: =_xlfn.TEXTJOIN(CHAR(10), TRUE, H6:J6) -> Mentor CSAT
A7: Joanna Relkin | B7: Mentor Operations Coordinator | C7: Full-Time Contractor | D7: > Mentoring program operations | E7: Mentor required action completion rate | F7: Mentor concern case QA | Z7: =_xlfn.TEXTJOIN(CHAR(10), TRUE, E7:G7) -> Mentor required action completion rate Mentor concern case QA | AA7: =_xlfn.TEXTJOIN(CHAR(10), TRUE, H7:J7)
A8: Trevor Shelton | B8: Senior Manager of Enrollment Services | C8: FTE | D8: > Enrollment services lead > Enrollment funnel performance, strategy, and innovation | H8: Reduction of enrollment related support cases Reduction of admissions tier 2 support cases | J8: Application start to admission yield Admission to registration yield Registration to auto-drop yield | Z8: =_xlfn.TEXTJOIN(CHAR(10), TRUE, E8:G8) | AA8: =_xlfn.TEXTJOIN(CHAR(10), TRUE, H8:J8) -> Reduction of enrollment related support cases Reduction of admissions tier 2 support cases Application start to admission yield Admission to registration yield Registration to auto-drop yield
A9: Rachel Kirk | B9: Enrollment Counseling Manager | C9: FTE | D9: > Enrollment Counseling program lead | E9: Enrollment Counseling required action completion rate Enrollment Counseling contact rate by alert | F9: Enrollment Counseling CSAT rate Enrollment Counseling yield contribution | Z9: =_xlfn.TEXTJOIN(CHAR(10), TRUE, E9:G9) -> Enrollment Counseling required action completion rate Enrollment Counseling contact rate by alert Enrollment Counseling CSAT rate Enrollment Counseling yield contribution | AA9: =_xlfn.TEXTJOIN(CHAR(10), TRUE, H9:J9)
A10: Kimarie Howard | B10: Enrollment Counseling Development and Performance Coordinator | C10: Full-Time Contractor | D10: > Enrollment Counseling development and performance | F10: Enrollment Counseling CSAT rate Enrollment Counseling yield contribution | Z10: =_xlfn.TEXTJOIN(CHAR(10), TRUE, E10:G10) -> Enrollment Counseling CSAT rate Enrollment Counseling yield contribution | AA10: =_xlfn.TEXTJOIN(CHAR(10), TRUE, H10:J10)
A11: Megan Niblett | B11: Enrollment Counseling Operations Coordinator | C11: Full-Time Contractor | D11: > Enrollment Counseling operations | E11: Enrollment Counseling required action completion rate Enrollment Counseling contact rate by alert | Z11: =_xlfn.TEXTJOIN(CHAR(10), TRUE, E11:G11) -> Enrollment Counseling required action completion rate Enrollment Counseling contact rate by alert | AA11: =_xlfn.TEXTJOIN(CHAR(10), TRUE, H11:J11)
A12: Shaunasee Janette James | B12: Enrollment Coordinator | C12: FTE | D12: > Transfer evaluation > Ecclesiastical endorsement > Chaplain partnership | E12: Transfer evaluation processing rate Transfer evaluation case resolution rate | F12: Number of transfer evaluation cases | Z12: =_xlfn.TEXTJOIN(CHAR(10), TRUE, E12:G12) -> Transfer evaluation processing rate Transfer evaluation case resolution rate Number of transfer evaluation cases | AA12: =_xlfn.TEXTJOIN(CHAR(10), TRUE, H12:J12)
A13: Ely Zmolek | B13: Enrollment Services Specialist | C13: FTE | D13: > Application processing > Admissons exceptions > Admissions systems | E13: Application processing rate Application manual review turnaround rate | F13: Number of admissions support cases Admissions case resolution rate | Z13: =_xlfn.TEXTJOIN(CHAR(10), TRUE, E13:G13) -> Application processing rate Application manual review turnaround rate Number of admissions support cases Admissions case resolution rate | AA13: =_xlfn.TEXTJOIN(CHAR(10), TRUE, H13:J13)
B14: University Chaplain | C14: FTE | D14: > Ecclesiastical endorsements for non-member students | E14: Non-member endorsement completion rate | F14: Number of support cases with non-member endorsement concerns | Z14: =_xlfn.TEXTJOIN(CHAR(10), TRUE, E14:G14) -> Non-member endorsement completion rate Number of support cases with non-member endorsement concerns | AA14: =_xlfn.TEXTJOIN(CHAR(10), TRUE, H14:J14)
Z15: =_xlfn.TEXTJOIN(" | ", TRUE, E15:G15) | AA15: =_xlfn.TEXTJOIN(" | ", TRUE, H15:J15)
Z16: =_xlfn.TEXTJOIN(" | ", TRUE, E16:G16) | AA16: =_xlfn.TEXTJOIN(" | ", TRUE, H16:J16)
Z17: =_xlfn.TEXTJOIN(" | ", TRUE, E17:G17) | AA17: =_xlfn.TEXTJOIN(" | ", TRUE, H17:J17)
Z18: =_xlfn.TEXTJOIN(" | ", TRUE, E18:G18) | AA18: =_xlfn.TEXTJOIN(" | ", TRUE, H18:J18)
Z19: =_xlfn.TEXTJOIN(" | ", TRUE, E19:G19) | AA19: =_xlfn.TEXTJOIN(" | ", TRUE, H19:J19)
Z20: =_xlfn.TEXTJOIN(" | ", TRUE, E20:G20) | AA20: =_xlfn.TEXTJOIN(" | ", TRUE, H20:J20)
Z21: =_xlfn.TEXTJOIN(" | ", TRUE, E21:G21) | AA21: =_xlfn.TEXTJOIN(" | ", TRUE, H21:J21)
Z22: =_xlfn.TEXTJOIN(" | ", TRUE, E22:G22) | AA22: =_xlfn.TEXTJOIN(" | ", TRUE, H22:J22)
Z23: =_xlfn.TEXTJOIN(" | ", TRUE, E23:G23) | AA23: =_xlfn.TEXTJOIN(" | ", TRUE, H23:J23)
Z24: =_xlfn.TEXTJOIN(" | ", TRUE, E24:G24) | AA24: =_xlfn.TEXTJOIN(" | ", TRUE, H24:J24)
Z25: =_xlfn.TEXTJOIN(" | ", TRUE, E25:G25) | AA25: =_xlfn.TEXTJOIN(" | ", TRUE, H25:J25)
Z26: =_xlfn.TEXTJOIN(" | ", TRUE, E26:G26) | AA26: =_xlfn.TEXTJOIN(" | ", TRUE, H26:J26)
... Z32: =_xlfn.TEXTJOIN(" | ", TRUE, E32:G32) | AA32: =_xlfn.TEXTJOIN(" | ", TRUE, H32:J32)

Sheet Records, Registration, Supp (2)
A1: Employee Information | E1: Operational Outcomes | H1: Student Outcomes
A2: Employee Name | B2: Name | C2: Employment Status | D2: Stewardship | E2: Speed | F2: Quality | G2: Cost | H2: Student Autonomy | I2: Student Satisfaction | J2: Completion
A3: Mark Gefrom | B3: Director of Student Support | C3: FTE | D3: > Registrar, student support, Tech support oversight > Help center > Customer relations systems > Case systems | E3: Teams meeting or exceeding response service-level agreements Teams meeting or exceeding resolution service-level agreements | F3: Teams meeting QA service-level agreements Teams meeting CSAT service-level agreements Teams meeting first contact resolution service-level agreements | G3: Student records, registration, and support department budget | H3: Overall student autonomy (primary) | I3: Overall student satisfaction (secondary) | Z3: =_xlfn.TEXTJOIN(CHAR(10), TRUE, E3:G3) -> Teams meeting or exceeding response service-level agreements Teams meeting or exceeding resolution service-level agreements Teams meeting QA service-level agreements Teams meeting CSAT service-level agreements Teams meeting first contact resolution service-level agreements Student records, registration, and support department budget | AA3: =_xlfn.TEXTJOIN(CHAR(10), TRUE, H3:J3) -> Overall student autonomy (primary) Overall student satisfaction (secondary)
A4: Brad Lester | B4: Senior Manager of Student Support | C4: FTE | D4: > Inbound student support lead > Academic advising program | G4: Student support budget | H4: Autonomy rate for student support cases | Z4: =_xlfn.TEXTJOIN(CHAR(10), TRUE, E4:G4) -> Student support budget | AA4: =_xlfn.TEXTJOIN(CHAR(10), TRUE, H4:J4) -> Autonomy rate for student support cases
A5: Alyssa Burrell | B5: Student Support Coordinator | C5: FTE | D5: > Phone support > General support | E5: General support case response rate General support case resolution rate Phone answer speed Phone handle rate Agent availability | F5: Phone support QA Phone support CSAT Phone support first contact resolution | Z5: =_xlfn.TEXTJOIN(CHAR(10), TRUE, E5:G5) -> General support case response rate General support case resolution rate Phone answer speed Phone handle rate Agent availability Phone support QA Phone support CSAT Phone support first contact resolution | AA5: =_xlfn.TEXTJOIN(CHAR(10), TRUE, H5:J5)
A6: Hilary Bagley | B6: Training & Quality Assurance Manager | C6: FTE | D6: > Training, area collaboration, & partner communication > Media & Knowledge Base development > Student Support content accuracy > Student journey mapping | E6: Request-to-KB publish rate QA feedback cycle rate | F6: QA calibration consistency rate Knowledge Base audit pass rate QA team lead feedback success rate | G6: Cost per QA Evaluation ($ per Evaluation) Cost per KB Article Maintained ($ per Article Updated or Audited) | Z6: =_xlfn.TEXTJOIN(CHAR(10), TRUE, E6:G6) -> Request-to-KB publish rate QA feedback cycle rate QA calibration consistency rate Knowledge Base audit pass rate QA team lead feedback success rate Cost per QA Evaluation ($ per Evaluation) Cost per KB Article Maintained ($ per Article Updated or Audited) | AA6: =_xlfn.TEXTJOIN(CHAR(10), TRUE, H6:J6)
A7: Kira Hayes | B7: Training & Quality Assurance Coordinator | C7: FTE | D7: > caseing QA > External Knowledge Base articles > Support agent onboarding and training | E7: KB publishing rate | F7: QA evaluation completion rate DSAT and critical violation delivery rate | Z7: =_xlfn.TEXTJOIN(CHAR(10), TRUE, E7:G7) -> KB publishing rate QA evaluation completion rate DSAT and critical violation delivery rate | AA7: =_xlfn.TEXTJOIN(CHAR(10), TRUE, H7:J7)
A8: Matthew Smith | B8: Technical Support Manager | C8: FTE | D8: > Inbound tech support lead | E8: Tech support case resolution rate | G8: Tech support costs | H8: Autonomy rate for tech support cases | Z8: =_xlfn.TEXTJOIN(CHAR(10), TRUE, E8:G8) -> Tech support case resolution rate Tech support costs | AA8: =_xlfn.TEXTJOIN(CHAR(10), TRUE, H8:J8) -> Autonomy rate for tech support cases
A9: Colby Warner | B9: Product Support Engineer | C9: FTE | D9: > Tech support troubleshooting & resolution | E9: Escalated case resolution rate | F9: Tech Support case QA Tech Support case CSAT Tech Support case first contract resolution | Z9: =_xlfn.TEXTJOIN(CHAR(10), TRUE, E9:G9) -> Escalated case resolution rate Tech Support case QA Tech Support case CSAT Tech Support case first contract resolution | AA9: =_xlfn.TEXTJOIN(CHAR(10), TRUE, H9:J9)
A10: Kari Johnson | B10: Registrar | C10: FTE | D10: > Registration and Records lead > Academic record maintenance > Block/Term system and catalog data publishing | G10: Registrar budget | H10: Autonomy for registrar processes Autonomy for registrar cases | I10: Case CSAT for planning and registration | Z10: =_xlfn.TEXTJOIN(CHAR(10), TRUE, E10:G10) -> Registrar budget | AA10: =_xlfn.TEXTJOIN(CHAR(10), TRUE, H10:J10) -> Autonomy for registrar processes Autonomy for registrar cases Case CSAT for planning and registration
A11: Kim Overdiek | B11: Associate Registrar | C11: FTE | D11: > Policies & processes > Curriculum/catalog maintenance > Academic planning system configuration > Course registration process | E11: Process case resolution rate On-time catalog publishing rate On-time system configuration rate | F11: Process case QA Process case CSAT | Z11: =_xlfn.TEXTJOIN(CHAR(10), TRUE, E11:G11) -> Process case resolution rate On-time catalog publishing rate On-time system configuration rate Process case QA Process case CSAT | AA11: =_xlfn.TEXTJOIN(CHAR(10), TRUE, H11:J11)
A12: Tyson Bell | B12: Associate Registrar | C12: FTE | D12: > Student records >Transcripts >Graduation >Enrollment verification | E12: Records case resolution rate | F12: Records case QA Records case CSAT | Z12: =_xlfn.TEXTJOIN(CHAR(10), TRUE, E12:G12) -> Records case resolution rate Records case QA Records case CSAT | AA12: =_xlfn.TEXTJOIN(CHAR(10), TRUE, H12:J12)
A13: Angie Holt | B13: Graduation Coordinator | C13: Full-Time Contractor | D13: > Graduation application > Diploma awarding process | E13: Graduation application case completion rate Award processing rate | F13: Number of Rescinded Degrees Application QA Awarding QA | Z13: =_xlfn.TEXTJOIN(CHAR(10), TRUE, E13:G13) -> Graduation application case completion rate Award processing rate Number of Rescinded Degrees Application QA Awarding QA | AA13: =_xlfn.TEXTJOIN(CHAR(10), TRUE, H13:J13)
A14: Anne E. Owen | B14: Records & Transcript Coordinator | C14: FTE | D14: > Grade changes > Academic exceptions > Transcript requests | E14: Process case completion rate | F14: Process case CSAT Process case QA Transcript accuracy QA | Z14: =_xlfn.TEXTJOIN(CHAR(10), TRUE, E14:G14) -> Process case completion rate Process case CSAT Process case QA Transcript accuracy QA | AA14: =_xlfn.TEXTJOIN(CHAR(10), TRUE, H14:J14)
A15: Cindi C Putnam | B15: Planning Coordinator | C15: FTE | D15: > Degree progress audit corrections | E15: Degree planning escalation case resolution rate | F15: Degree planning escalation case CSAT Degree planning escalation case QA | Z15: =_xlfn.TEXTJOIN(CHAR(10), TRUE, E15:G15) -> Degree planning escalation case resolution rate Degree planning escalation case CSAT Degree planning escalation case QA | AA15: =_xlfn.TEXTJOIN(CHAR(10), TRUE, H15:J15)
A16: Nikki Jane Chambers | B16: Enrollment Verification Specialist | C16: FTT | D16: > Enrollment verification > Partner transfer evaluation > Apostilles > Student verification letters | E16: Enrollment verification completion rate Apostille completion rate | F16: Enrollment verification QA Apostille QA Enrollment verification CSAT Apostille C-Sat | Z16: =_xlfn.TEXTJOIN(CHAR(10), TRUE, E16:G16) -> Enrollment verification completion rate Apostille completion rate Enrollment verification QA Apostille QA Enrollment verification CSAT Apostille C-Sat | AA16: =_xlfn.TEXTJOIN(CHAR(10), TRUE, H16:J16)
A17: Daniel Zago | B17: Registration Specialist | C17: Contractor | D17: > Registration user testing > Registration support > Manual registration projects | E17: Registration issue case resolution rate | F17: Registration issue case QA Registration issue case CSAT | Z17: =_xlfn.TEXTJOIN(CHAR(10), TRUE, E17:G17) -> Registration issue case resolution rate Registration issue case QA Registration issue case CSAT | AA17: =_xlfn.TEXTJOIN(CHAR(10), TRUE, H17:J17)
Z18: =_xlfn.TEXTJOIN(" | ", TRUE, E18:J18)
Z19: =_xlfn.TEXTJOIN(" | ", TRUE, E19:J19)
Z20: =_xlfn.TEXTJOIN(" | ", TRUE, E20:J20)
Z21: =_xlfn.TEXTJOIN(" | ", TRUE, E21:J21)
Z22: =_xlfn.TEXTJOIN(" | ", TRUE, E22:J22)
Z23: =_xlfn.TEXTJOIN(" | ", TRUE, E23:J23)
Z24: =_xlfn.TEXTJOIN(" | ", TRUE, E24:J24)
Z25: =_xlfn.TEXTJOIN(" | ", TRUE, E25:J25)
Z26: =_xlfn.TEXTJOIN(" | ", TRUE, E26:J26)
Z27: =_xlfn.TEXTJOIN(" | ", TRUE, E27:J27)
Z28: =_xlfn.TEXTJOIN(" | ", TRUE, E28:J28)
Z29: =_xlfn.TEXTJOIN(" | ", TRUE, E29:J29)
Z30: =_xlfn.TEXTJOIN(" | ", TRUE, E30:J30)

Sheet Records, Registration, Support 
A1: Employee Information | E1: Operational Outcomes | H1: Student Outcomes
A2: Employee Name | B2: Name | C2: Employment Status | D2: Stewardship | E2: Speed | F2: Quality | G2: Cost | H2: Student Autonomy | I2: Student Satisfaction | J2: Completion
A3: Mark Gefrom | B3: Director of Student Support | C3: FTE | D3: > Registrar, student support, Tech support oversight > Help center > Customer relations systems > Case systems | E3: Teams meeting or exceeding response service-level agreements Teams meeting or exceeding resolution service-level agreements | F3: Teams meeting QA service-level agreements Teams meeting CSAT service-level agreements Teams meeting first contact resolution service-level agreements | G3: Student records, registration, and support department budget | H3: Overall student autonomy (primary) | I3: Overall student satisfaction (secondary) | Z3: =_xlfn.TEXTJOIN(CHAR(10), TRUE, E3:G3) -> Teams meeting or exceeding response service-level agreements Teams meeting or exceeding resolution service-level agreements Teams meeting QA service-level agreements Teams meeting CSAT service-level agreements Teams meeting first contact resolution service-level agreements Student records, registration, and support department budget | AA3: =_xlfn.TEXTJOIN(CHAR(10), TRUE, H3:J3) -> Overall student autonomy (primary) Overall student satisfaction (secondary)
A4: Brad Lester | B4: Senior Manager of Student Support | C4: FTE | D4: > Inbound student support lead > Academic advising program | E4: Student support case response rates Student support case resolution rates | F4: Student support QA Student support CSAT Student support first contact resolution | G4: Student support budget | H4: Autonomy rate for student support cases | Z4: =_xlfn.TEXTJOIN(CHAR(10), TRUE, E4:G4) -> Student support case response rates Student support case resolution rates Student support QA Student support CSAT Student support first contact resolution Student support budget | AA4: =_xlfn.TEXTJOIN(CHAR(10), TRUE, H4:J4) -> Autonomy rate for student support cases
A5: Alyssa Burrell | B5: Student Support Coordinator | C5: FTE | D5: > Phone support > General support | E5: General support case response rate General support case resolution rate Phone answer Speed Phone handle rate Agent availability | F5: Phone support QA Phone support CSAT Phone upport first contanct resolution | G5: Phone support costs | Z5: =_xlfn.TEXTJOIN(CHAR(10), TRUE, E5:G5) -> General support case response rate General support case resolution rate Phone answer Speed Phone handle rate Agent availability Phone support QA Phone support CSAT Phone upport first contanct resolution Phone support costs | AA5: =_xlfn.TEXTJOIN(CHAR(10), TRUE, H5:J5)
A6: Hilary Bagley | B6: Training & Quality Assurance Manager | C6: FTE | D6: > Training, area collaboration, & partner communication > Media & Knowledge Base development > Student Support content accuracy > Student journey mapping | E6: Request-to-KB publish rate QA feedback cycle rate | F6: QA calibration consistency rate Knowledge Base audit pass rate QA team lead feedback success rate | G6: Cost per QA Evaluation ($ per Evaluation) Cost per KB Article Maintained ($ per Article Updated or Audited) | Z6: =_xlfn.TEXTJOIN(CHAR(10), TRUE, E6:G6) -> Request-to-KB publish rate QA feedback cycle rate QA calibration consistency rate Knowledge Base audit pass rate QA team lead feedback success rate Cost per QA Evaluation ($ per Evaluation) Cost per KB Article Maintained ($ per Article Updated or Audited) | AA6: =_xlfn.TEXTJOIN(CHAR(10), TRUE, H6:J6)
A7: Kira Hayes | B7: Training & Quality Assurance Coordinator | C7: FTE | D7: > caseing QA > External Knowledge Base articles > Support agent onboarding and training | E7: KB publishing rate | F7: QA evaluation completion rate DSAT and critical violation delivery rate | G7: QA Team Costs Knowledge Base (KB) Team Costs | Z7: =_xlfn.TEXTJOIN(CHAR(10), TRUE, E7:G7) -> KB publishing rate QA evaluation completion rate DSAT and critical violation delivery rate QA Team Costs Knowledge Base (KB) Team Costs | AA7: =_xlfn.TEXTJOIN(CHAR(10), TRUE, H7:J7)
A8: Matthew Smith | B8: Technical Support Manager | C8: FTE | D8: > Inbound tech support lead | E8: Tech support case resolution rate | F8: Tech Support case QA Tech Support case CSAT Tech Support case first contract resolution | G8: Tech support costs | H8: Autonomy rate for tech support cases | Z8: =_xlfn.TEXTJOIN(CHAR(10), TRUE, E8:G8) -> Tech support case resolution rate Tech Support case QA Tech Support case CSAT Tech Support case first contract resolution Tech support costs | AA8: =_xlfn.TEXTJOIN(CHAR(10), TRUE, H8:J8) -> Autonomy rate for tech support cases
A9: Colby Warner | B9: Product Support Engineer | C9: FTE | D9: > Tech support troubleshooting & resolution | E9: Escalated case resolution rate Tech support case response rate | F9: Tech Support case QA Tech Support case CSAT Tech Support case first contract resolution | Z9: =_xlfn.TEXTJOIN(CHAR(10), TRUE, E9:G9) -> Escalated case resolution rate Tech support case response rate Tech Support case QA Tech Support case CSAT Tech Support case first contract resolution | AA9: =_xlfn.TEXTJOIN(CHAR(10), TRUE, H9:J9)
A10: Kari Johnson | B10: Registrar | C10: FTE | D10: > Registration and Records lead > Academic record maintenance > Block/Term system and catalog data publishing | E10: Registrar process resolution rate Registrar case resolution rate | F10: CSAT for registrar processes CSAT for registrar cases | G10: Registrar budget | H10: Autonomy for registrar processes Autonomy for registrar cases | I10: Case C-Sat for planning and registration | Z10: =_xlfn.TEXTJOIN(CHAR(10), TRUE, E10:G10) -> Registrar process resolution rate Registrar case resolution rate CSAT for registrar processes CSAT for registrar cases Registrar budget | AA10: =_xlfn.TEXTJOIN(CHAR(10), TRUE, H10:J10) -> Autonomy for registrar processes Autonomy for registrar cases Case C-Sat for planning and registration
A11: Kim Overdiek | B11: Associate Registrar | C11: FTE | D11: > Policies & processes > Curriculum/catalog maintenance > Academic planning system configuration > Course registration process | E11: Process case resolution rate On-time catalog publishing rate On-time system configuration rate | F11: Process case QA Process case CSAT Score | G11: Planning and registration team costs | Z11: =_xlfn.TEXTJOIN(CHAR(10), TRUE, E11:G11) -> Process case resolution rate On-time catalog publishing rate On-time system configuration rate Process case QA Process case CSAT Score Planning and registration team costs | AA11: =_xlfn.TEXTJOIN(CHAR(10), TRUE, H11:J11)
A12: Tyson Bell | B12: Associate Registrar | C12: FTE | D12: > Student records >Transcripts >Graduation >Enrollment verification | E12: Records case resolution rate | F12: Records case QA Records case CSAT | G12: Records team costs | Z12: =_xlfn.TEXTJOIN(CHAR(10), TRUE, E12:G12) -> Records case resolution rate Records case QA Records case CSAT Records team costs | AA12: =_xlfn.TEXTJOIN(CHAR(10), TRUE, H12:J12)
A13: Geraldine Susan Bean | B13: Graduation Coordinator | C13: FTE | D13: > Graduation application > Diploma awarding process | E13: Graduation application case completion rate Award processing rate | F13: Number of Rescinded Degrees Application QA Awarding QA | G13: Graduation team costs | Z13: =_xlfn.TEXTJOIN(CHAR(10), TRUE, E13:G13) -> Graduation application case completion rate Award processing rate Number of Rescinded Degrees Application QA Awarding QA Graduation team costs | AA13: =_xlfn.TEXTJOIN(CHAR(10), TRUE, H13:J13)
A14: Anne E. Owen | B14: Records & Transcript Coordinator | C14: FTE | D14: > Grade changes > Academic exceptions > Transcript requests | E14: Process case completion rate | F14: Process case CSAT Process case QA Transcript Accuracy QA | G14: Process team costs | Z14: =_xlfn.TEXTJOIN(CHAR(10), TRUE, E14:G14) -> Process case completion rate Process case CSAT Process case QA Transcript Accuracy QA Process team costs | AA14: =_xlfn.TEXTJOIN(CHAR(10), TRUE, H14:J14)
A15: Cindi C Putnam | B15: Planning Coordinator | C15: FTE | D15: > Degree progress audit corrections | E15: Degree planning escalation case resolution rate | F15: Degree Planning Escalation case CSAT Score Degree Planning Escalation case QA Score | G15: Degree planning team costs | Z15: =_xlfn.TEXTJOIN(CHAR(10), TRUE, E15:G15) -> Degree planning escalation case resolution rate Degree Planning Escalation case CSAT Score Degree Planning Escalation case QA Score Degree planning team costs | AA15: =_xlfn.TEXTJOIN(CHAR(10), TRUE, H15:J15)
A16: Nikki Jane Chambers | B16: Enrollment Verification Specialist | C16: FTT | D16: > Enrollment verification > Partner transfer evaluation > Apostilles > Student verification letters | E16: Enrollment verification completion rate Apostille completion rate | F16: Enrollment verification QA Apostille QA Enrollment verification CSAT Apostille C-Sat | G16: Enrollment verification team costs | Z16: =_xlfn.TEXTJOIN(CHAR(10), TRUE, E16:G16) -> Enrollment verification completion rate Apostille completion rate Enrollment verification QA Apostille QA Enrollment verification CSAT Apostille C-Sat Enrollment verification team costs | AA16: =_xlfn.TEXTJOIN(CHAR(10), TRUE, H16:J16)
A17: Angie Holt | B17: Registration Specialist | C17: Contractor | D17: > Registration user testing > Registration support > Manual registration projects | E17: Registration issue case resolution rate | F17: Registration issue case QA Registration issue case CSAT | G17: Registration team costs | Z17: =_xlfn.TEXTJOIN(CHAR(10), TRUE, E17:G17) -> Registration issue case resolution rate Registration issue case QA Registration issue case CSAT Registration team costs | AA17: =_xlfn.TEXTJOIN(CHAR(10), TRUE, H17:J17)
Z18: =_xlfn.TEXTJOIN(" | ", TRUE, E18:J18)
Z19: =_xlfn.TEXTJOIN(" | ", TRUE, E19:J19)
Z20: =_xlfn.TEXTJOIN(" | ", TRUE, E20:J20)
Z21: =_xlfn.TEXTJOIN(" | ", TRUE, E21:J21)
Z22: =_xlfn.TEXTJOIN(" | ", TRUE, E22:J22)
Z23: =_xlfn.TEXTJOIN(" | ", TRUE, E23:J23)
Z24: =_xlfn.TEXTJOIN(" | ", TRUE, E24:J24)
Z25: =_xlfn.TEXTJOIN(" | ", TRUE, E25:J25)
Z26: =_xlfn.TEXTJOIN(" | ", TRUE, E26:J26)
Z27: =_xlfn.TEXTJOIN(" | ", TRUE, E27:J27)
Z28: =_xlfn.TEXTJOIN(" | ", TRUE, E28:J28)
Z29: =_xlfn.TEXTJOIN(" | ", TRUE, E29:J29)
Z30: =_xlfn.TEXTJOIN(" | ", TRUE, E30:J30)

Sheet 2025 Baseline KPIs
A1: Employee Name | B1: Role | C1: Department | D1: Scheduling | E1: Key Responsibilities | F1: Current Projects (If Any) | G1: Conditions for Success | H1: Current KPIs | I1: Suggested KPIs | J1: Data Source | K1: Timeframe | L1: Ben's Thought
A2: Steven K. Thomas | B2: Dean of Students | C2: DOS | D2: Complete | E2: > Provide executive-level and strategic leadership for all six DOS Office service areas (Student Honor & Conduct; Accessibility; Belonging; Grievances; Sexual Misconduct/Title IX; Students in Crisis). > Title IX Coordinator and ADA/Sec. 504 Coordinator for the institution. > Set vision, strategic direction, and institutional alignment for the DOS Office across BYU-Pathway Worldwide’s global student body. > Lead policy development, cross-institutional coordination, and executive-level stakeholder collaboration (BYU-Idaho, Ensign College, ICS/IT, GEO, Digital Ops, etc.). > Oversee crisis-response strategy, including escalation frameworks, global monitoring, partner communication pathways, and institutional student-safety protocols. > Direct development and implementation of DOS Office reporting dashboards, analytics tools, and annual reports. > Steward DOS Office staffing, operational budget, contractor strategy, and technological modernization initiatives. > Represent the DOS Office in executive councils, SSEC, cross-institutional committees, accreditation-related efforts, and Student Success imperatives. | F2: > Student Crisis Portfolio development > Multi-Language Program (MLP) DOS Office implementation roadmap > DOS Partner Resource Portal (policies, workflows, referral processes) > DOS Office Annual Report design and launch (impact, case data, findings, predictive insights) > Technological innovation initiatives supported by ITD funding > Companion App feature expansion across all six services areas (Accessibility workflows, case intake, etc.). > Executive Secretary/Project Manager onboarding and integration > Data standardization with Digital Ops (DOS Office Power BI Dashboard) | G2: > DOS Office processes standardized globally with clear escalation pathways > Accurate, timely DOS Office dashboards for all six service areas > Strong cross-institutional alignment with partner schools and internal departments > Student trust and case-resolution consistency across regions > Effective utilization of Digital Ops, Springboard teams, and contractor talent > Documented, scalable procedures usable at 190+ country scale | H2: > Successful decoupling from partner institutions across all six DOS Office service areas. | I2: High-Level Strategic / Executive Focus 1. Operational Clarity & Scalability • Complete DOS Office Position Descriptions, Success Measures, and full process documentation across all six service areas. • Finalize succession plans for critical roles. • Validate and deliver scalability plans to support future growth to 1 million students. 2. Stakeholder & Student Satisfaction • Implement quarterly CSAT surveys for internal and external partners. • Launch post-interaction student CSAT surveys across service areas and integrate results into dashboards. • Demonstrate measurable increases in partner trust and clarity with DOS processes. 3. Cross-Institutional Collaboration & Alignment • Ensure DOS-chaired committees produce documented outcomes and alignment with partner institutions. • Strengthen year-round collaboration and communication with institutional partners. • Improve system health and reduce friction across shared processes. 4. High-Quality, Scalable Performance • Achieve student satisfaction with DOS services at or above 80%. • Resolve 90%+ of DOS tickets within 5 days (excluding Title IX/Sexual Misconduct timelines). • Demonstrate dashboard readiness and data accuracy for all service areas. 5. Retention & Completion Impact • Establish realistic retention and completion benchmarks for students who receive DOS Office services. | J2: > Power BI dashboards (DOS service areas) > Adobe Analytics (student behavior and case-flow insights) > Digital Ops data pipelines > Crisis monitoring systems and global intelligence feeds > Companion App and REACH/CRM case records | K2: Ongoing – Block, Quarterly, and Annual Reporting Cycles
A3: Anne Marie Clark | B3: Associate Dean of Students | C3: DOS | D3: Complete | E3: > Provide operational leadership and oversight for DOS Office teams and service areas. > Deputy Title IX Coordinator and Duputy ADA/Sec. 504 Coordinator for the institution. > Lead day-to-day coordination of policies, case management practices, instructor support workflows, and DOS Office procedural alignment. > Ensure consistency and accuracy in case handling, documentation, student communication, and compliance across all six service areas. > Oversee cross-departmental coordination with Enrollment Counseling, Mentoring, Support & Services, and Digital Ops. > Support implementation of DOS dashboards, data-cleaning initiatives, and service-area reporting. > Manage sensitive and escalated student cases; provide counsel to internal partners and managers. > Lead workforce training for policies, referral workflows, and crisis-scenario readiness. > Support development of the DOS Partner Resource Portal and Annual DOS Office Report. | F3: > DOS Office case-practice standardization and documentation > Internal and partner-facing student crisis-response guidance and escalation pathways > DOS dashboards data-accuracy initiative with Digital Ops > Policies and workflow alignment for internal staff and partner instituitions > Support & Services escalation improvement initiative > Annual DOS Office Report (data, narrative, outcomes) | G3: > Clean, reliable, and consistently entered DOS Office data > Clear and documented processes for internal staff and external partners > Strengthened relationships with partner schools and internal stakeholders > Reduced student touchpoints and faster resolution timelines > Improved operational accuracy and consistency across case managers and coordinators | H3: > Efficient and effective case resolution across all six DOS Office service areas. | I3: Operational / Execution Focus 1. Process Fidelity & Documentation • Maintain service-area Standard Operational Procedures (SOPs), escalation guides, and workflow documentation. • Achieve 100% implementation of updated processes within established timelines. 2. Case Quality & Consistency • Maintain 90%+ accuracy in case documentation and data entry. • Reduce procedural errors and repeat student contacts. • Ensure consistent adherence to policy and procedural standards. 3. Ticket Resolution & Service Performance • Resolve 85–90% of tickets within defined timelines (within 5 days for non-Title IX cases). • Reduce Support & Services delays impacting DOS cases. 4. Dashboard & Data Reliability • Conduct weekly data-quality verification (accuracy, completeness, consistency). • Meet dashboard-readiness milestones in partnership with Digital Ops. 5. Stakeholder Communication & Alignment • Maintain positive feedback from Instructors, GEO, Communications, and partner institutions. • Deliver quarterly updates to partner institutions and cross-departmental teams on schedule. 6. Training & Readiness • Ensure 100% of instructors, mentors, internal staff, and partners are trained in revised escalation and crisis-response processes. • Improve partner understanding of DOS procedures as reflected in CSAT and quarterly reviews. 7. Student & Partner Satisfaction Implementation • Execute student and partner CSAT survey distribution. • Monitor response trends and apply insights into operational improvements. | J3: > Power BI dashboards (DOS service areas) > Adobe Analytics (student behavior and case-flow insights) > Digital Ops data pipelines > Crisis monitoring systems and global intelligence feeds > Companion App and REACH/CRM case records | K3: Ongoing – Block, Quarterly, and Annual Reporting Cycles
A4: Katelyn Ray | B4: Student Honor & Grievance Coordinator | C4: DOS | D4: Complete | E4: > Place Holds on Student Accounts > Scheduled Phone calls with Disgruntled students > Grievances weekly team meeting > Enroll students in Academic Integrity Course > Coordination with BYU-I & Ensign Honor Offices > DOS weekly team meeting > Compile data regarding trends for grievances for past week/month > Manage the Navigating Academic Honesty course on Canvas | F4: Student honor and conduct committee Co-chair Adding AI section to Navigating Academic Honesty course on Canvas | G4: Tracks student honor violations and ensures that appropriate action is taken in each case to resolve the concern in accordance with our institution policies. Ensure a strong relationship with BYU-I & Ensign Honor Offices Maintain open communication and strong relationship with instructional teams to streamline violation processing. | H4: Number of cases received - tracked Number of repeat offender - tracked Case age, 5 days or less - 90% | I4: CSAT - Students | J4: > Power BI dashboards (DOS service areas) > Adobe Analytics (student behavior and case-flow insights) > Digital Ops data pipelines > Crisis monitoring systems and global intelligence feeds > Companion App and REACH/CRM case records | K4: Weekly
A5: Alison Cundiff | B5: Director of Enrollment & Retention | C5: Enrollment & Retention | D5: Pending - Extended to Friday Dec 5th | E5: > Oversee the Enrollment Counselling and Mentoring teams: >> 1:1s >> Team meetings >> Long-Term planning to meet Student Success and Organizational objectives > Oversee student throughput across the student journey/pipeline >> Milestones >> Dashboards >> AI/Human intervention strategies > Report on progress in weekly 1:1 with the VP of Student Success. > Represent EC and Mentoring in daily, weekly, and monthly cross-functional meetings related to registration. > Prepare agendas and facilitate the Retention Council, various workgroup participation | F5: Retention Council (Chair) Orientation, Analytics Engine Workgroup (Chair) Enrollment & Retention Suite dashboard project w/ Dallin Milestone map project EC3 Mentor exploration CARE Committee (participant) CES Student Success Committee (participant) Companion Implementation Taskforce (participant) Advising Committee (participant) | G5: Mentoring is functioning optimally, mentor role is clear, and students know how to reach their mentor. Enrollment Counseling is functioning optimally, and that we have the right intervention model set up to increase yield rates from Application to Registration. Teams have all the resources (access to data, systems) needed to perform their roles in a paced and effective way. We are aligned across the organization on the primary persistence and retention measurements and are consistently making progress on them from term to term, year to year. | H5: EC RA completion 95% average Mentor CSAT - 85% average Mentor RA Implementation - 90% completion Mentor Scorecard (Quality) - 85% average PC Completion: 45% C&D 4-Term Retention: 55% C1 Completion: 40% | I5: None | J5: > https://app.fabric.microsoft.com/groups/4f9c84ba-b5d3-4eda-a86b-41fbb3b3bc4a/reports/d0f58bce-3a7d-49b6-80a3-eade14ab09fc/e3ff97a21eaacb03dbca?experience=fabric-developer&clientSideAuth=0 > https://app.powerbi.com/groups/me/reports/7177fab9-23b0-4184-8f31-f0db822282c0/ReportSection964c860de430a5035bab?ctid=61e6eeb3-5fd7-4aaa-ae3c-61e8deb09b79&experience=power-bi > https://app.powerbi.com/groups/4f9c84ba-b5d3-4eda-a86b-41fbb3b3bc4a/reports/8b8c6aa8-361e-4ed7-8018-ac9b625ec004/51439a40d9bbc658cac9?experience=power-bi > https://app.powerbi.com/groups/4f9c84ba-b5d3-4eda-a86b-41fbb3b3bc4a/reports/e2b5b9d8-0b16-4185-9213-61b41d61c157/40663d76a0ae8a192407?experience=power-bi | K5: Weekly, Monthly, and By Term
A6: Rachel Kirk | B6: Enrollment Counseling Manager | C6: Enrollment & Retention | D6: Complete | E6: > Supporting my team and escalating complicated issues (50%) > Cross-departmental collaboration (15%) > Planning targeted outreach (10%) > Monitoring enrollment counseling effectiveness/performance (10%) > Planning and Requesting optimization to our tools (5%) > Synthesize and present results of key initiatives and team performance to senior leadership (10%) | F6: New Student Orientation Workgroup | G6: Ensuring that the EC team is functioning effectively and supporting students Planning RAs and outreach Tracking tool efficacy and ensuring tool repair and updates | H6: RA completion 95% average | I6: EC CSAT 85% average - New metric being tracked | J6: > https://app.fabric.microsoft.com/groups/4f9c84ba-b5d3-4eda-a86b-41fbb3b3bc4a/reports/d0f58bce-3a7d-49b6-80a3-eade14ab09fc/e3ff97a21eaacb03dbca?experience=fabric-developer&clientSideAuth=0 > https://app.powerbi.com/groups/me/reports/7177fab9-23b0-4184-8f31-f0db822282c0/ReportSection964c860de430a5035bab?ctid=61e6eeb3-5fd7-4aaa-ae3c-61e8deb09b79&experience=power-bi | K6: Weekly
A7: Kelley Richardson | B7: Mentoring Manager | C7: Enrollment & Retention | D7: Complete | E7: > Implement the Mentoring Strategy > CRM needs and adjustments > Oversee Mentor & Evaluator training sessions > Supply guides and Required Action Implementation to standardize and inform Mentors regarding changes made and process updates. > Build and maintain the mentor scorecard model. > Implement and quality assure items in Mentoring such as Case Management and Mentor Interaction with students (timing, frequency, and quality). | F7: MLP Portuguese Pilot mentors EC3 Project Pilot mentor update | G7: Mentoring strategy is being implemented successfully. Mentors & Evaluators trainings are provided to Springboard before new items are expected to be implemented. Mentor guides & RA guides are provided and updated as needed. Mentor Evaluation updates are delivered regularly | H7: Mentor CSAT - 85% average RA Implementation - 90% completion Scorecard (Quality) - 85% average | I7: None | J7: https://app.powerbi.com/groups/4f9c84ba-b5d3-4eda-a86b-41fbb3b3bc4a/reports/8b8c6aa8-361e-4ed7-8018-ac9b625ec004/51439a40d9bbc658cac9?experience=power-bi https://app.powerbi.com/groups/4f9c84ba-b5d3-4eda-a86b-41fbb3b3bc4a/reports/e2b5b9d8-0b16-4185-9213-61b41d61c157/40663d76a0ae8a192407?experience=power-bi | K7: Weekly & by Term
A8: Jacob Adams | B8: Director of Digital Operations | C8: Digital Ops | D8: Complete | E8: > Strategic discernment of analytics engine (backend) and Companion/Mentor portal (frontend) feature alignment, development, and maintenance to scale to millions of students in multiple languages with the best of AI and human relationship-based intervention. > Daily/weekly scrum meetings with human role applications on behalf of students aligned with analytics engine with Companion, PowerBI, and machine learning and agentic AI teams. > Review non-linear and linear UX impacts and results. | F8: None | G8: Digital Ops projects are progressing on time and completed project meet their requirements. Stakeholder approval with high satisfaction. | H8: None | I8: 85% CSAT in Companion 100% uptime (0% P1s) with clear pro-active maintenance windows communicated to students and stakeholders Each prompt/answer in Companion 98% QA accurate/relevant/ethical/accountable separated by feature (i.e. jobs, course assistant, Versant prep assistant, etc.) Simulate results for stability in Azure with 1 million students in Spanish, Portuguese, French, English (i.e. 98% accuracy, 100% uptime, 3% milestone achievement over predicted) Predictive model accuracy 92% on average for each micro-milestone | J8: PowerBI Azure chat transcript tables Microsoft Application Insights Azure notebooks | K8: > CSAT and Uptime - daily > QA weekly
A9: Ricky Kailiponi Jr. | B9: Senior Manager of Digital Ops | C9: Digital Ops | D9: Complete | E9: > Collaborate with IT and ICS partners, including solution managers Kyle C. and Jeff Van Drimmelen, product managers Dustin Waith (Registration), Cary Johnson (formerly EC3), Johanna Powell (Admissions), Mike Hilmo (Finance/Gatherings), and Chad Neth (Reach), and ICS developers Bob Capel and Gordon Young (Reach/D365). > Work closely with portfolio architect Dennis Kiesel and various ICS engineers supporting Azure and AI services. > Hold weekly team meetings and 1:1s with each manager to maintain alignment and support individual well-being, performance, and growth. > Weekly development and development QA with managers. > Meet with ICS contacts specifically related to AI initiatives. These meetings ensure compliance with security protocols and help secure the support needed to advance our work. | G9: High engagement and alignment with stakeholders and team Strong cross-team collaboration with IT and ICS partners Timely delivery of AI-related initiatives Effective QA and development with managers | H9: 90% or better of projects delivered on time and within scope across our team (Overall execution and alignment with org priorities) 85% or better stakeholder satisfaction score (Effectiveness of collaboration and communication at an operational level) 80% or better engagement score from quarterly team surveys or retention metrics (Leadership quality and team stability) One or more of our AI initiatives successfully integrated into business processes per quarter (Strategic contribution to modernization and innovation) | I9: None | J9: None | K9: Quarterly & Biannually
A10: Dezjaron Dorsey | B10: AI Manager | C10: Digital Ops | D10: Complete | E10: > Track project progression > Manage team through 1on1s and team meetings > Source solutions to unfolding project challenges > Build AI/ML Architecture > Build data model > Weekly reporting meetings > Maintain and manage >> Azure Developers board >> GitHub Repos >> Azure DevOps Pipelines | F10: Course Assistant Fluency Assistant Companion Assistant (different from Native) Grader Assistant Data Model | G10: Ensure Digital Ops final products can be used successfully by the end users. Ensure feedback and improvement backends are built into projects so they can be monitored and maintained. Projects are updated and improved as needed to keep them functioning optimally. | H10: None | I10: None
A11: Mark Gefrom | B11: Director of Student Support | C11: Student Support | D11: Pending | E11: > Ensuring the path for students to get help is clear and easy by promoting the use of the Help Center > Ticket management systems are configured properly to allow us to effectively record, categorize, and quantify inbound ticket traffic > Promoting ongoing employee coaching and development > Internal knowledge articles are in place to guide agents on how to help students and know what internal processes to follow > External knowledge articles are in place on the Help Center to address common questions/issues for students > Balancing efficiency and quality (CSAT surveys, First Contact Resolution, and QA Evaluations) as it pertains to ticket handling > Identifying, quantifying, and escalating system bugs for Product Managers and ICS to work on permanent fixes > Identifying ticket trends which are negatively impacting students. This includes working with other departments to reduce escalations by training and empowering our agents > Handling VIP and escalated support issues > Addressing team and employee performance issues | F11: Ticket Task Force | G11: Ensure that the Help Center is fully operational and the path for students to get support is clear and reliable. All agents QA’d and given feedback monthly. Ticket systems are running optimally and students are receiving high quality support. | H11: 24 hour Response Time 48 hour Resolution Time 90% of tickets resolved within 5 days 95% First Contact Resolution 30 second wait time to speak with an agent (Phone Support) 80% agent availability to take calls (Phone Support) 20 minute average talk time (Phone Support) 60% resolution rate (Phone Support) 90% CSAT All agents QA’d and given feedback monthly | I11: None | J11: Power BI Dashboards | K11: Weekly & Monthly
A12: Brad Lester | B12: General Support Manager | C12: Student Support | D12: Complete | E12: Team Oversight & Check-ins > Run weekly team meetings or stand-ups to align priorities. > Conduct 1:1 check-ins with direct reports. > Monitor workload distribution and adjust assignments. Operational Monitoring > Review open support cases/tickets, escalations, or backlog. Issue Resolution & Escalation > Address customer or stakeholder escalations. > Troubleshoot recurring issues with processes, tools, or systems. Performance Tracking > Review weekly KPIs (e.g., response times, customer satisfaction). > Identify early trends and areas needing quick correction. Communication & Coordination > Update leadership on support trends or risks. > Share policy/process updates with the team. > Coordinate with other departments to resolve cross-functional issues. Team Development > Provide ongoing coaching or feedback. > Reinforce best practices and standard procedures. | F12: Advisor Workgroup New Registration Workgroup | G12: Queue Health: > Ensure that ticket queues are turning over and cases are being resolved in a timely manner. > Diagnose ticket issues to ensure cases are in the correct queues. Ensure that escalated cases are sent to the correct teams. Maintain infrastructure health and request software updates as needed. Plan and implement team development and ongoing training consistently. Use KPIs to identify agents that need additional training and focus. | H12: Ticket resolutions per day - as high as possible Average response time in hours - as low as possible Average resolution time - 3 days or less First contact resolution rate - 90% average CSAT - 90% average Quality assurance - 95% average | J12: https://app.powerbi.com/groups/4f9c84ba-b5d3-4eda-a86b-41fbb3b3bc4a/reports/af9ba6b3-8092-4e0c-bb52-4f8903b1b861/b4f5a8a463b9d5aef9c3?experience=power-bi | K12: Weekly & Monthly
A13: Matthew Smith | B13: Technical Support Manager | C13: Student Support | D13: Complete | E13: > Managing and developing the technical support team staff. > Updating key stakeholders on bug/issues. > Coordinating and prioritizing bug/issues based on key factors such as scope/impact/etc. > Responding to VIPs and other staff on issues for urgent matters. > Check and keep our Knowledge Base up to date. > Providing training and sharing knowledge with lower tiers of support to ensure first contact resolution success. | F13: Team Restructure towards efficiency: > Product presentations for each product and assign a member of tech support to each product and get a bi-weekly update of Product Bugs, continued issues, concerns on what needs to get fixed and risks to the product if they aren't fixed. This includes number of tickets and the main issues attached to each. We should have a running PPT that will provide this information to Product Managers. Portal Product Service Reports with Miguel. Get Reporting for each Product Manager. Training, Development, and Access Future: > Refine FTE onboarding > Create student employee onboarding | G13: Tech Support team is functioning effectively and developing towards improving the student experience. Improve knowledge & training for technical support team Provide weekly report on current ticket issues per team Lower user access/merge issues for students: > Identify solutions to prevent students from deleting their user details. > Manage KBs used by Account Management to assist with user account issues | H13: Track average of new KB per month - goal 2 per month per person (6 FT & 1 PT) Improve quality of service offered by Tech Support: > QA ticket scoring 85% > Ticket resolution within 5 days to 90% once escalated to Tech Support > Initial response time within 48 hours once escalated to Tech Support | I13: Add Kira's QA scores to KPIs End-to-end testing if that procedure can be implemented | J13: https://app.powerbi.com/groups/me/reports/f4e772a1-108f-4def-8aa5-c298e2c4eb0a/5bd92746cf75258f9eb1?experience=power-bi | K13: Monthly
A14: Colby Warner | B14: Product Support Engineer | C14: Student Support | D14: Complete | E14: > Resolve student cases. > Coordinate and help resolve any P1 issues. > Write DevOps bugs for ICS as necessary. > Write Knowledge Base articles and provide any necessary training. > Help keep the team running smoothly and efficiently. > Bug testing systems. | F14: Student accounts merging. | G14: Improve knowledge & training for technical support team Provide weekly report on current ticket issues per team Lower user access/merge issues for students: > Identify solutions to prevent students from deleting their user details. > Manage KBs used by Account Management to assist with user account issues. | H14: Create or edit 10 KB articles per month Improve quality of service offered by Tech Support: > QA ticket scoring 85% > Ticket resolution within 5 days to 90% once escalated to Tech Support > Initial response time within 48 hours once escalated to Tech Support Close 40 tickets per week minimum (depending on how many tickets are in the queue) | J14: https://app.powerbi.com/groups/me/reports/f4e772a1-108f-4def-8aa5-c298e2c4eb0a/5bd92746cf75258f9eb1?experience=power-bi | K14: Weekly & Monthly
A15: Kira Hayes | B15: Consistency Coordinator | C15: Student Support | D15: Complete | E15: > Managing the QA team > Managing the External KB team > Ensuring that internal articles get created when Support agents have questions or is missing information when helping students. > Providing reports on how well Support is doing in reference to our QA metrics > Aiding with the staffing needs of student support | F15: > Updating Onboarding Training > Constant QA team training/improvement > Maintaining all employee records across multiple teams for QA/dashboard purposes | G15: Quality Assurance: > Monthly reports are sent to senior leaders on time Onboarding: > New hires are trained within the appropriate time frame to avoid delaying start dates Knowledge Management: > Monthly random auditing of Help Center KB articles (checking for consistency) > Monitoring backlog of internal feedback and new requests awaiting SME responses and sending monthly report to senior leaders | H15: Quality Assurance: > All agents receive at least 3 QAs per month > Team Leaders provide feedback to agents within the same month of the evaluation - 90% goal > 1 consistency monitoring session per week with team > 100% of critical violations sent to team leaders Onboarding: > New hires are trained and ready to take calls within 1 and a half weeks Knowledge Management: > Help Center KB articles published within 48 hours of being requested | I15: None | J15: https://app.powerbi.com/groups/4f9c84ba-b5d3-4eda-a86b-41fbb3b3bc4a/reports/af9ba6b3-8092-4e0c-bb52-4f8903b1b861/1afb91a1da6d47c71041?ctid=61e6eeb3-5fd7-4aaa-ae3c-61e8deb09b79&experience=power-bi | K15: Monthly
A16: Alyssa Burrell | B16: Student Support Coordinator | C16: Student Support | D16: Complete | E16: > Lead and oversee the Phone Support team at BYU-Pathway Worldwide, including domestic student employees and international contractors > Monitor and report weekly metrics and provide training for the team or coach individual agents when goals are not met. > Train Phone Support Leads and assist them in answering agent questions to ensure that accurate information is being always given out > Monitor phone calls to provide feedback to leads, agents, and jump in when necessary > Design and deliver training programs on call center skills such as active listening, de-escalation, FERPA compliance, and escalation procedures > Write and publish Knowledge Base articles specific to the phone support team > Collaborate with other teams and departments to provide student feedback, report errors, and create escalation paths > Act as a key point of escalation for complex or urgent student issues, ensuring timely resolution and communication > Review QA and CSAT scores and assist the leads in providing feedback to agents and the team > Manage domestic student employees time, schedules, and absences | F16: > Adding additional contact methods once ICS is ready > Ongoing training and development for Phone Support Team | G16: This role is successful when the Phone Support team is performing optimally, meeting their goals, and developing their skills. | H16: > Number of Calls Answered - as low as possible, depends on all tools functioning correctly. > Abandoned Rate - under 5% > Caller wait time - no current goal, tracking > Caller handle time - under 20 minutes > Availability - 80% > Resolution Rate - no current goal, tracking > CSAT - 85% > QA Scores - 85% > Case Open Time - under 5 days | I16: None | J16: Student Support Metrics dashboard | K16: Weekly
B17: Director of Student Services | C17: Student Services
A18: Kari Johnson | B18: Registrar | C18: Student Services | D18: Complete | E18: Maintain student academic records and ensure compliance with institutional policies, accreditations standards, and regulations. Oversee the following teams: registration, graduation, enrollment verification and internal transfer credits, records, degree progress audit, and planning. Oversee course registration for each block including manual GEC registration. Manage publishing Block/Term data and EnglishConnect section creation. Oversee the graduation process for each block. Coordinate with various departments and area managers to resolve student record issues. Review data and processes with partner institutions for auditing purposes. Catalog maintenance Oversee academic exceptions committee and weekly meetings. | F18: Ticket Task Force All other projects are contained within the typical functioning of the registrar's office. Single PV Graduation Processing Move Students to new Program Versions Path 1.0 Data Migration Syncing Campus Based Courses and Credentials (BYU-I, Ensign College) GEC Section Management Registration - Matriculation Management Apostille - SAQA and Brazil Blocking transcript ordering from more than one institutuion (BYUPW, BYUI, Ensign) Budgets Catalog - publish new catalog 2026 - Catalog maintenance Companion Implementation Task force Course / Program Teach-out Course section creation colaboration with BYU-Idaho Direct Admits - removing | G18: Constantly improving the student experience. Ensure that all student academic records are accurate, current, and accessible. Provide support and leadership for the registration, graduation, enrolment verification, records, DPA, and planning teams and ensure they are functioning optimally. Provide oversight to ensure all student registration happens efficiently and effectively. Ensure that Block data is published and all needed sections are created in Canvas. Ensure that the graduation process in carried out efficiently and accurately for each block. High employee productivity due to clear direction and leadership. Effective collaboration among team members. | H18: None | I18: Achieve 100% accuracy rate in student academic records. Increase team member task completion rate Ensure Block data is 100% published by due date | J18: None | K18: None
A19: Kim Overdiek | B19: Associate Registrar | C19: Student Services | D19: Complete | E19: > Work on ADO resolution (1 hours) > Review Coursedog proposals for Academic Catalog updates (1 hours) > Make configuration updates in Anthology Student (2 hours) > Meetings to maintain policy and processes for Curriculum, Planning, and Registration (6 to 7 hours) > Assist with manual registration as needed - GEC, Portuguese sections (2 to 3 hours) > Continued testing on current curriculum or configuration updates (2 hours) > Other meetings with team members (1 to 2 hours) > Planning for next day (30 minutes) | F19: Program Plans (Student facing) Program Sheets (Organization facing) | G19: Curriculum is updated and functioning in Anthology to allow for on-time Registration. Ensure that Registration Cleanup data is available and actioned appropriately. Coordinate the Coursedog proposal procedure to ensure that all stakeholders are completing their actions items so curriculum updates can be implemented on time. | H19: None | I19: Configuration Updates Made Each block Catalog Updates Made Each block Team is task goals completed each block | J19: None | K19: TBD
A20: Geraldine Susan Bean | B20: Graduation Coordinator | C20: Student Services | D20: Complete | E20: > Oversee the graduation team as they work through graduation applications and graduation issues. > Personally vet and award credentials each week. > Send orders for paper copies of diplomas. > Take care of escalated students who have not received their credentials for any given reason. > Work with partners to go over any graduation questions or issues they might have. > Work through apostilles for students needing documents certified for use outside of the US (this can include certificates, diplomas, official transcripts, and enrollment verification letters). > Work with communications team to send information about graduation to students. > Work with partner institutions for vetting and auditing lists of graduates, as well as posting final numbers and getting names into the graduation programs. > Work in the configuration to make sure we can send portal alerts for apostille and am working on getting them set up for graduation as well. > Apart from graduation, I am also overseeing the hiring and basic training for the registrar office. | F20: Term 6 Active to Pending Completion Queue (Anthology Student workflow) Term 6 Applications (REACH) Finishing the Ensign Audit from 5/10/2025 Sending grads to the printer weekly | G20: Ample access to resources and training modules Daily team work sessions via zoom Weekly leadership check-ins and trainings Prioritize quality over quantity | H20: Zero incorrect graduations/rescinded degrees. Prioritize quality over quantity All applications submitted before the term deadline will have at least one review before the end of the term, and students will be notified. Every graduate receives two reviews before their graduation is finalized. One at mid-term, and the final review after grades post. Employees process 2-3 graduations or on-track reviews per hour | I20: None | J20: None | K20: Per term
A21: Anne E. Owen | B21: Records & Transcript Coordinator | C21: Student Services | D21: Complete | E21: > Grade Changes: Oversees documentation and processing of grade change requests, reinstatements, and grievance-related updates. > Academic Exceptions: Facilitates exception requests via the Companion Bot, collaborates with institutional partners, and supports the Academic Exceptions Committee. > Transcript Management: Manages manual transcript processing and verification, resolving legacy data issues in partnership with technical teams and institutions. > Transcript Cleanup: Coordinates with Anthology to maintain transcript data integrity through daily issue resolution. > Official Transcript Requests: Ensures compliant handling and delivery of official transcript requests submitted through the Companion Bot. | F21: Transcript Cleanup & Accuracy: Ongoing resolution of legacy data issues in Anthology to ensure accurate transcripts. Academic Exceptions Management: Facilitating committee reviews and improving turnaround times for exception cases. Grade Change Processing: Maintaining accuracy and timeliness for reinstatements and grievance-related updates. Knowledge Base Updates: Regularly refining content based on trends and escalations. Service Performance Reporting: Weekly tracking agent outcomes and service trends for Springboard collaboration. | G21: System Stability: Reduced SIS bugs and improved Anthology functionality for transcript processing. Cross-Team Collaboration: Timely communication with BYU–Idaho, Ensign College, and Anthology partners. Clear SOPs: Fully documented processes for grade changes, academic exceptions, and transcript handling. QA & Training: Ongoing quality assurance reviews and team training to maintain compliance and accuracy. | H21: Grade Change Accuracy Rate: Target ≥ 97% Transcript Accuracy Rate: Target ≥ 95% Academic Exception Accuracy: Target ≥ 95% QA Review Pass Rate: Target ≥ 90% Knowledge Base Updates: 2–4 per month Response Time to Partners: ≤ 24 hours Meeting Attendance: ≥ 95% Turnaround Times:Grade Changes: ≤ 3-5 business days Academic Exceptions: ≤ 8-14 business days Transcript Fulfillment: ≤ 8-14 business days | I21: Escalation Resolution Time: Average ≤ 72 hours Issue Flagging & Resolution Rate: ≥ 90% within SLA Training Sessions Conducted: 1–weekly Service Performance Reporting Compliance: 100% of weekly reports submitted | J21: Reach: For tracking grade changes, academic exceptions, and transcript requests. Anthology: For transcript accuracy and ADO issue resolution. QA Audit Reports: For compliance and accuracy metrics. Knowledge Base Logs: For update frequency. Internal Meeting Records & Timecards: For attendance and cyclical tasks. | K21: Weekly: Service performance reports, QA reviews, meeting attendance tracking. Monthly: KPI dashboard updates, Knowledge Base updates. Quarterly: SMART goal progress evaluation, workload trend analysis. Bi-Annual: Performance reviews and cyclical compliance checks
A22: Cindi C Putnam | B22: Planning Coordinator | C22: Student Services | D22: Complete | E22: > Meet with Planning Team leadership (student employees) to review the team's productivity and training. > Work with other teams both inside and outside the Registrar's office to iron out issues in students' DPAs and planning. > Creating and refining processes to address issues in weekly meetings with other Coordinators. > Meet with Anthology once a week to review questions about the platform and issues found. > Attend and participate in the Academic Exceptions meeting at least once a week. | F22: Assisting with Curriculum updates Creating and refining processes Creating and updating KBs for Planning Team | G22: Number of new incoming cases is monitored to inform new KB and procedure needs. Student DPA issues are reducing, and the institution is working toward data cleanliness. Maintain an open dialog with Anthology to ensure system updates are moving forward appropriately. Understand and contribute to Academic Exceptions team. | H22: Cases completed - 80 cases per day Number of cases in the queue - less than 160 cases Quality assurance - 90% average Cases age - less than 14 days old (Case age can only be controlled so far by the planning team because they are worked by other teams first but this metric is an aspirational KPI) | I22: None | J22: https://app.powerbi.com/groups/me/apps/edf61692-3af5-4aba-af7e-ef1de76ce451/reports/6f338692-a93d-4072-b2d6-b7af6aa347ab/e205f7687b0c4b678359?ctid=61e6eeb3-5fd7-4aaa-ae3c-61e8deb09b79&experience=power-bi | K22: Weekly
A23: Nikki Jane Chambers | B23: Enrollment Verification Specialist | C23: Student Services | D23: Complete | E23: > Emailing third parties that need an enrolment verification > Communicating with BYU-I on letters and forms I can fill out > Letters from the Department of the Defense > Internal Credits missing from BYUI and Ensign College that need to be input into the system > Custom letters for students | F23: Add BYU-I & Ensign courses to Anthology | G23: Third-party verification cases are processed and sent to students as soon as possible. Ensuring that students receive enrolment verifications efficiently and effectively. Collaborate with other departments and government organizations to provide students with custom letters as efficiently as possible. Refine and update internal credit system with the goal of establishing accuracy. | H23: Enrolment verification cases - 3 per hour per agent Internal credit additions - 1 per hour per agent Quality assurance - 90% goal Maximum case age - 5 days | I23: None | J23: None - tracking in spreadsheets | K23: Weekly & Monthly
A24: Emma Stone | B24: Registration Specialist | C24: Student Services | D24: Out of office
A25: Joshua Stafford Hadden | B25: System & Operations Manager | C25: Student Services | D25: Complete | E25: Systems and Operations is a new team intended to help Student Services operate with greater efficiency and efficacy. The Systems & Operations team does this through three major emphases: > Help steer future state projects--We help guide and plan for future state projects (especially the technical elements), allowing SMEs to focus on serving current student needs/initiatives. Some current examples of these projects are the MLP and New Registration projects. In addition to this, we frequently meet with SMEs to design ways to optimize their operations through better processes, tools, and best practices. > Provide operational data/reports (especially to members of student services) --We provide data and reports to help SMEs work more effectively in their area. We also produce reports that allow teams to measure their overall effectiveness/productivity. Additionally, we present the needs and standards for students to record data to a variety of internal and external partners. > Be SIS specialist--We provide support for how to best utilize the SIS and its features. This involves consulting with SMEs on their processes and how they use the SIS. We also manage much of the configuration of the entities within the SIS to tailor the system for our programs, initiatives, and students. | F25: None | G25: State projects have all the technical support and project planning to roll out effectively without distracting SMEs. Ensure the Student Information System has the necessary support to run effectively and efficiently. All Power BI reports are functional and providing data to fulfill their purposes. | H25: Tasks completed on time - goal to be set Number of task hours completed - goal to be set | I25: None | J25: Pending | K25: Monthly
A26: David Peck | B26: Operational Data Analyst | C26: Student Services | D26: Complete | E26: > Manage the reports in the Power BI Apps that I have developed and ensure that they continue to refresh as expected. | F26: None | G26: All Power BI reports are functional and providing data to fulfill their purposes. | H26: Tasks completed on time - goal to be set Number of task hours completed - goal to be set | I26: None | J26: Pending | K26: Monthly
A27: Pelenatita Neiufi | B27: Reporting & Evaluation Coordinator | C27: Student Services | D27: Complete | E27: > NSC reporting for both BYUI and EC > Enrollment Verifications > Demographic changes > SSN verifications > Auto-Drop Process > Grade Posting Process > Academic Calendar - Dates & Deadlines > Term Configurations > Updating student services website through Coursedog | F27: None | G27: All Student Services process reports are functional and updating appropriately. Student Services website is always fully updated. | H27: Tasks completed on time - goal to be set Number of task hours completed - goal to be set | I27: None | J27: Pending | K27: Monthly
A28: Victor Lamôni Calado Ferreira | B28: System & Operations Associate Registrar | C28: Student Services | D28: Complete | E28: > Overseeing the Student Information System (SIS) > Implementing institutional academic policies > FERPA compliance | F28: None | G28: Ensure the Student Information System has the necessary support to run effectively and efficiently. FERPA practices are maintained for all students. | H28: Tasks completed on time - goal to be set Number of task hours completed - goal to be set | I28: None | J28: Pending | K28: Monthly
A29: Trevor Shelton | B29: Admissions Services Manager | C29: Student Services | D29: Complete | E29: > Develop admissions policies and strategies to support new and evolving initiatives > Key business owner for system design, testing, and improvement efforts to enhance student access > Monitor key admissions metrics to inform decisions > Collaborate with BYU-Pathway leadership, partner institutions, and cross-functional teams to align processes > Support organizational scalability through planning and documentation > Provide oversight and direction to staff who manage operational processes (application review, endorsements, transcripts, data integrity | F29: MLP System development and updates New Registration Updates (Ecclesiastical Endorsement, Progressing Students) Improve transfer credit evaluation process | G29: Reduced BYU-Pathway Support traffic for all areas overseen by Admissions Improved application to registration through-put High employee productivity due to clear direction and leadership. Effective collaboration among team members. | H29: None | I29: Percentage of started admission applications that get an admissions decision (admit or deny). Delivery of Strategic Admissions Initiatives Completion of planned admissions initiatives on time and as scoped. Reduction of enrollment related support tickets. Elimination of Admissions-SME tier 2 support tickets. | J29: None | K29: Per term
A30: Shaunasee Janette James | B30: Enrollment Coordinator | C30: Student Services | D30: Complete | E30: > Liaise with the Ecclesiastical Clearance Office (ECO) and chaplains to resolve endorsement-related issues. > Manage a team that notifies students with missing or MRNs and resetting endorsement requests. > Oversee transfer evaluation team as they make sure of transcript submission. workflows and ensure accurate linkage to student records. > Support or lead transcript evaluation processes to verify credit. > Identify and merge duplicate student records in Reach. > Manage and monitor student portal tools, including the English Language Assessment and Parent Program Selection. | F30: Updating Transfer Evaluation Policies Checking and correcting endorsement hold groups Creating transfer evaluation QA procedure | G30: Consistently reducing transfer evaluation backlog Admission SME Support queue is emptying each day Endorsement related issues are resolved efficiently and effectively Student MRN issues are tracked and corrected by collaborating with the student to prevent barriers for continuation Ensure student portal tools are functional | H30: Maximum case age - 5 days Quality assurance - 90% average | I30: Transfer evaluations are completed at an average rate of 1.25 per hour per agent. Maximum case age does not exceed 5 days, ensuring evaluations do not develop into a backlog. Quality assurance scores average 90 percent or higher across completed evaluations. Reduction of enrollment related support tickets. Elimination of Admissions-SME tier 2 support tickets | J30: Pending | K30: Weekly & Monthly
A31: Ely Zmolek | B31: Enrollment Services Specialist | C31: Student Services | D31: Complete | E31: > Process student applications across various programs. > Monitor integration logs to verify successful application processing and resolve reported issues. > Review and process applications flagged for Manual Review, including those requiring exceptions. > Manually provision students when necessary or upon request. > Maintain and update application settings in Reach for each term, including application periods, decisions, and admission letters. > Create and update knowledge base (KB) articles related to the application process. > Collaborate with the Registrar’s Office to update returning students’ credits and PathwayConnect graduations upon enrollment. > Test new application versions (e.g., Portuguese application) and report issues for resolution. > Oversee the Admissions SME Support queue, identifying and managing cases related to the application. > Supervise a team of student employees, providing weekly training and ongoing support. | F31: Application processing Ensuring integration and provisioning to get all student licenses Resolve escalated issues in the SME Admissions Support Queue Manual Review on Applications Ensuring Application setting are correctly updated each block | G31: Promote admitted students within 1 business day of application submission Students receive admissions communication at the proper times during the application process. Resolve Manual Review on Application within a week Application settings are always updated and correct | H31: None | I31: Get student their BYU-Pathway email within a business day of promotion 100% application processed within a business day 100% of admitted applications processed (promoted) within one business day during promotion periods. 100% of applications selected for manual review are completed, or the student is communicated with, within one week. Reduction of application related support tickets. Elimination of Admissions-SME tier 2 support tickets. | J31: REACH Queues | K31: Per term
A32: Trey Mooney | B32: University Chaplain | C32: Student Services | D32: Pending | E32: > Coordination Meeting with Admissions Leadership > Data Team ECO Coordination Meeting > Volunteer Chaplain Leadership Coordination > Salt Lake City HQ Mission Presidency Coordination > Conduct Ecclesiastical Endorsement Interviews Training Leadership Interview new Chaplains | F32: Ecclesiastical Endorsement Interview Oversight Partnership and Communication with the Ecclesiastical Clearance Office (ECO). Chaplain Training and Onboarding Forecasting and Capacity Planning Data, Reporting, and Continuous Improvement Chaplain Endorsement Tool Oversight Chaplain Recruitment and Load Balancing Escalation & Student Communication BYU-Pathway and Partner Collaboration | G32: Interviews are accurate, complete, and aligned with the Honor Code. Chaplains are well-trained, confident, and performing at high quality levels. Chaplains are provided with the tools that allow them to be efficient and effective in conducting Ecclesiastical Endorsement Interviews (Chaplain Portal) There exists a high level of discretion, care, and spiritual sensitivity in student and team interactions. There is strong collaboration with internal departments and external partners to ensure alignment on policies, communication, and endorsement processes. All updates to ECS and all tracking tools reflect current and correct information. Dashboards and reports provide clear, actionable insights that guide decisions. Feedback from students, chaplains, and ECO indicates a positive and supportive interview experience. | H32: Target interview timelines (goal: within 2 weeks) are consistently met. | I32: 100% of Chaplain endorsement requests being worked on within 1 week (first contact attempt). Endorsement requests completed within 2 weeks of entering Chaplain queue. Weekly training/coordination with lead chaplains. Monthly training/coordination with all chaplains." | J32: Chaplin dashboard | K32: Monthly
A33: Hilary Bagley | B33: Student Experience Coordinator | C33: Student Services | D33: Complete | E33: > Coordinate Training with other Pathway departments as well as with our partners. > Coordinate with those working on video and other media creative projects to supplement our KBs. > Communicate with SSC structure within the organization and with our partners. > Collaborate with Student Support to ensure that the student-facing articles on the Help Centre are easily accessible and accurate. > Outline and communicate the student journey | F33: Milestone Maps Training Development New Registration KBs for who is moving to new registration and who isn't Class Planning How to us Program Plans Springboard contractors checking all KBs for accuracy. | G33: Ensure that the Help Centre has everything a student needs to navigate the student experience autonomously. Including all steps, micro steps, links, pictures, and videos. Understand the full student experience to advocate and plan for their needs. Coordinate with SMEs and write KBs to their specifications. | H33: None | I33: Audit every external article each quarter. Confirm SME meetings are occurring each week. | J33: None | K33: Weekly & Quarterly

Sheet KPI Registry
A1: Employee | B1: Role | C1: Dept | D1: KPI Measure | E1: KPI Category | F1: Category Type | G1: Data | H1: Performance | N1: Data options
A2: Steven K. Thomas | B2: Dean of Students | C2: Dean of Students | D2: No material audit findings attributable to Dean of Students governance | E2: Operational Outcomes | F2: Quality | G2: Data available | H2: 0 | I2: 0 | J2: ≥1 | N2: No data
A3: Steven K. Thomas | B3: Dean of Students | C3: Dean of Students | D3: No legal findings attributable to Dean of Students governance | E3: Operational Outcomes | F3: Quality | G3: Data available | H3: 0 | I3: 0 | J3: ≥1 | N3: Data available
A4: Steven K. Thomas | B4: Dean of Students | C4: Dean of Students | D4: No accreditation findings attributable to Dean of Students governance | E4: Operational Outcomes | F4: Quality | G4: Data available | H4: 0 | I4: 0 | J4: ≥1 | N4: Data in report
A5: Steven K. Thomas | B5: Dean of Students | C5: Dean of Students | D5: Annual DOS budget | E5: Operational Outcomes | F5: Cost | G5: Data available | H5: $ | I5: $ | J5: $
A6: Steven K. Thomas | B6: Dean of Students | C6: Dean of Students | D6: Overall student satisfaction (primary) | E6: Student Outcomes | F6: Satisfaction | G6: Data in report | H6: 0.75 | I6: - | J6: -
A7: Anne Marie Clark | B7: Associate Dean of Students | C7: Dean of Students | D7: Dean of Students response time | E7: Operational Outcomes | F7: Speed | G7: Data available | H7: <5 days | I7: 5 - 7 days | J7: >7 days
A8: Anne Marie Clark | B8: Associate Dean of Students | C8: Dean of Students | D8: Dean of Students resolution time | E8: Operational Outcomes | F8: Speed | G8: Data available
A9: Anne Marie Clark | B9: Associate Dean of Students | C9: Dean of Students | D9: Dean of Students services escalation rates | E9: Operational Outcomes | F9: Quality | G9: Data available
A10: Anne Marie Clark | B10: Associate Dean of Students | C10: Dean of Students | D10: Partner CSAT | E10: Operational Outcomes | F10: Quality | G10: No data
A11: Katelyn Ray | B11: Student Honor & Conduct Coordinator | C11: Dean of Students | D11: Honor and Conduct response time | E11: Operational Outcomes | F11: Speed | G11: Data available | H11: <5 days | I11: 5 - 7 days | J11: >7 days
A12: Katelyn Ray | B12: Student Honor & Conduct Coordinator | C12: Dean of Students | D12: Honor and Conduct resolution time | E12: Operational Outcomes | F12: Speed | G12: No data | H12: TBD | I12: TBD | J12: TBD
A13: Katelyn Ray | B13: Student Honor & Conduct Coordinator | C13: Dean of Students | D13: Rate of repeat offenders | E13: Operational Outcomes | F13: Quality | G13: Data available | H13: 0.05 | I13: 0.15 | J13: 0.25
A14: Sandra Wurttele | B14: Student Accessibility Coordinator | C14: Dean of Students | D14: Accommodation determination processing rate | E14: Operational Outcomes | F14: Speed | G14: Data available | H14: <5 days | I14: 5 - 7 days | J14: >7 days
A15: Sandra Wurttele | B15: Student Accessibility Coordinator | C15: Dean of Students | D15: Accommodation resolution rate | E15: Operational Outcomes | F15: Speed | G15: Data available | H15: <3 days | I15: 3 - 6 days | J15: > 6 days
A16: Sandra Wurttele | B16: Student Accessibility Coordinator | C16: Dean of Students | D16: ADA and Section 504 standard compliance rate | E16: Operational Outcomes | F16: Quality | G16: Data available | H16: - | I16: - | J16: -
A17: Sandra Wurttele | B17: Student Accessibility Coordinator | C17: Dean of Students | D17: ADA and Section 504 Audit compliance rate | E17: Operational Outcomes | F17: Quality | G17: Data available | H17: - | I17: - | J17: -
A18: Ana De Castro | B18: Student Belonging Coordinator | C18: Dean of Students | D18: Discrimination resolution rate | E18: Operational Outcomes | F18: Quality | G18: Data available | H18: - | I18: - | J18: -
A19: Ana De Castro | B19: Student Belonging Coordinator | C19: Dean of Students | D19: Student sentiment on belonging | E19: Operational Outcomes | F19: Quality | G19: No data | H19: NA | I19: NA | J19: NA
A20: Ana De Castro | B20: Student Belonging Coordinator | C20: Dean of Students | D20: CSAT for Student Belonging | E20: Operational Outcomes | F20: Quality | G20: No data | H20: NA | I20: NA | J20: NA
A21: Helen Reboucas | B21: Student Grievance Coordinator | C21: Dean of Students | D21: Student grievance case resolution time | E21: Operational Outcomes | F21: Speed | G21: Data available | H21: <5 days | I21: 5 - 7 days | J21: >7 days
A22: Helen Reboucas | B22: Student Grievance Coordinator | C22: Dean of Students | D22: Grievance QA | E22: Operational Outcomes | F22: Quality | G22: Data available | H22: < 90% | I22: 70% - 90% | J22: < 70%
A23: Joseph Bentum | B23: Student Crisis Coordinator | C23: Dean of Students | D23: Crisis response time | E23: Operational Outcomes | F23: Speed | G23: Data available | H23: < 24 hours | I23: 24 - 48 hours | J23: > 48 hours
A24: Mark Gefrom | B24: Director of Student Support | C24: Records, Registration, Support | D24: Teams meeting or exceeding response service-level agreements | E24: Operational Outcomes | F24: Speed | G24: Data in report | H24: < 24 hours | I24: 24 - 48 hours | J24: > 48 hours
A25: Mark Gefrom | B25: Director of Student Support | C25: Records, Registration, Support | D25: Teams meeting or exceeding resolution service-level agreements | E25: Operational Outcomes | F25: Speed | G25: Data in report | H25: <48 hours | I25: 48 - 72 hours | J25: > 72 hours
... A32: Brad Lester | B32: Senior Manager of Student Support | C32: Records, Registration, Support | D32: Student support budget | E32: Operational Outcomes | F32: Cost | G32: Data available | H32: $ | I32: $ | J32: $
A33: Brad Lester | B33: Senior Manager of Student Support | C33: Records, Registration, Support | D33: Autonomy rate for student support cases | E33: Student Outcomes | F33: Autonomy | G33: Data in report | H33: 100% - 85% | I33: 84% - 70% | J33: 0.69
A34: Alyssa Burrell | B34: Student Support Coordinator | C34: Records, Registration, Support | D34: General support case response rate | E34: Operational Outcomes | F34: Speed | G34: Data in report | H34: 1-3 Days | I34: 4-5 Days | J34: 5+ Days
A35: Alyssa Burrell | B35: Student Support Coordinator | C35: Records, Registration, Support | D35: General support case resolution rate | E35: Operational Outcomes | F35: Speed | G35: Data in report | H35: ≥ 90% | I35: 80-90% | J35: < 80%
A36: Alyssa Burrell | B36: Student Support Coordinator | C36: Records, Registration, Support | D36: Phone answer speed | E36: Operational Outcomes | F36: Speed | G36: Data in report | H36: < 1 minute | I36: 2-5 minutes | J36: 5+ minutes
A37: Alyssa Burrell | B37: Student Support Coordinator | C37: Records, Registration, Support | D37: Phone handle rate | E37: Operational Outcomes | F37: Speed | G37: Data in report | H37: ≥ 90% | I37: 80-89% | J37: < 80%
A38: Alyssa Burrell | B38: Student Support Coordinator | C38: Records, Registration, Support | D38: Agent availability | E38: Operational Outcomes | F38: Speed | G38: Data in report | H38: ≥ 80% | I38: 75 - 79 % | J38: < 75%
A39: Alyssa Burrell | B39: Student Support Coordinator | C39: Records, Registration, Support | D39: Phone support QA | E39: Operational Outcomes | F39: Quality | G39: Data in report | H39: ≥ 80% | I39: 75-85% | J39: < 75%
A40: Alyssa Burrell | B40: Student Support Coordinator | C40: Records, Registration, Support | D40: Phone support CSAT | E40: Operational Outcomes | F40: Quality | G40: Data in report | H40: ≥ 80% | I40: 75-85% | J40: < 75%
A41: Alyssa Burrell | B41: Student Support Coordinator | C41: Records, Registration, Support | D41: Phone support first contact resolution | E41: Operational Outcomes | F41: Quality | G41: Data in report | H41: ≥ 90% | I41: 80-90% | J41: < 80%
A42: Hilary Bagley | B42: Training & Quality Assurance Manager | C42: Records, Registration, Support | D42: Request-to-KB publish rate | E42: Operational Outcomes | F42: Speed | G42: No data | H42: NA | I42: NA | J42: NA
A43: Hilary Bagley | B43: Training & Quality Assurance Manager | C43: Records, Registration, Support | D43: QA feedback cycle rate | E43: Operational Outcomes | F43: Speed | G43: Data in report
A44: Hilary Bagley | B44: Training & Quality Assurance Manager | C44: Records, Registration, Support | D44: QA calibration consistency rate | E44: Operational Outcomes | F44: Quality | G44: No data | H44: NA | I44: NA | J44: NA
A45: Hilary Bagley | B45: Training & Quality Assurance Manager | C45: Records, Registration, Support | D45: Knowledge Base audit pass rate | E45: Operational Outcomes | F45: Quality | G45: No data | H45: NA | I45: NA | J45: NA
A46: Hilary Bagley | B46: Training & Quality Assurance Manager | C46: Records, Registration, Support | D46: QA team lead feedback success rate | E46: Operational Outcomes | F46: Quality | G46: Data in report
A47: Hilary Bagley | B47: Training & Quality Assurance Manager | C47: Records, Registration, Support | D47: Cost per QA Evaluation ($ per Evaluation) | E47: Operational Outcomes | F47: Cost | G47: Data available | H47: $ | I47: $ | J47: $
A48: Hilary Bagley | B48: Training & Quality Assurance Manager | C48: Records, Registration, Support | D48: Cost per KB Article Maintained ($ per Article Updated or Audited) | E48: Operational Outcomes | F48: Cost | G48: Data available | H48: $ | I48: $ | J48: $
A49: Kira Hayes | B49: Training & Quality Assurance Coordinator | C49: Records, Registration, Support | D49: KB publishing rate | E49: Operational Outcomes | F49: Speed | G49: No data | H49: NA | I49: NA | J49: NA
A50: Kira Hayes | B50: Training & Quality Assurance Coordinator | C50: Records, Registration, Support | D50: QA evaluation completion rate | E50: Operational Outcomes | F50: Quality | G50: No data | H50: NA | I50: NA | J50: NA
A51: Kira Hayes | B51: Training & Quality Assurance Coordinator | C51: Records, Registration, Support | D51: DSAT and critical violation delivery rate | E51: Operational Outcomes | F51: Quality | G51: No data | H51: NA | I51: NA | J51: NA
A52: Matthew Smith | B52: Technical Support Manager | C52: Records, Registration, Support | D52: Tech support case resolution rate | E52: Operational Outcomes | F52: Speed | G52: Data in report | H52: 3 business days | I52: 5 business days | J52: > 10 business days
A53: Matthew Smith | B53: Technical Support Manager | C53: Records, Registration, Support | D53: Tech support costs | E53: Operational Outcomes | F53: Cost | G53: Data available | H53: $ | I53: $ | J53: $
A54: Matthew Smith | B54: Technical Support Manager | C54: Records, Registration, Support | D54: Autonomy rate for tech support cases | E54: Student Outcomes | F54: Autonomy | G54: Data in report | H54: 0 | I54: 0 | J54: 0
A55: Colby Warner | B55: Product Support Engineer | C55: Records, Registration, Support | D55: Escalated case resolution rate | E55: Operational Outcomes | F55: Speed | G55: Data in report | H55: 90-100% | I55: 75-90% | J55: < 75%
A56: Colby Warner | B56: Product Support Engineer | C56: Records, Registration, Support | D56: Tech Support case QA | E56: Operational Outcomes | F56: Quality | G56: Data in report | H56: 90-100% | I56: 80-90% | J56: <80%
A57: Colby Warner | B57: Product Support Engineer | C57: Records, Registration, Support | D57: Tech Support case CSAT | E57: Operational Outcomes | F57: Quality | G57: Data in report | H57: 90-100% | I57: 80-90% | J57: <80%
A58: Colby Warner | B58: Product Support Engineer | C58: Records, Registration, Support | D58: Tech Support case first contact resolution | E58: Operational Outcomes | F58: Quality | G58: Data in report | H58: 90-100% | I58: 75-90% | J58: < 75%
A59: Kari Johnson | B59: Registrar | C59: Records, Registration, Support | D59: Registrar budget | E59: Operational Outcomes | F59: Cost | G59: Data available | H59: $ | I59: $ | J59: $
A60: Kari Johnson | B60: Registrar | C60: Records, Registration, Support | D60: Autonomy for student registration (% students registered without submitting a support request) | E60: Student Outcomes | F60: Autonomy | G60: Data in report | H60: 90-100% | I60: 75-90% | J60: <75%
A61: Kari Johnson | B61: Registrar | C61: Records, Registration, Support | D61: Transcripts processed within 10 days | E61: Student Outcomes | F61: Autonomy | G61: Data available | H61: 0-5% of student reaching out | I61: 5-30% of Students reaching out | J61: 30-100% of students reaching out
A62: Kari Johnson | B62: Registrar | C62: Records, Registration, Support | D62: Case CSAT for planning and registration | E62: Student Outcomes | F62: Satisfaction | G62: Data in report | H62: 85-100% | I62: 70-84% | J62: Below 70%
A63: Kim Overdiek | B63: Associate Registrar | C63: Records, Registration, Support | D63: Case resolution within 5 days | E63: Operational Outcomes | F63: Speed | G63: Data in report | H63: 85-100% | I63: 65-84% | J63: Below 65%
A64: Kim Overdiek | B64: Associate Registrar | C64: Records, Registration, Support | D64: On-time catalog publishing rate | E64: Operational Outcomes | F64: Speed | G64: No data | H64: NA | I64: NA | J64: NA
A65: Kim Overdiek | B65: Associate Registrar | C65: Records, Registration, Support | D65: On-time system configuration rate | E65: Operational Outcomes | F65: Speed | G65: No data | H65: NA | I65: NA | J65: NA
A66: Kim Overdiek | B66: Associate Registrar | C66: Records, Registration, Support | D66: Process case QA | E66: Operational Outcomes | F66: Quality | G66: Data in report | H66: 85-100% | I66: 70-84% | J66: Below 70%
... A72: Angie Holt | B72: Graduation Coordinator | C72: Records, Registration, Support | D72: Award processing rate | E72: Operational Outcomes | F72: Speed | G72: Data available | H72: < 3 weeks | I72: 3-6 weeks | J72: Above 6 weeks
A73: Angie Holt | B73: Graduation Coordinator | C73: Records, Registration, Support | D73: Number of Rescinded Degrees | E73: Operational Outcomes | F73: Quality | G73: Data available | H73: 0 | I73: NA | J73: >1
A74: Angie Holt | B74: Graduation Coordinator | C74: Records, Registration, Support | D74: Application QA | E74: Operational Outcomes | F74: Quality | G74: Data available | H74: 1 | I74: 85-99% | J74: Below 85%
A75: Angie Holt | B75: Graduation Coordinator | C75: Records, Registration, Support | D75: Awarding QA | E75: Operational Outcomes | F75: Quality | G75: Data available | H75: 1 | I75: 85-99% | J75: Below 85%
A76: Anne E. Owen | B76: Records & Transcript Coordinator | C76: Records, Registration, Support | D76: Process case completion rate | E76: Operational Outcomes | F76: Speed | G76: Data in report | H76: < 5 days | I76: 6-10 Days | J76: Above 10 Days
A77: Anne E. Owen | B77: Records & Transcript Coordinator | C77: Records, Registration, Support | D77: Process case CSAT | E77: Operational Outcomes | F77: Quality | G77: Data in report | H77: 85-100% | I77: 70-84% | J77: Below 70%
A78: Anne E. Owen | B78: Records & Transcript Coordinator | C78: Records, Registration, Support | D78: Process case QA | E78: Operational Outcomes | F78: Quality | G78: Data in report | H78: 85-100% | I78: 70-84% | J78: Below 70%
A79: Anne E. Owen | B79: Records & Transcript Coordinator | C79: Records, Registration, Support | D79: Transcript accuracy QA | E79: Operational Outcomes | F79: Quality | G79: Data in report | H79: 85-100% | I79: 70-84% | J79: Below 70%
A80: Cindi C Putnam | B80: Planning Coordinator | C80: Records, Registration, Support | D80: Degree planning escalation case resolution rate | E80: Operational Outcomes | F80: Speed | G80: Data in report | H80: Resolution Rate < 5 Days | I80: 6-10 days | J80: Above 10 Day
A81: Cindi C Putnam | B81: Planning Coordinator | C81: Records, Registration, Support | D81: Degree planning escalation case CSAT | E81: Operational Outcomes | F81: Quality | G81: Data in report | H81: 85-100% | I81: 70-84% | J81: Below 70%
A82: Cindi C Putnam | B82: Planning Coordinator | C82: Records, Registration, Support | D82: Degree planning escalation case QA | E82: Operational Outcomes | F82: Quality | G82: Data in report | H82: 85-100% | I82: 70-84% | J82: Below 70%
A83: Nikki Jane Chambers | B83: Enrollment Verification Specialist | C83: Records, Registration, Support | D83: Enrollment verification completion rate | E83: Operational Outcomes | F83: Speed | G83: Data in report | H83: < 5 days | I83: 6-10 Days | J83: Above 10 Days
A84: Nikki Jane Chambers | B84: Enrollment Verification Specialist | C84: Records, Registration, Support | D84: Apostille completion rate | E84: Operational Outcomes | F84: Speed | G84: Data in report | H84: <10 Days | I84: 11-14 days | J84: Above 14 days
A85: Nikki Jane Chambers | B85: Enrollment Verification Specialist | C85: Records, Registration, Support | D85: Enrollment verification QA | E85: Operational Outcomes | F85: Quality | G85: Data in report | H85: 85-100% | I85: 70-84% | J85: Below 70%
A86: Nikki Jane Chambers | B86: Enrollment Verification Specialist | C86: Records, Registration, Support | D86: Apostille QA | E86: Operational Outcomes | F86: Quality | G86: No data | H86: NA | I86: NA | J86: NA
A87: Nikki Jane Chambers | B87: Enrollment Verification Specialist | C87: Records, Registration, Support | D87: Enrollment verification CSAT | E87: Operational Outcomes | F87: Quality | G87: Data in report | H87: 85-100% | I87: 70-84% | J87: Below 70%
... A91: Daniel Zago | B91: Registration Specialist | C91: Records, Registration, Support | D91: Registration issue case CSAT | E91: Operational Outcomes | F91: Quality | G91: Data in report | H91: 85-100% | I91: 70-84% | J91: Below 70%
A92: Jacob Adams | B92: =_xlfn.XLOOKUP(A92,'Digital Ops'!$A$3:$A$12,'Digital Ops'!$B$3:$B$12) -> Director of Digital Operations | C92: Digital Operations | D92: Overall Stakeholder CSAT | E92: Operational Outcomes | F92: Quality | G92: Data available | H92: 85-100% | I92: 75-84% | J92: <75%
A93: Jacob Adams | B93: =_xlfn.XLOOKUP(A93,'Digital Ops'!$A$3:$A$12,'Digital Ops'!$B$3:$B$12) -> Director of Digital Operations | C93: Digital Operations | D93: Digital Ops budget | E93: Operational Outcomes | F93: Cost | G93: Data available | H93: $ | I93: $ | J93: $
A94: Jacob Adams | B94: =_xlfn.XLOOKUP(A94,'Digital Ops'!$A$3:$A$12,'Digital Ops'!$B$3:$B$12) -> Director of Digital Operations | C94: Digital Operations | D94: Costs saved by customers due to Digital Ops technologies (secondary) | E94: Operational Outcomes | F94: Cost | G94: Data available | H94: $ | I94: $ | J94: $
A95: Jacob Adams | B95: =_xlfn.XLOOKUP(A95,'Digital Ops'!$A$3:$A$12,'Digital Ops'!$B$3:$B$12) -> Director of Digital Operations | C95: Digital Operations | D95: Overall student autonomy (secondary) | E95: Student Outcomes | F95: Student Autonomy | G95: Data in report | H95: 80-100% | I95: 65-79% | J95: <65%
A96: Jacob Adams | B96: =_xlfn.XLOOKUP(A96,'Digital Ops'!$A$3:$A$12,'Digital Ops'!$B$3:$B$12) -> Director of Digital Operations | C96: Digital Operations | D96: Overall student satisfaction (secondary) | E96: Student Outcomes | F96: Student Satisfaction | G96: Data in report | H96: 80-100% | I96: 65-79% | J96: <65%
A97: Jacob Adams | B97: =_xlfn.XLOOKUP(A97,'Digital Ops'!$A$3:$A$12,'Digital Ops'!$B$3:$B$12) -> Director of Digital Operations | C97: Digital Operations | D97: Application Rate | E97: Student Outcomes | F97: Completion | G97: Data in report | H97: 80-100% | I97: 65-79% | J97: <65%
A98: Jacob Adams | B98: =_xlfn.XLOOKUP(A98,'Digital Ops'!$A$3:$A$12,'Digital Ops'!$B$3:$B$12) -> Director of Digital Operations | C98: Digital Operations | D98: Retention Rate | E98: Student Outcomes | F98: Completion | G98: Data in report | H98: >75% | I98: 65-74% | J98: <65%
A99: Jacob Adams | B99: =_xlfn.XLOOKUP(A99,'Digital Ops'!$A$3:$A$12,'Digital Ops'!$B$3:$B$12) -> Director of Digital Operations | C99: Digital Operations | D99: Completion Rate (Secondary) | E99: Student Outcomes | F99: Completion | G99: Data in report | H99: >40% | I99: 30-39% | J99: <30%
A100: Ricky Kailiponi Jr. | B100: =_xlfn.XLOOKUP(A100,'Digital Ops'!$A$3:$A$12,'Digital Ops'!$B$3:$B$12) -> Senior Manager of Digital Ops | C100: Digital Operations | D100: Team meeting project deadlines rate | E100: Operational Outcomes | F100: Speed
A101: Ricky Kailiponi Jr. | B101: =_xlfn.XLOOKUP(A101,'Digital Ops'!$A$3:$A$12,'Digital Ops'!$B$3:$B$12) -> Senior Manager of Digital Ops | C101: Digital Operations | D101: Companion feature C-Sat | E101: Operational Outcomes | F101: Quality | G101: Data in report | H101: 85-100% | I101: 75-84% | J101: <75%
A102: Ricky Kailiponi Jr. | B102: =_xlfn.XLOOKUP(A102,'Digital Ops'!$A$3:$A$12,'Digital Ops'!$B$3:$B$12) -> Senior Manager of Digital Ops | C102: Digital Operations | D102: Companion usage rates | E102: Student Outcomes | F102: Student Autonomy | G102: Data in report | H102: 75-100% | I102: 50-74% | J102: <50%
A103: Ricky Kailiponi Jr. | B103: =_xlfn.XLOOKUP(A103,'Digital Ops'!$A$3:$A$12,'Digital Ops'!$B$3:$B$12) -> Senior Manager of Digital Ops | C103: Digital Operations | D103: Companion C-Sat | E103: Student Outcomes | F103: Student Satisfaction | G103: Data in report | H103: 85-100% | I103: 75-84% | J103: <75%
A104: Ricky Kailiponi Jr. | B104: =_xlfn.XLOOKUP(A104,'Digital Ops'!$A$3:$A$12,'Digital Ops'!$B$3:$B$12) -> Senior Manager of Digital Ops | C104: Digital Operations | D104: AI retention effect | E104: Student Outcomes | F104: Completion | G104: Data available | H104: >4% | I104: 2-3% | J104: 0.01
A105: Joshua Stafford Hadden | B105: =_xlfn.XLOOKUP(A105,'Digital Ops'!$A$3:$A$12,'Digital Ops'!$B$3:$B$12) -> Operational Research & Reporting Manager | C105: Digital Operations | D105: Team meeting project timelines rate | E105: Operational Outcomes | F105: Speed
A106: Joshua Stafford Hadden | B106: =_xlfn.XLOOKUP(A106,'Digital Ops'!$A$3:$A$12,'Digital Ops'!$B$3:$B$12) -> Operational Research & Reporting Manager | C106: Digital Operations | D106: Stakeholder CSAT on team's projects | E106: Operational Outcomes | F106: Quality | G106: Data available | H106: 85-100% | I106: 75-84% | J106: <75%
A107: Joshua Stafford Hadden | B107: =_xlfn.XLOOKUP(A107,'Digital Ops'!$A$3:$A$12,'Digital Ops'!$B$3:$B$12) -> Operational Research & Reporting Manager | C107: Digital Operations | D107: Cost reductions in service areas (secondary) | E107: Operational Outcomes | F107: Cost | G107: Data available | H107: $ | I107: $ | J107: $
A108: David Peck | B108: =_xlfn.XLOOKUP(A108,'Digital Ops'!$A$3:$A$12,'Digital Ops'!$B$3:$B$12) -> Operational Data Analyst | C108: Digital Operations | D108: Project delivery on time rate | E108: Operational Outcomes | F108: Speed
A109: David Peck | B109: =_xlfn.XLOOKUP(A109,'Digital Ops'!$A$3:$A$12,'Digital Ops'!$B$3:$B$12) -> Operational Data Analyst | C109: Digital Operations | D109: Stakeholder CSAT - communication, quality of work, impact | E109: Operational Outcomes | F109: Quality | G109: Data available | H109: 85-100% | I109: 75-84% | J109: <75%
A110: Pelenatita Neiufi | B110: =_xlfn.XLOOKUP(A110,'Digital Ops'!$A$3:$A$12,'Digital Ops'!$B$3:$B$12) -> Reporting & Evaluation Coordinator | C110: Digital Operations | D110: Project delivery on time rate | E110: Operational Outcomes | F110: Speed
A111: Pelenatita Neiufi | B111: =_xlfn.XLOOKUP(A111,'Digital Ops'!$A$3:$A$12,'Digital Ops'!$B$3:$B$12) -> Reporting & Evaluation Coordinator | C111: Digital Operations | D111: Stakeholder CSAT - communication, quality of work, impact | E111: Operational Outcomes | F111: Quality | G111: Data available | H111: 85-100% | I111: 75-84% | J111: <75%
A112: Victor Lamôni Calado Ferreira | B112: =_xlfn.XLOOKUP(A112,'Digital Ops'!$A$3:$A$12,'Digital Ops'!$B$3:$B$12) -> System & Operations Associate Registrar (title change) | C112: Digital Operations | D112: Project delivery on time rate | E112: Operational Outcomes | F112: Speed
A113: Victor Lamôni Calado Ferreira | B113: =_xlfn.XLOOKUP(A113,'Digital Ops'!$A$3:$A$12,'Digital Ops'!$B$3:$B$12) -> System & Operations Associate Registrar (title change) | C113: Digital Operations | D113: Stakeholder CSAT - communication, quality of work, impact | E113: Operational Outcomes | F113: Quality | G113: Data available | H113: 85-100% | I113: 75-84% | J113: <75%
A114: John Ayinde | B114: =_xlfn.XLOOKUP(A114,'Digital Ops'!$A$3:$A$12,'Digital Ops'!$B$3:$B$12) -> D365 & Automation Manager | C114: Digital Operations | D114: Stakeholder CSAT - timeliness per project | E114: Operational Outcomes | F114: Speed | G114: Data available | H114: 85-100% | I114: 75-84% | J114: <75%
...

Sheet KPI ScoreCard
A1: Draft v1.0 | Updated monthly | Last refreshed: July 07, 2026 | R1: Automation reference - powers Performance Status. Edit only to set/correct a KPI's target.
A2: Employee | B2: Role | C2: Dept | D2: KPI Measure | E2: KPI Category | F2: Category Type | G2: Data | H2: Performance | K2: Tracking Status | L2: Current Value | M2: Performance Status | N2: Data Source (Link to Sheet or Report) | O2: Update Frequency | P2: Update Date | R2: Direction | S2: Green Cutoff | T2: Red Cutoff | U2: Data options
A3: Steven K. Thomas | B3: Dean of Students | C3: Dean of Students | D3: No material audit findings attributable to Dean of Students governance | E3: Operational Outcomes | F3: Quality | G3: Data available | H3: 0 | I3: 0 | J3: ≥1 | K3: Tracking | L3: 0 | M3: =IF(K3="Not Tracking","Not Tracked",IF(L3="","No Data",IF(R3="Higher is Better",IF(L3>=S3,"Green",IF(L3>=T3,"Yellow","Red")),IF(R3="Lower is Better",IF(L3<=S3,"Green",IF(L3<=T3,"Yellow","Red")),"Manual Review")))) -> Green | N3: Excel link | O3: Monthly | R3: Lower is Better | S3: 0 | T3: 1 | U3: Lower is Better | V3: Bi-Weekly | W3: No data | X3: Tracking
A4: Steven K. Thomas | B4: Dean of Students | C4: Dean of Students | D4: No legal findings attributable to Dean of Students governance | E4: Operational Outcomes | F4: Quality | G4: Data available | H4: 0 | I4: 0 | J4: ≥1 | K4: Tracking | L4: 0 | M4: =IF(K4="Not Tracking","Not Tracked",IF(L4="","No Data",IF(R4="Higher is Better",IF(L4>=S4,"Green",IF(L4>=T4,"Yellow","Red")),IF(R4="Lower is Better",IF(L4<=S4,"Green",IF(L4<=T4,"Yellow","Red")),"Manual Review")))) -> Green | N4: Excel link | O4: Monthly | R4: Lower is Better | S4: 0 | T4: 1 | U4: Manual | V4: Monthly | W4: Data available | X4: Not Tracking
A5: Steven K. Thomas | B5: Dean of Students | C5: Dean of Students | D5: No accreditation findings attributable to Dean of Students governance | E5: Operational Outcomes | F5: Quality | G5: Data available | H5: 0 | I5: 0 | J5: ≥1 | K5: Tracking | L5: 0 | M5: =IF(K5="Not Tracking","Not Tracked",IF(L5="","No Data",IF(R5="Higher is Better",IF(L5>=S5,"Green",IF(L5>=T5,"Yellow","Red")),IF(R5="Lower is Better",IF(L5<=S5,"Green",IF(L5<=T5,"Yellow","Red")),"Manual Review")))) -> Green | N5: Excel link | O5: Monthly | R5: Lower is Better | S5: 0 | T5: 1 | U5: Higher is Better | V5: Quarterly | W5: Data in report | X5: Pending Review
A6: Steven K. Thomas | B6: Dean of Students | C6: Dean of Students | D6: Annual DOS budget | E6: Operational Outcomes | F6: Cost | G6: Data available | H6: $ | I6: $ | J6: $ | K6: Not Tracking | M6: =IF(K6="Not Tracking","Not Tracked",IF(L6="","No Data",IF(R6="Higher is Better",IF(L6>=S6,"Green",IF(L6>=T6,"Yellow","Red")),IF(R6="Lower is Better",IF(L6<=S6,"Green",IF(L6<=T6,"Yellow","Red")),"Manual Review")))) -> Not Tracked | O6: Monthly | R6: Manual | V6: Annually
A7: Steven K. Thomas | B7: Dean of Students | C7: Dean of Students | D7: Overall student satisfaction (primary) | E7: Student Outcomes | F7: Satisfaction | G7: Data in report | H7: ≥75% | I7: 65% - 75% | J7: < 65% | K7: Tracking | L7: 0.69 | M7: =IF(K7="Not Tracking","Not Tracked",IF(L7="","No Data",IF(R7="Higher is Better",IF(L7>=S7,"Green",IF(L7>=T7,"Yellow","Red")),IF(R7="Lower is Better",IF(L7<=S7,"Green",IF(L7<=T7,"Yellow","Red")),"Manual Review")))) -> Yellow | N7: https://app.powerbi.com/Redirect?action=OpenReport&appId=d4fe7f49-1b93-41aa-9e7d-6ee6d5ec3eb0&reportObjectId=58eb3239-b972-4ee8-8645-fcf195f36c96&ctid=61e6eeb3-5fd7-4aaa-ae3c-61e8deb09b79&reportPage=02d230574060475bc0e4&pbi_source=appShareLink&portalSessionId=90e3d628-0853-431e-a924-80acd7dbd750 | O7: Term | R7: Higher is Better | S7: 0.75 | T7: 0.65 | V7: Term
B8: University Chaplain | C8: Dean of Students | D8: Non-member endorsement completion rate | E8: Operational Outcomes | F8: Speed | G8: Data available | K8: Not Tracking | M8: =IF(K8="Not Tracking","Not Tracked",IF(L8="","No Data",IF(R8="Higher is Better",IF(L8>=S8,"Green",IF(L8>=T8,"Yellow","Red")),IF(R8="Lower is Better",IF(L8<=S8,"Green",IF(L8<=T8,"Yellow","Red")),"Manual Review")))) -> Not Tracked | R8: Manual
B9: University Chaplain | C9: Dean of Students | D9: Number of support cases with non-member endorsement concerns | E9: Operational Outcomes | F9: Quality | G9: Data available | K9: Not Tracking | M9: =IF(K9="Not Tracking","Not Tracked",IF(L9="","No Data",IF(R9="Higher is Better",IF(L9>=S9,"Green",IF(L9>=T9,"Yellow","Red")),IF(R9="Lower is Better",IF(L9<=S9,"Green",IF(L9<=T9,"Yellow","Red")),"Manual Review")))) -> Not Tracked | R9: Manual
A10: Anne Marie Clark | B10: Associate Dean of Students | C10: Dean of Students | D10: Dean of Students response time | E10: Operational Outcomes | F10: Speed | G10: Data available | H10: <5 days | I10: 5 - 7 days | J10: >7 days | K10: Tracking | M10: =IF(K10="Not Tracking","Not Tracked",IF(L10="","No Data",IF(R10="Higher is Better",IF(L10>=S10,"Green",IF(L10>=T10,"Yellow","Red")),IF(R10="Lower is Better",IF(L10<=S10,"Green",IF(L10<=T10,"Yellow","Red")),"Manual Review")))) -> No Data | N10: Excel link | O10: Monthly | R10: Lower is Better | S10: 5 | T10: 7
A11: Anne Marie Clark | B11: Associate Dean of Students | C11: Dean of Students | D11: Dean of Students resolution time | E11: Operational Outcomes | F11: Speed | G11: Data available | K11: Not Tracking | M11: =IF(K11="Not Tracking","Not Tracked",IF(L11="","No Data",IF(R11="Higher is Better",IF(L11>=S11,"Green",IF(L11>=T11,"Yellow","Red")),IF(R11="Lower is Better",IF(L11<=S11,"Green",IF(L11<=T11,"Yellow","Red")),"Manual Review")))) -> Not Tracked | O11: Monthly | R11: Manual
A12: Anne Marie Clark | B12: Associate Dean of Students | C12: Dean of Students | D12: Dean of Students services escalation rates | E12: Operational Outcomes | F12: Quality | G12: Data available | K12: Not Tracking | M12: =IF(K12="Not Tracking","Not Tracked",IF(L12="","No Data",IF(R12="Higher is Better",IF(L12>=S12,"Green",IF(L12>=T12,"Yellow","Red")),IF(R12="Lower is Better",IF(L12<=S12,"Green",IF(L12<=T12,"Yellow","Red")),"Manual Review")))) -> Not Tracked | O12: Monthly | R12: Manual
A13: Anne Marie Clark | B13: Associate Dean of Students | C13: Dean of Students | D13: Partner CSAT | E13: Operational Outcomes | F13: Quality | G13: No data | K13: Not Tracking | M13: =IF(K13="Not Tracking","Not Tracked",IF(L13="","No Data",IF(R13="Higher is Better",IF(L13>=S13,"Green",IF(L13>=T13,"Yellow","Red")),IF(R13="Lower is Better",IF(L13<=S13,"Green",IF(L13<=T13,"Yellow","Red")),"Manual Review")))) -> Not Tracked | O13: Monthly | R13: Manual
A14: Katelyn Ray | B14: Student Honor & Conduct Coordinator | C14: Dean of Students | D14: Honor and Conduct response time | E14: Operational Outcomes | F14: Speed | G14: Data available | H14: <5 days | I14: 5 - 7 days | J14: >7 days | K14: Tracking | M14: =IF(K14="Not Tracking","Not Tracked",IF(L14="","No Data",IF(R14="Higher is Better",IF(L14>=S14,"Green",IF(L14>=T14,"Yellow","Red")),IF(R14="Lower is Better",IF(L14<=S14,"Green",IF(L14<=T14,"Yellow","Red")),"Manual Review")))) -> No Data | N14: Excel link | O14: Monthly | R14: Lower is Better | S14: 5 | T14: 7
A15: Katelyn Ray | B15: Student Honor & Conduct Coordinator | C15: Dean of Students | D15: Honor and Conduct resolution time | E15: Operational Outcomes | F15: Speed | G15: No data | H15: TBD | I15: TBD | J15: TBD | K15: Not Tracking | M15: =IF(K15="Not Tracking","Not Tracked",IF(L15="","No Data",IF(R15="Higher is Better",IF(L15>=S15,"Green",IF(L15>=T15,"Yellow","Red")),IF(R15="Lower is Better",IF(L15<=S15,"Green",IF(L15<=T15,"Yellow","Red")),"Manual Review")))) -> Not Tracked | O15: Monthly | R15: Manual
A16: Katelyn Ray | B16: Student Honor & Conduct Coordinator | C16: Dean of Students | D16: Rate of repeat offenders | E16: Operational Outcomes | F16: Quality | G16: Data available | H16: 0.05 | I16: 0.15 | J16: 0.25 | K16: Tracking | M16: =IF(K16="Not Tracking","Not Tracked",IF(L16="","No Data",IF(R16="Higher is Better",IF(L16>=S16,"Green",IF(L16>=T16,"Yellow","Red")),IF(R16="Lower is Better",IF(L16<=S16,"Green",IF(L16<=T16,"Yellow","Red")),"Manual Review")))) -> No Data | N16: Excel link | O16: Monthly | R16: Lower is Better | S16: 0.05 | T16: 0.25
A17: Sandra Wurttele | B17: Student Accessibility Coordinator | C17: Dean of Students | D17: Accommodation determination processing rate | E17: Operational Outcomes | F17: Speed | G17: Data available | H17: <5 days | I17: 5 - 7 days | J17: >7 days | K17: Not Tracking | M17: =IF(K17="Not Tracking","Not Tracked",IF(L17="","No Data",IF(R17="Higher is Better",IF(L17>=S17,"Green",IF(L17>=T17,"Yellow","Red")),IF(R17="Lower is Better",IF(L17<=S17,"Green",IF(L17<=T17,"Yellow","Red")),"Manual Review")))) -> Not Tracked | N17: Excel link | O17: Monthly | R17: Lower is Better | S17: 5 | T17: 7
A18: Sandra Wurttele | B18: Student Accessibility Coordinator | C18: Dean of Students | D18: Accommodation resolution rate | E18: Operational Outcomes | F18: Speed | G18: Data available | H18: <3 days | I18: 3 - 6 days | J18: > 6 days | K18: Not Tracking | M18: =IF(K18="Not Tracking","Not Tracked",IF(L18="","No Data",IF(R18="Higher is Better",IF(L18>=S18,"Green",IF(L18>=T18,"Yellow","Red")),IF(R18="Lower is Better",IF(L18<=S18,"Green",IF(L18<=T18,"Yellow","Red")),"Manual Review")))) -> Not Tracked | N18: Excel link | O18: Monthly | R18: Lower is Better | S18: 3 | T18: 6
A19: Sandra Wurttele | B19: Student Accessibility Coordinator | C19: Dean of Students | D19: ADA and Section 504 standard compliance rate | E19: Operational Outcomes | F19: Quality | G19: Data available | H19: - | I19: - | J19: - | K19: Not Tracking | M19: =IF(K19="Not Tracking","Not Tracked",IF(L19="","No Data",IF(R19="Higher is Better",IF(L19>=S19,"Green",IF(L19>=T19,"Yellow","Red")),IF(R19="Lower is Better",IF(L19<=S19,"Green",IF(L19<=T19,"Yellow","Red")),"Manual Review")))) -> Not Tracked | O19: Monthly | R19: Manual
A20: Sandra Wurttele | B20: Student Accessibility Coordinator | C20: Dean of Students | D20: ADA and Section 504 Audit compliance rate | E20: Operational Outcomes | F20: Quality | G20: Data available | H20: - | I20: - | J20: - | K20: Not Tracking | M20: =IF(K20="Not Tracking","Not Tracked",IF(L20="","No Data",IF(R20="Higher is Better",IF(L20>=S20,"Green",IF(L20>=T20,"Yellow","Red")),IF(R20="Lower is Better",IF(L20<=S20,"Green",IF(L20<=T20,"Yellow","Red")),"Manual Review")))) -> Not Tracked | O20: Monthly | R20: Manual
A21: Ana De Castro | B21: Student Belonging Coordinator | C21: Dean of Students | D21: Discrimination resolution rate | E21: Operational Outcomes | F21: Quality | G21: Data available | H21: - | I21: - | J21: - | K21: Not Tracking | M21: =IF(K21="Not Tracking","Not Tracked",IF(L21="","No Data",IF(R21="Higher is Better",IF(L21>=S21,"Green",IF(L21>=T21,"Yellow","Red")),IF(R21="Lower is Better",IF(L21<=S21,"Green",IF(L21<=T21,"Yellow","Red")),"Manual Review")))) -> Not Tracked | O21: Monthly | R21: Manual
A22: Ana De Castro | B22: Student Belonging Coordinator | C22: Dean of Students | D22: Student sentiment on belonging | E22: Operational Outcomes | F22: Quality | G22: No data | H22: NA | I22: NA | J22: NA | K22: Not Tracking | M22: =IF(K22="Not Tracking","Not Tracked",IF(L22="","No Data",IF(R22="Higher is Better",IF(L22>=S22,"Green",IF(L22>=T22,"Yellow","Red")),IF(R22="Lower is Better",IF(L22<=S22,"Green",IF(L22<=T22,"Yellow","Red")),"Manual Review")))) -> Not Tracked | O22: Monthly | R22: Manual
A23: Ana De Castro | B23: Student Belonging Coordinator | C23: Dean of Students | D23: CSAT for Student Belonging | E23: Operational Outcomes | F23: Quality | G23: No data | H23: NA | I23: NA | J23: NA | K23: Not Tracking | M23: =IF(K23="Not Tracking","Not Tracked",IF(L23="","No Data",IF(R23="Higher is Better",IF(L23>=S23,"Green",IF(L23>=T23,"Yellow","Red")),IF(R23="Lower is Better",IF(L23<=S23,"Green",IF(L23<=T23,"Yellow","Red")),"Manual Review")))) -> Not Tracked | O23: Monthly | R23: Manual
A24: Ana De Castro | B24: Student Belonging Coordinator | C24: Dean of Students | D24: X% of non-member ecclesiastical endorsements completed with X days | E24: Operational Outcomes | F24: Speed | G24: Speed | K24: Not Tracking | M24: =IF(K24="Not Tracking","Not Tracked",IF(L24="","No Data",IF(R24="Higher is Better",IF(L24>=S24,"Green",IF(L24>=T24,"Yellow","Red")),IF(R24="Lower is Better",IF(L24<=S24,"Green",IF(L24<=T24,"Yellow","Red")),"Manual Review")))) -> Not Tracked | O24: Monthly | R24: Manual
A25: Helen Reboucas | B25: Student Grievance Coordinator | C25: Dean of Students | D25: Student grievance case resolution time | E25: Operational Outcomes | F25: Speed | G25: Speed | H25: <5 days | I25: 5 - 7 days | J25: >7 days | K25: Not Tracking | M25: =IF(K25="Not Tracking","Not Tracked",IF(L25="","No Data",IF(R25="Higher is Better",IF(L25>=S25,"Green",IF(L25>=T25,"Yellow","Red")),IF(R25="Lower is Better",IF(L25<=S25,"Green",IF(L25<=T25,"Yellow","Red")),"Manual Review")))) -> Not Tracked | N25: Excel link | O25: Monthly | R25: Lower is Better | S25: 5 | T25: 7
A26: Helen Reboucas | B26: Student Grievance Coordinator | C26: Dean of Students | D26: Grievance QA | E26: Operational Outcomes | F26: Quality | G26: Data available | H26: < 90% | I26: 70% - 90% | J26: < 70% | K26: Tracking | M26: =IF(K26="Not Tracking","Not Tracked",IF(L26="","No Data",IF(R26="Higher is Better",IF(L26>=S26,"Green",IF(L26>=T26,"Yellow","Red")),IF(R26="Lower is Better",IF(L26<=S26,"Green",IF(L26<=T26,"Yellow","Red")),"Manual Review")))) -> No Data | N26: Excel link | O26: Monthly | R26: Higher is Better | S26: 0.9 | T26: 0.7
A27: Joseph Bentum | B27: Student Crisis Coordinator | C27: Dean of Students | D27: Crisis response time | E27: Operational Outcomes | F27: Speed | G27: Data available | H27: < 24 hours | I27: 24 - 48 hours | J27: > 48 hours | K27: Tracking | M27: =IF(K27="Not Tracking","Not Tracked",IF(L27="","No Data",IF(R27="Higher is Better",IF(L27>=S27,"Green",IF(L27>=T27,"Yellow","Red")),IF(R27="Lower is Better",IF(L27<=S27,"Green",IF(L27<=T27,"Yellow","Red")),"Manual Review")))) -> No Data | N27: Excel link | O27: Monthly | R27: Lower is Better | S27: 24 | T27: 48
A28: Mark Gefrom | B28: Director of Student Support | C28: Records, Registration, Support | D28: Teams meeting or exceeding response service-level agreements | E28: Operational Outcomes | F28: Speed | G28: Data in report | H28: < 24 hours | I28: 24 - 48 hours | J28: > 48 hours | K28: Tracking | M28: =IF(K28="Not Tracking","Not Tracked",IF(L28="","No Data",IF(R28="Higher is Better",IF(L28>=S28,"Green",IF(L28>=T28,"Yellow","Red")),IF(R28="Lower is Better",IF(L28<=S28,"Green",IF(L28<=T28,"Yellow","Red")),"Manual Review")))) -> No Data | O28: Monthly | R28: Lower is Better | S28: 24 | T28: 48
A29: Mark Gefrom | B29: Director of Student Support | C29: Records, Registration, Support | D29: Teams meeting or exceeding resolution service-level agreements | E29: Operational Outcomes | F29: Speed | G29: Data in report | H29: <48 hours | I29: 48 - 72 hours | J29: > 72 hours | K29: Tracking | M29: =IF(K29="Not Tracking","Not Tracked",IF(L29="","No Data",IF(R29="Higher is Better",IF(L29>=S29,"Green",IF(L29>=T29,"Yellow","Red")),IF(R29="Lower is Better",IF(L29<=S29,"Green",IF(L29<=T29,"Yellow","Red")),"Manual Review")))) -> No Data | O29: Monthly | R29: Lower is Better | S29: 48 | T29: 72
A30: Mark Gefrom | B30: Director of Student Support | C30: Records, Registration, Support | D30: Teams meeting QA service-level agreements | E30: Operational Outcomes | F30: Quality | G30: Data in report | H30: ≥90% | I30: 85% - 90% | J30: < 85% | K30: Tracking | M30: =IF(K30="Not Tracking","Not Tracked",IF(L30="","No Data",IF(R30="Higher is Better",IF(L30>=S30,"Green",IF(L30>=T30,"Yellow","Red")),IF(R30="Lower is Better",IF(L30<=S30,"Green",IF(L30<=T30,"Yellow","Red")),"Manual Review")))) -> No Data | O30: Monthly | R30: Higher is Better | S30: 0.9 | T30: 0.85
A31: Mark Gefrom | B31: Director of Student Support | C31: Records, Registration, Support | D31: Teams meeting CSAT service-level agreements | E31: Operational Outcomes | F31: Quality | G31: Data in report | H31: ≥85% | I31: 80% - 85% | J31: <80% | K31: Tracking | M31: =IF(K31="Not Tracking","Not Tracked",IF(L31="","No Data",IF(R31="Higher is Better",IF(L31>=S31,"Green",IF(L31>=T31,"Yellow","Red")),IF(R31="Lower is Better",IF(L31<=S31,"Green",IF(L31<=T31,"Yellow","Red")),"Manual Review")))) -> No Data | O31: Monthly | R31: Higher is Better | S31: 0.85 | T31: 0.8
A32: Mark Gefrom | B32: Director of Student Support | C32: Records, Registration, Support | D32: Teams meeting first contact resolution service-level agreements | E32: Operational Outcomes | F32: Quality | G32: Data in report | H32: ≥90% | I32: 85% - 90% | J32: <85% | K32: Tracking | M32: =IF(K32="Not Tracking","Not Tracked",IF(L32="","No Data",IF(R32="Higher is Better",IF(L32>=S32,"Green",IF(L32>=T32,"Yellow","Red")),IF(R32="Lower is Better",IF(L32<=S32,"Green",IF(L32<=T32,"Yellow","Red")),"Manual Review")))) -> No Data | O32: Monthly | R32: Higher is Better | S32: 0.9 | T32: 0.85
A33: Mark Gefrom | B33: Director of Student Support | C33: Records, Registration, Support | D33: Student records, registration, and support department budget | E33: Operational Outcomes | F33: Cost | G33: Data available | H33: $ | I33: $ | J33: $ | K33: Not Tracking | M33: =IF(K33="Not Tracking","Not Tracked",IF(L33="","No Data",IF(R33="Higher is Better",IF(L33>=S33,"Green",IF(L33>=T33,"Yellow","Red")),IF(R33="Lower is Better",IF(L33<=S33,"Green",IF(L33<=T33,"Yellow","Red")),"Manual Review")))) -> Not Tracked | O33: Monthly | R33: Manual
A34: Mark Gefrom | B34: Director of Student Support | C34: Records, Registration, Support | D34: Overall student autonomy (primary) | E34: Student Outcomes | F34: Autonomy | G34: Data in report | H34: ≥85% | I34: 80% - 85% | J34: < 80% | K34: Tracking | L34: 0.67 | M34: =IF(K34="Not Tracking","Not Tracked",IF(L34="","No Data",IF(R34="Higher is Better",IF(L34>=S34,"Green",IF(L34>=T34,"Yellow","Red")),IF(R34="Lower is Better",IF(L34<=S34,"Green",IF(L34<=T34,"Yellow","Red")),"Manual Review")))) -> Red | N34: https://app.powerbi.com/groups/me/apps/d4fe7f49-1b93-41aa-9e7d-6ee6d5ec3eb0/reports/fcf13746-fad2-48de-9d61-a4ab0ae71022/90333e1e71861247c683?experience=power-bi | O34: Monthly | R34: Higher is Better | S34: 0.85 | T34: 0.8
A35: Mark Gefrom | B35: Director of Student Support | C35: Records, Registration, Support | D35: Overall student satisfaction (secondary) | E35: Student Outcomes | F35: Satisfaction | G35: Data in report | H35: ≥75% | I35: 65% - 75% | J35: < 65% | K35: Tracking | L35: 0.82 | M35: =IF(K35="Not Tracking","Not Tracked",IF(L35="","No Data",IF(R35="Higher is Better",IF(L35>=S35,"Green",IF(L35>=T35,"Yellow","Red")),IF(R35="Lower is Better",IF(L35<=S35,"Green",IF(L35<=T35,"Yellow","Red")),"Manual Review")))) -> Green | N35: https://app.powerbi.com/Redirect?action=OpenReport&appId=d4fe7f49-1b93-41aa-9e7d-6ee6d5ec3eb0&reportObjectId=58eb3239-b972-4ee8-8645-fcf195f36c96&ctid=61e6eeb3-5fd7-4aaa-ae3c-61e8deb09b79&reportPage=02d230574060475bc0e4&pbi_source=appShareLink&portalSessionId=90e3d628-0853-431e-a924-80acd7dbd750 | O35: Term | R35: Higher is Better | S35: 0.75 | T35: 0.65
A36: Brad Lester | B36: Senior Manager of Student Support | C36: Records, Registration, Support | D36: Student support budget | E36: Operational Outcomes | F36: Cost | G36: Data available | H36: $ | I36: $ | J36: $ | K36: Not Tracking | M36: =IF(K36="Not Tracking","Not Tracked",IF(L36="","No Data",IF(R36="Higher is Better",IF(L36>=S36,"Green",IF(L36>=T36,"Yellow","Red")),IF(R36="Lower is Better",IF(L36<=S36,"Green",IF(L36<=T36,"Yellow","Red")),"Manual Review")))) -> Not Tracked | O36: Monthly | R36: Manual
A37: Brad Lester | B37: Senior Manager of Student Support | C37: Records, Registration, Support | D37: Autonomy rate for student support cases | E37: Student Outcomes | F37: Autonomy | G37: Data in report | H37: 100% - 85% | I37: 84% - 70% | J37: 0.69 | K37: Tracking | M37: =IF(K37="Not Tracking","Not Tracked",IF(L37="","No Data",IF(R37="Higher is Better",IF(L37>=S37,"Green",IF(L37>=T37,"Yellow","Red")),IF(R37="Lower is Better",IF(L37<=S37,"Green",IF(L37<=T37,"Yellow","Red")),"Manual Review")))) -> No Data | N37: https://app.powerbi.com/groups/me/apps/d4fe7f49-1b93-41aa-9e7d-6ee6d5ec3eb0/reports/fcf13746-fad2-48de-9d61-a4ab0ae71022/90333e1e71861247c683?experience=power-bi | O37: Monthly | R37: Higher is Better | S37: 1 | T37: 0.69
A38: Alyssa Burrell | B38: Student Support Coordinator | C38: Records, Registration, Support | D38: General support case response rate | E38: Operational Outcomes | F38: Speed | G38: Data in report | H38: 1-3 Days | I38: 4-5 Days | J38: 5+ Days | K38: Tracking | M38: =IF(K38="Not Tracking","Not Tracked",IF(L38="","No Data",IF(R38="Higher is Better",IF(L38>=S38,"Green",IF(L38>=T38,"Yellow","Red")),IF(R38="Lower is Better",IF(L38<=S38,"Green",IF(L38<=T38,"Yellow","Red")),"Manual Review")))) -> No Data | N38: https://app.powerbi.com/groups/4f9c84ba-b5d3-4eda-a86b-41fbb3b3bc4a/reports/af9ba6b3-8092-4e0c-bb52-4f8903b1b861/acd0ee0b785069a6a598?experience=power-bi | O38: Monthly | R38: Lower is Better | S38: 3 | T38: 5
A39: Alyssa Burrell | B39: Student Support Coordinator | C39: Records, Registration, Support | D39: General support case resolution rate | E39: Operational Outcomes | F39: Speed | G39: Data in report | H39: ≥ 90% | I39: 80-90% | J39: < 80% | K39: Not Tracking | M39: =IF(K39="Not Tracking","Not Tracked",IF(L39="","No Data",IF(R39="Higher is Better",IF(L39>=S39,"Green",IF(L39>=T39,"Yellow","Red")),IF(R39="Lower is Better",IF(L39<=S39,"Green",IF(L39<=T39,"Yellow","Red")),"Manual Review")))) -> Not Tracked | N39: https://app.powerbi.com/groups/4f9c84ba-b5d3-4eda-a86b-41fbb3b3bc4a/reports/af9ba6b3-8092-4e0c-bb52-4f8903b1b861/acd0ee0b785069a6a598?experience=power-bi | O39: Monthly | R39: Higher is Better | S39: 0.9 | T39: 0.8
A40: Alyssa Burrell | B40: Student Support Coordinator | C40: Records, Registration, Support | D40: Phone answer speed | E40: Operational Outcomes | F40: Speed | G40: Data in report | H40: < 1 minute | I40: 2-5 minutes | J40: 5+ minutes | K40: Tracking | L40: 3 minutes | M40: =IF(K40="Not Tracking","Not Tracked",IF(L40="","No Data",IF(R40="Higher is Better",IF(L40>=S40,"Green",IF(L40>=T40,"Yellow","Red")),IF(R40="Lower is Better",IF(L40<=S40,"Green",IF(L40<=T40,"Yellow","Red")),"Manual Review")))) -> Red | N40: https://app.powerbi.com/groups/4f9c84ba-b5d3-4eda-a86b-41fbb3b3bc4a/reports/af9ba6b3-8092-4e0c-bb52-4f8903b1b861/ec6a4f4305973947e908?experience=power-bi | O40: Monthly | R40: Lower is Better | S40: 1 | T40: 5
A41: Alyssa Burrell | B41: Student Support Coordinator | C41: Records, Registration, Support | D41: Phone handle rate | E41: Operational Outcomes | F41: Speed | G41: Data in report | H41: ≥ 90% | I41: 80-89% | J41: < 80% | K41: Tracking | L41: 0.825 | M41: =IF(K41="Not Tracking","Not Tracked",IF(L41="","No Data",IF(R41="Higher is Better",IF(L41>=S41,"Green",IF(L41>=T41,"Yellow","Red")),IF(R41="Lower is Better",IF(L41<=S41,"Green",IF(L41<=T41,"Yellow","Red")),"Manual Review")))) -> Yellow | N41: https://app.powerbi.com/groups/4f9c84ba-b5d3-4eda-a86b-41fbb3b3bc4a/reports/af9ba6b3-8092-4e0c-bb52-4f8903b1b861/ec6a4f4305973947e908?experience=power-bi | O41: Monthly | R41: Higher is Better | S41: 0.9 | T41: 0.8
A42: Alyssa Burrell | B42: Student Support Coordinator | C42: Records, Registration, Support | D42: Agent availability | E42: Operational Outcomes | F42: Speed | G42: Data in report | H42: ≥ 80% | I42: 75 - 79 % | J42: < 75% | K42: Tracking | L42: 0.96 | M42: =IF(K42="Not Tracking","Not Tracked",IF(L42="","No Data",IF(R42="Higher is Better",IF(L42>=S42,"Green",IF(L42>=T42,"Yellow","Red")),IF(R42="Lower is Better",IF(L42<=S42,"Green",IF(L42<=T42,"Yellow","Red")),"Manual Review")))) -> Green | N42: https://app.powerbi.com/groups/4f9c84ba-b5d3-4eda-a86b-41fbb3b3bc4a/reports/af9ba6b3-8092-4e0c-bb52-4f8903b1b861/ec6a4f4305973947e908?experience=power-bi | O42: Monthly | R42: Higher is Better | S42: 0.8 | T42: 0.75
A43: Alyssa Burrell | B43: Student Support Coordinator | C43: Records, Registration, Support | D43: Phone support QA | E43: Operational Outcomes | F43: Quality | G43: Data in report | H43: ≥ 80% | I43: 75-85% | J43: < 75% | K43: Tracking | L43: 0.98 | M43: =IF(K43="Not Tracking","Not Tracked",IF(L43="","No Data",IF(R43="Higher is Better",IF(L43>=S43,"Green",IF(L43>=T43,"Yellow","Red")),IF(R43="Lower is Better",IF(L43<=S43,"Green",IF(L43<=T43,"Yellow","Red")),"Manual Review")))) -> Green | N43: https://app.powerbi.com/groups/4f9c84ba-b5d3-4eda-a86b-41fbb3b3bc4a/reports/af9ba6b3-8092-4e0c-bb52-4f8903b1b861/1afb91a1da6d47c71041?experience=power-bi | O43: Monthly | R43: Higher is Better | S43: 0.8 | T43: 0.75
A44: Alyssa Burrell | B44: Student Support Coordinator | C44: Records, Registration, Support | D44: Phone support CSAT | E44: Operational Outcomes | F44: Quality | G44: Data in report | H44: ≥ 80% | I44: 75-85% | J44: < 75% | K44: Tracking | L44: 0.77 | M44: =IF(K44="Not Tracking","Not Tracked",IF(L44="","No Data",IF(R44="Higher is Better",IF(L44>=S44,"Green",IF(L44>=T44,"Yellow","Red")),IF(R44="Lower is Better",IF(L44<=S44,"Green",IF(L44<=T44,"Yellow","Red")),"Manual Review")))) -> Yellow | N44: https://app.powerbi.com/groups/4f9c84ba-b5d3-4eda-a86b-41fbb3b3bc4a/reports/af9ba6b3-8092-4e0c-bb52-4f8903b1b861/77b2e5ed1050bc711c70?experience=power-bi | O44: Monthly | R44: Higher is Better | S44: 0.8 | T44: 0.75
A45: Alyssa Burrell | B45: Student Support Coordinator | C45: Records, Registration, Support | D45: Phone support first contact resolution | E45: Operational Outcomes | F45: Quality | G45: Data in report | H45: ≥ 90% | I45: 80-90% | J45: < 80% | K45: Tracking | L45: 0.97 | M45: =IF(K45="Not Tracking","Not Tracked",IF(L45="","No Data",IF(R45="Higher is Better",IF(L45>=S45,"Green",IF(L45>=T45,"Yellow","Red")),IF(R45="Lower is Better",IF(L45<=S45,"Green",IF(L45<=T45,"Yellow","Red")),"Manual Review")))) -> Green | N45: https://app.powerbi.com/groups/4f9c84ba-b5d3-4eda-a86b-41fbb3b3bc4a/reports/af9ba6b3-8092-4e0c-bb52-4f8903b1b861/acd0ee0b785069a6a598?experience=power-bi | O45: Monthly | R45: Higher is Better | S45: 0.9 | T45: 0.8
A46: Hilary Bagley | B46: Training & Quality Assurance Manager | C46: Records, Registration, Support | D46: Request-to-KB publish rate | E46: Operational Outcomes | F46: Speed | G46: No data | H46: NA | I46: NA | J46: NA | K46: Not Tracking | M46: =IF(K46="Not Tracking","Not Tracked",IF(L46="","No Data",IF(R46="Higher is Better",IF(L46>=S46,"Green",IF(L46>=T46,"Yellow","Red")),IF(R46="Lower is Better",IF(L46<=S46,"Green",IF(L46<=T46,"Yellow","Red")),"Manual Review")))) -> Not Tracked | O46: Monthly | R46: Manual
A47: Hilary Bagley | B47: Training & Quality Assurance Manager | C47: Records, Registration, Support | D47: QA feedback cycle rate | E47: Operational Outcomes | F47: Speed | G47: Data in report | K47: Tracking | M47: =IF(K47="Not Tracking","Not Tracked",IF(L47="","No Data",IF(R47="Higher is Better",IF(L47>=S47,"Green",IF(L47>=T47,"Yellow","Red")),IF(R47="Lower is Better",IF(L47<=S47,"Green",IF(L47<=T47,"Yellow","Red")),"Manual Review")))) -> No Data | N47: https://app.powerbi.com/groups/4f9c84ba-b5d3-4eda-a86b-41fbb3b3bc4a/reports/af9ba6b3-8092-4e0c-bb52-4f8903b1b861/4c2855c01a3caaf171d0?experience=power-bi | O47: Monthly | R47: Manual
A48: Hilary Bagley | B48: Training & Quality Assurance Manager | C48: Records, Registration, Support | D48: QA calibration consistency rate | E48: Operational Outcomes | F48: Quality | G48: No data | H48: NA | I48: NA | J48: NA | K48: Not Tracking | M48: =IF(K48="Not Tracking","Not Tracked",IF(L48="","No Data",IF(R48="Higher is Better",IF(L48>=S48,"Green",IF(L48>=T48,"Yellow","Red")),IF(R48="Lower is Better",IF(L48<=S48,"Green",IF(L48<=T48,"Yellow","Red")),"Manual Review")))) -> Not Tracked | O48: Monthly | R48: Manual
A49: Hilary Bagley | B49: Training & Quality Assurance Manager | C49: Records, Registration, Support | D49: Knowledge Base audit pass rate | E49: Operational Outcomes | F49: Quality | G49: No data | H49: NA | I49: NA | J49: NA | K49: Not Tracking | M49: =IF(K49="Not Tracking","Not Tracked",IF(L49="","No Data",IF(R49="Higher is Better",IF(L49>=S49,"Green",IF(L49>=T49,"Yellow","Red")),IF(R49="Lower is Better",IF(L49<=S49,"Green",IF(L49<=T49,"Yellow","Red")),"Manual Review")))) -> Not Tracked | O49: Monthly | R49: Manual
A50: Hilary Bagley | B50: Training & Quality Assurance Manager | C50: Records, Registration, Support | D50: QA team lead feedback success rate | E50: Operational Outcomes | F50: Quality | G50: Data in report | K50: Tracking | L50: 0.8324 | M50: =IF(K50="Not Tracking","Not Tracked",IF(L50="","No Data",IF(R50="Higher is Better",IF(L50>=S50,"Green",IF(L50>=T50,"Yellow","Red")),IF(R50="Lower is Better",IF(L50<=S50,"Green",IF(L50<=T50,"Yellow","Red")),"Manual Review")))) -> Manual Review | N50: https://app.powerbi.com/groups/4f9c84ba-b5d3-4eda-a86b-41fbb3b3bc4a/reports/af9ba6b3-8092-4e0c-bb52-4f8903b1b861/4c2855c01a3caaf171d0?experience=power-bi | O50: Monthly | R50: Manual
A51: Hilary Bagley | B51: Training & Quality Assurance Manager | C51: Records, Registration, Support | D51: Cost per QA Evaluation ($ per Evaluation) | E51: Operational Outcomes | F51: Cost | G51: Data available | H51: $ | I51: $ | J51: $ | K51: Not Tracking | M51: =IF(K51="Not Tracking","Not Tracked",IF(L51="","No Data",IF(R51="Higher is Better",IF(L51>=S51,"Green",IF(L51>=T51,"Yellow","Red")),IF(R51="Lower is Better",IF(L51<=S51,"Green",IF(L51<=T51,"Yellow","Red")),"Manual Review")))) -> Not Tracked | O51: Monthly | R51: Manual
A52: Hilary Bagley | B52: Training & Quality Assurance Manager | C52: Records, Registration, Support | D52: Cost per KB Article Maintained ($ per Article Updated or Audited) | E52: Operational Outcomes | F52: Cost | G52: Data available | H52: $ | I52: $ | J52: $ | K52: Not Tracking | M52: =IF(K52="Not Tracking","Not Tracked",IF(L52="","No Data",IF(R52="Higher is Better",IF(L52>=S52,"Green",IF(L52>=T52,"Yellow","Red")),IF(R52="Lower is Better",IF(L52<=S52,"Green",IF(L52<=T52,"Yellow","Red")),"Manual Review")))) -> Not Tracked | O52: Monthly | R52: Manual
A53: Kira Hayes | B53: Training & Quality Assurance Coordinator | C53: Records, Registration, Support | D53: KB publishing rate | E53: Operational Outcomes | F53: Speed | G53: No data | H53: NA | I53: NA | J53: NA | K53: Not Tracking | M53: =IF(K53="Not Tracking","Not Tracked",IF(L53="","No Data",IF(R53="Higher is Better",IF(L53>=S53,"Green",IF(L53>=T53,"Yellow","Red")),IF(R53="Lower is Better",IF(L53<=S53,"Green",IF(L53<=T53,"Yellow","Red")),"Manual Review")))) -> Not Tracked | O53: Monthly | R53: Manual
A54: Kira Hayes | B54: Training & Quality Assurance Coordinator | C54: Records, Registration, Support | D54: QA evaluation completion rate | E54: Operational Outcomes | F54: Quality | G54: No data | H54: NA | I54: NA | J54: NA | K54: Not Tracking | M54: =IF(K54="Not Tracking","Not Tracked",IF(L54="","No Data",IF(R54="Higher is Better",IF(L54>=S54,"Green",IF(L54>=T54,"Yellow","Red")),IF(R54="Lower is Better",IF(L54<=S54,"Green",IF(L54<=T54,"Yellow","Red")),"Manual Review")))) -> Not Tracked | O54: Monthly | R54: Manual
A55: Kira Hayes | B55: Training & Quality Assurance Coordinator | C55: Records, Registration, Support | D55: DSAT and critical violation delivery rate | E55: Operational Outcomes | F55: Quality | G55: No data | H55: NA | I55: NA | J55: NA | K55: Not Tracking | M55: =IF(K55="Not Tracking","Not Tracked",IF(L55="","No Data",IF(R55="Higher is Better",IF(L55>=S55,"Green",IF(L55>=T55,"Yellow","Red")),IF(R55="Lower is Better",IF(L55<=S55,"Green",IF(L55<=T55,"Yellow","Red")),"Manual Review")))) -> Not Tracked | O55: Monthly | R55: Manual
A56: Matthew Smith | B56: Technical Support Manager | C56: Records, Registration, Support | D56: Tech support case resolution rate | E56: Operational Outcomes | F56: Speed | G56: Data in report | H56: 3 business days | I56: 5 business days | J56: > 10 business days | K56: Not Tracking | M56: =IF(K56="Not Tracking","Not Tracked",IF(L56="","No Data",IF(R56="Higher is Better",IF(L56>=S56,"Green",IF(L56>=T56,"Yellow","Red")),IF(R56="Lower is Better",IF(L56<=S56,"Green",IF(L56<=T56,"Yellow","Red")),"Manual Review")))) -> Not Tracked | N56: https://app.powerbi.com/groups/4f9c84ba-b5d3-4eda-a86b-41fbb3b3bc4a/reports/af9ba6b3-8092-4e0c-bb52-4f8903b1b861/acd0ee0b785069a6a598?experience=power-bi | O56: Monthly | R56: Lower is Better | S56: 3 | T56: 10
A57: Matthew Smith | B57: Technical Support Manager | C57: Records, Registration, Support | D57: Tech support costs | E57: Operational Outcomes | F57: Cost | G57: Data available | H57: $ | I57: $ | J57: $ | K57: Not Tracking | M57: =IF(K57="Not Tracking","Not Tracked",IF(L57="","No Data",IF(R57="Higher is Better",IF(L57>=S57,"Green",IF(L57>=T57,"Yellow","Red")),IF(R57="Lower is Better",IF(L57<=S57,"Green",IF(L57<=T57,"Yellow","Red")),"Manual Review")))) -> Not Tracked | O57: Monthly | R57: Manual
A58: Matthew Smith | B58: Technical Support Manager | C58: Records, Registration, Support | D58: Autonomy rate for tech support cases | E58: Student Outcomes | F58: Autonomy | G58: Data in report | H58: 0 | I58: 0 | J58: 0 | K58: Not Tracking | M58: =IF(K58="Not Tracking","Not Tracked",IF(L58="","No Data",IF(R58="Higher is Better",IF(L58>=S58,"Green",IF(L58>=T58,"Yellow","Red")),IF(R58="Lower is Better",IF(L58<=S58,"Green",IF(L58<=T58,"Yellow","Red")),"Manual Review")))) -> Not Tracked | N58: https://app.powerbi.com/groups/me/apps/d4fe7f49-1b93-41aa-9e7d-6ee6d5ec3eb0/reports/20549c98-8ffc-4600-b08a-67e5f927e9d6/23134ede7649a89fe09c?experience=power-bi | O58: Monthly | R58: Manual
A59: Colby Warner | B59: Product Support Engineer | C59: Records, Registration, Support | D59: Escalated case resolution rate | E59: Operational Outcomes | F59: Speed | G59: Data in report | H59: 90-100% | I59: 75-90% | J59: < 75% | K59: Not Tracking | M59: =IF(K59="Not Tracking","Not Tracked",IF(L59="","No Data",IF(R59="Higher is Better",IF(L59>=S59,"Green",IF(L59>=T59,"Yellow","Red")),IF(R59="Lower is Better",IF(L59<=S59,"Green",IF(L59<=T59,"Yellow","Red")),"Manual Review")))) -> Not Tracked | N59: https://app.powerbi.com/groups/me/apps/d4fe7f49-1b93-41aa-9e7d-6ee6d5ec3eb0/reports/1d513597-8eb5-4912-8692-96ff2a683a51/0209ae92d2720717522a?experience=power-bi | O59: Monthly | R59: Higher is Better | S59: 0.9 | T59: 0.75
A60: Colby Warner | B60: Product Support Engineer | C60: Records, Registration, Support | D60: Tech Support case QA | E60: Operational Outcomes | F60: Quality | G60: Data in report | H60: 90-100% | I60: 80-90% | J60: <80% | K60: Tracking | L60: 0.94 | M60: =IF(K60="Not Tracking","Not Tracked",IF(L60="","No Data",IF(R60="Higher is Better",IF(L60>=S60,"Green",IF(L60>=T60,"Yellow","Red")),IF(R60="Lower is Better",IF(L60<=S60,"Green",IF(L60<=T60,"Yellow","Red")),"Manual Review")))) -> Green | N60: https://app.powerbi.com/groups/me/apps/d4fe7f49-1b93-41aa-9e7d-6ee6d5ec3eb0/reports/1d513597-8eb5-4912-8692-96ff2a683a51/0209ae92d2720717522a?experience=power-bi | O60: Monthly | R60: Higher is Better | S60: 0.9 | T60: 0.8
A61: Colby Warner | B61: Product Support Engineer | C61: Records, Registration, Support | D61: Tech Support case CSAT | E61: Operational Outcomes | F61: Quality | G61: Data in report | H61: 90-100% | I61: 80-90% | J61: <80% | K61: Tracking | L61: 0.778 | M61: =IF(K61="Not Tracking","Not Tracked",IF(L61="","No Data",IF(R61="Higher is Better",IF(L61>=S61,"Green",IF(L61>=T61,"Yellow","Red")),IF(R61="Lower is Better",IF(L61<=S61,"Green",IF(L61<=T61,"Yellow","Red")),"Manual Review")))) -> Red | N61: https://app.powerbi.com/groups/4f9c84ba-b5d3-4eda-a86b-41fbb3b3bc4a/reports/af9ba6b3-8092-4e0c-bb52-4f8903b1b861/77b2e5ed1050bc711c70?experience=power-bi | O61: Monthly | R61: Higher is Better | S61: 0.9 | T61: 0.8
A62: Colby Warner | B62: Product Support Engineer | C62: Records, Registration, Support | D62: Tech Support case first contact resolution | E62: Operational Outcomes | F62: Quality | G62: Data in report | H62: 90-100% | I62: 75-90% | J62: < 75% | K62: Tracking | L62: 0.96 | M62: =IF(K62="Not Tracking","Not Tracked",IF(L62="","No Data",IF(R62="Higher is Better",IF(L62>=S62,"Green",IF(L62>=T62,"Yellow","Red")),IF(R62="Lower is Better",IF(L62<=S62,"Green",IF(L62<=T62,"Yellow","Red")),"Manual Review")))) -> Green | N62: https://app.powerbi.com/groups/me/apps/d4fe7f49-1b93-41aa-9e7d-6ee6d5ec3eb0/reports/1d513597-8eb5-4912-8692-96ff2a683a51/0209ae92d2720717522a?experience=power-bi | O62: Monthly | R62: Higher is Better | S62: 0.9 | T62: 0.75
A63: Kari Johnson | B63: Registrar | C63: Records, Registration, Support | D63: Registrar budget | E63: Operational Outcomes | F63: Cost | G63: Data available | H63: $ | I63: $ | J63: $ | K63: Not Tracking | M63: =IF(K63="Not Tracking","Not Tracked",IF(L63="","No Data",IF(R63="Higher is Better",IF(L63>=S63,"Green",IF(L63>=T63,"Yellow","Red")),IF(R63="Lower is Better",IF(L63<=S63,"Green",IF(L63<=T63,"Yellow","Red")),"Manual Review")))) -> Not Tracked | O63: Monthly | R63: Manual
A64: Kari Johnson | B64: Registrar | C64: Records, Registration, Support | D64: Autonomy for student registration (% students registered without submitting a support request) | E64: Student Outcomes | F64: Autonomy | G64: Data available | H64: 90-100% | I64: 75-90% | J64: <75% | K64: Tracking | M64: =IF(K64="Not Tracking","Not Tracked",IF(L64="","No Data",IF(R64="Higher is Better",IF(L64>=S64,"Green",IF(L64>=T64,"Yellow","Red")),IF(R64="Lower is Better",IF(L64<=S64,"Green",IF(L64<=T64,"Yellow","Red")),"Manual Review")))) -> No Data | N64: https://grafanapathway-bvcefagkg2gtgzb6.eus.grafana.azure.com/d/edt8uho6bh0jkc/anthology-monitoring-top?orgId=1&from=now-6h&to=now&timezone=America%2FDenver&refresh=10s | O64: Monthly | R64: Higher is Better | S64: 0.9 | T64: 0.75
A65: Kari Johnson | B65: Registrar | C65: Records, Registration, Support | D65: Transcripts processed within 10 days | E65: Student Outcomes | F65: Autonomy | G65: Data in report | H65: 90-100% | I65: 75-90% | J65: <75% | K65: Tracking | L65: 0.93 | M65: =IF(K65="Not Tracking","Not Tracked",IF(L65="","No Data",IF(R65="Higher is Better",IF(L65>=S65,"Green",IF(L65>=T65,"Yellow","Red")),IF(R65="Lower is Better",IF(L65<=S65,"Green",IF(L65<=T65,"Yellow","Red")),"Manual Review")))) -> Green | N65: https://app.powerbi.com/groups/me/apps/d4fe7f49-1b93-41aa-9e7d-6ee6d5ec3eb0/reports/32370e33-dc03-418d-9403-25cfd508af0b/ReportSection9394f2e53928728d117e?experience=power-bi | O65: Monthly | R65: Lower is Better | S65: 5 | T65: 30
A66: Kari Johnson | B66: Registrar | C66: Records, Registration, Support | D66: Case CSAT for planning and registration | E66: Student Outcomes | F66: Satisfaction | G66: Data in report | H66: 85-100% | I66: 70-84% | J66: Below 70% | K66: Tracking | M66: =IF(K66="Not Tracking","Not Tracked",IF(L66="","No Data",IF(R66="Higher is Better",IF(L66>=S66,"Green",IF(L66>=T66,"Yellow","Red")),IF(R66="Lower is Better",IF(L66<=S66,"Green",IF(L66<=T66,"Yellow","Red")),"Manual Review")))) -> No Data | N66: https://app.powerbi.com/groups/4f9c84ba-b5d3-4eda-a86b-41fbb3b3bc4a/reports/af9ba6b3-8092-4e0c-bb52-4f8903b1b861/77b2e5ed1050bc711c70?experience=power-bi | O66: Monthly | R66: Higher is Better | S66: 0.85 | T66: 0.7
A67: Kim Overdiek | B67: Associate Registrar | C67: Records, Registration, Support | D67: Case resolution within 5 days | E67: Operational Outcomes | F67: Speed | G67: Data in report | H67: 85-100% | I67: 65-84% | J67: Below 65% | K67: Tracking | M67: =IF(K67="Not Tracking","Not Tracked",IF(L67="","No Data",IF(R67="Higher is Better",IF(L67>=S67,"Green",IF(L67>=T67,"Yellow","Red")),IF(R67="Lower is Better",IF(L67<=S67,"Green",IF(L67<=T67,"Yellow","Red")),"Manual Review")))) -> No Data | N67: https://app.powerbi.com/groups/me/apps/edf61692-3af5-4aba-af7e-ef1de76ce451/reports/70c7e184-e400-4cac-9500-f8ec201a252b/ReportSection9394f2e53928728d117e?ctid=61e6eeb3-5fd7-4aaa-ae3c-61e8deb09b79&experience=power-bi | O67: Monthly | R67: Higher is Better | S67: 0.85 | T67: 0.65
A68: Kim Overdiek | B68: Associate Registrar | C68: Records, Registration, Support | D68: On-time catalog publishing rate | E68: Operational Outcomes | F68: Speed | G68: No data | H68: NA | I68: NA | J68: NA | K68: Not Tracking | M68: =IF(K68="Not Tracking","Not Tracked",IF(L68="","No Data",IF(R68="Higher is Better",IF(L68>=S68,"Green",IF(L68>=T68,"Yellow","Red")),IF(R68="Lower is Better",IF(L68<=S68,"Green",IF(L68<=T68,"Yellow","Red")),"Manual Review")))) -> Not Tracked | O68: Monthly | R68: Manual
A69: Kim Overdiek | B69: Associate Registrar | C69: Records, Registration, Support | D69: On-time system configuration rate | E69: Operational Outcomes | F69: Speed | G69: No data | H69: NA | I69: NA | J69: NA | K69: Not Tracking | M69: =IF(K69="Not Tracking","Not Tracked",IF(L69="","No Data",IF(R69="Higher is Better",IF(L69>=S69,"Green",IF(L69>=T69,"Yellow","Red")),IF(R69="Lower is Better",IF(L69<=S69,"Green",IF(L69<=T69,"Yellow","Red")),"Manual Review")))) -> Not Tracked | O69: Monthly | R69: Manual
A70: Kim Overdiek | B70: Associate Registrar | C70: Records, Registration, Support | D70: Process case QA | E70: Operational Outcomes | F70: Quality | G70: Data in report | H70: 85-100% | I70: 70-84% | J70: Below 70% | K70: Tracking | L70: =AVERAGE(L86,L94) -> 0.9543 | M70: =IF(K70="Not Tracking","Not Tracked",IF(L70="","No Data",IF(R70="Higher is Better",IF(L70>=S70,"Green",IF(L70>=T70,"Yellow","Red")),IF(R70="Lower is Better",IF(L70<=S70,"Green",IF(L70<=T70,"Yellow","Red")),"Manual Review")))) -> Green | N70: =N86&" / "&N94 -> https://app.powerbi.com/groups/me/apps/edf61692-3af5-4aba-af7e-ef1de76ce451/reports/7f263ef8-0c4e-4dbd-8c84-2d5d029a1085/e5ac827acf52df1bdc6a?ctid=61e6eeb3-5fd7-4aaa-ae3c-61e8deb09b79&experience=power-bi / https://app.powerbi.com/groups/me/apps/edf61692-3af5-4aba-af7e-ef1de76ce451/reports/7f263ef8-0c4e-4dbd-8c84-2d5d029a1085/185501d1d1107d800e43?ctid=61e6eeb3-5fd7-4aaa-ae3c-61e8deb09b79&experience=power-bi | O70: Monthly | P70: 46223 | R70: Higher is Better | S70: 0.85 | T70: 0.7
A71: Kim Overdiek | B71: Associate Registrar | C71: Records, Registration, Support | D71: Process case CSAT | E71: Operational Outcomes | F71: Quality | G71: Data in report | H71: 85-100% | I71: 70-84% | J71: Below 70% | K71: Tracking | L71: =AVERAGE(L85,L95) -> 0.8665 | M71: =IF(K71="Not Tracking","Not Tracked",IF(L71="","No Data",IF(R71="Higher is Better",IF(L71>=S71,"Green",IF(L71>=T71,"Yellow","Red")),IF(R71="Lower is Better",IF(L71<=S71,"Green",IF(L71<=T71,"Yellow","Red")),"Manual Review")))) -> Green | N71: =N85&" / "&N95 -> https://app.powerbi.com/groups/4f9c84ba-b5d3-4eda-a86b-41fbb3b3bc4a/reports/af9ba6b3-8092-4e0c-bb52-4f8903b1b861/77b2e5ed1050bc711c70?experience=power-bi / https://app.powerbi.com/groups/4f9c84ba-b5d3-4eda-a86b-41fbb3b3bc4a/reports/af9ba6b3-8092-4e0c-bb52-4f8903b1b861/77b2e5ed1050bc711c70?experience=power-bi | O71: Monthly | P71: 46223 | R71: Higher is Better | S71: 0.85 | T71: 0.7
A72: Tyson Bell | B72: Associate Registrar | C72: Records, Registration, Support | D72: Case resolution within 5 days | E72: Operational Outcomes | F72: Speed | G72: Data in report | H72: 90-100% | I72: 80-90% | J72: <80% | K72: Tracking | M72: =IF(K72="Not Tracking","Not Tracked",IF(L72="","No Data",IF(R72="Higher is Better",IF(L72>=S72,"Green",IF(L72>=T72,"Yellow","Red")),IF(R72="Lower is Better",IF(L72<=S72,"Green",IF(L72<=T72,"Yellow","Red")),"Manual Review")))) -> No Data | O72: Monthly | R72: Higher is Better | S72: 0.9 | T72: 0.8
A73: Tyson Bell | B73: Associate Registrar | C73: Records, Registration, Support | D73: Records case QA | E73: Operational Outcomes | F73: Quality | G73: Data in report | H73: 85-100% | I73: 70-84% | J73: Below 70% | K73: Tracking | M73: =IF(K73="Not Tracking","Not Tracked",IF(L73="","No Data",IF(R73="Higher is Better",IF(L73>=S73,"Green",IF(L73>=T73,"Yellow","Red")),IF(R73="Lower is Better",IF(L73<=S73,"Green",IF(L73<=T73,"Yellow","Red")),"Manual Review")))) -> No Data | N73: https://app.powerbi.com/groups/4f9c84ba-b5d3-4eda-a86b-41fbb3b3bc4a/reports/af9ba6b3-8092-4e0c-bb52-4f8903b1b861/1afb91a1da6d47c71041?experience=power-bi | O73: Monthly | R73: Higher is Better | S73: 0.85 | T73: 0.7
A74: Tyson Bell | B74: Associate Registrar | C74: Records, Registration, Support | D74: Records case CSAT | E74: Operational Outcomes | F74: Quality | G74: Data in report | H74: 85-100% | I74: 70-84% | J74: Below 70% | K74: Tracking | M74: =IF(K74="Not Tracking","Not Tracked",IF(L74="","No Data",IF(R74="Higher is Better",IF(L74>=S74,"Green",IF(L74>=T74,"Yellow","Red")),IF(R74="Lower is Better",IF(L74<=S74,"Green",IF(L74<=T74,"Yellow","Red")),"Manual Review")))) -> No Data | N74: https://app.powerbi.com/groups/4f9c84ba-b5d3-4eda-a86b-41fbb3b3bc4a/reports/af9ba6b3-8092-4e0c-bb52-4f8903b1b861/1afb91a1da6d47c71041?experience=power-bi | O74: Monthly | R74: Higher is Better | S74: 0.85 | T74: 0.7
A75: Angie Holt | B75: Graduation Coordinator | C75: Records, Registration, Support | D75: Graduation application case completion rate | E75: Operational Outcomes | F75: Speed | G75: Data available | H75: < 3 weeks | I75: 3-6 weeks | J75: Above 6 weeks | K75: Tracking | M75: =IF(K75="Not Tracking","Not Tracked",IF(L75="","No Data",IF(R75="Higher is Better",IF(L75>=S75,"Green",IF(L75>=T75,"Yellow","Red")),IF(R75="Lower is Better",IF(L75<=S75,"Green",IF(L75<=T75,"Yellow","Red")),"Manual Review")))) -> No Data | O75: Monthly | Q75: Work with Josh for a better report | R75: Lower is Better | S75: 3 | T75: 6
A76: Angie Holt | B76: Graduation Coordinator | C76: Records, Registration, Support | D76: Award processing rate | E76: Operational Outcomes | F76: Speed | G76: Data available | H76: < 3 weeks | I76: 3-6 weeks | J76: Above 6 weeks | K76: Not Tracking | L76: 3 | M76: =IF(K76="Not Tracking","Not Tracked",IF(L76="","No Data",IF(R76="Higher is Better",IF(L76>=S76,"Green",IF(L76>=T76,"Yellow","Red")),IF(R76="Lower is Better",IF(L76<=S76,"Green",IF(L76<=T76,"Yellow","Red")),"Manual Review")))) -> Not Tracked | N76: Block 3 Final Reviews_6.26.26.xlsx | O76: Monthly | P76: 46223 | R76: Lower is Better | S76: 3 | T76: 6
A77: Angie Holt | B77: Graduation Coordinator | C77: Records, Registration, Support | D77: Number of Rescinded Degrees | E77: Operational Outcomes | F77: Quality | G77: Data available | H77: 0 | I77: NA | J77: >1 | K77: Tracking | M77: =IF(K77="Not Tracking","Not Tracked",IF(L77="","No Data",IF(R77="Higher is Better",IF(L77>=S77,"Green",IF(L77>=T77,"Yellow","Red")),IF(R77="Lower is Better",IF(L77<=S77,"Green",IF(L77<=T77,"Yellow","Red")),"Manual Review")))) -> No Data | N77: Checking with Kari if this link can be shared outside the admin team | O77: Monthly | R77: Lower is Better | S77: 0 | T77: 1
A78: Angie Holt | B78: Graduation Coordinator | C78: Records, Registration, Support | D78: Application QA | E78: Operational Outcomes | F78: Quality | G78: Data available | H78: 95-100% | I78: 85-94% | J78: Below 85% | K78: Tracking | L78: 0.98 | M78: =IF(K78="Not Tracking","Not Tracked",IF(L78="","No Data",IF(R78="Higher is Better",IF(L78>=S78,"Green",IF(L78>=T78,"Yellow","Red")),IF(R78="Lower is Better",IF(L78<=S78,"Green",IF(L78<=T78,"Yellow","Red")),"Manual Review")))) -> Green | N78: 2026 Year QA Tracker.xlsx | O78: Monthly | P78: 46223 | R78: Higher is Better | S78: =95/100 -> 0.95 | T78: 0.85
A79: Angie Holt | B79: Graduation Coordinator | C79: Records, Registration, Support | D79: Awarding QA | E79: Operational Outcomes | F79: Quality | G79: Data available | H79: 95-100% | I79: 85-94% | J79: Below 85% | K79: Tracking | L79: 0.98 | M79: =IF(K79="Not Tracking","Not Tracked",IF(L79="","No Data",IF(R79="Higher is Better",IF(L79>=S79,"Green",IF(L79>=T79,"Yellow","Red")),IF(R79="Lower is Better",IF(L79<=S79,"Green",IF(L79<=T79,"Yellow","Red")),"Manual Review")))) -> Green | N79: 2026 Year QA Tracker.xlsx | O79: Monthly | P79: 46223 | R79: Higher is Better | S79: =95/100 -> 0.95 | T79: 0.85
A80: Anne E. Owen | B80: Records & Transcript Coordinator | C80: Records, Registration, Support | D80: Process case completion rate | E80: Operational Outcomes | F80: Speed | G80: Data in report | H80: < 5 days | I80: 6-10 Days | J80: Above 10 Days | K80: Tracking | M80: =IF(K80="Not Tracking","Not Tracked",IF(L80="","No Data",IF(R80="Higher is Better",IF(L80>=S80,"Green",IF(L80>=T80,"Yellow","Red")),IF(R80="Lower is Better",IF(L80<=S80,"Green",IF(L80<=T80,"Yellow","Red")),"Manual Review")))) -> No Data | N80: Transcript Requests - Power BI | O80: Monthly | R80: Lower is Better | S80: 5 | T80: 10
A81: Anne E. Owen | B81: Records & Transcript Coordinator | C81: Records, Registration, Support | D81: Process case CSAT | E81: Operational Outcomes | F81: Quality | G81: Data in report | H81: 85-100% | I81: 70-84% | J81: Below 70% | K81: Tracking | M81: =IF(K81="Not Tracking","Not Tracked",IF(L81="","No Data",IF(R81="Higher is Better",IF(L81>=S81,"Green",IF(L81>=T81,"Yellow","Red")),IF(R81="Lower is Better",IF(L81<=S81,"Green",IF(L81<=T81,"Yellow","Red")),"Manual Review")))) -> No Data | N81: C-SAT - Student Support Dashboard (R) - Power BI | O81: Monthly | R81: Higher is Better | S81: 0.85 | T81: 0.7
A82: Anne E. Owen | B82: Records & Transcript Coordinator | C82: Records, Registration, Support | D82: Process case QA | E82: Operational Outcomes | F82: Quality | G82: Data in report | H82: 85-100% | I82: 70-84% | J82: Below 70% | K82: Tracking | L82: 0.9 | M82: =IF(K82="Not Tracking","Not Tracked",IF(L82="","No Data",IF(R82="Higher is Better",IF(L82>=S82,"Green",IF(L82>=T82,"Yellow","Red")),IF(R82="Lower is Better",IF(L82<=S82,"Green",IF(L82<=T82,"Yellow","Red")),"Manual Review")))) -> Green | N82: Records Report | O82: Monthly | R82: Higher is Better | S82: 0.85 | T82: 0.7
A83: Anne E. Owen | B83: Records & Transcript Coordinator | C83: Records, Registration, Support | D83: Transcript accuracy QA | E83: Operational Outcomes | F83: Quality | G83: Data in report | H83: 85-100% | I83: 70-84% | J83: Below 70% | K83: Tracking | L83: 0.9 | M83: =IF(K83="Not Tracking","Not Tracked",IF(L83="","No Data",IF(R83="Higher is Better",IF(L83>=S83,"Green",IF(L83>=T83,"Yellow","Red")),IF(R83="Lower is Better",IF(L83<=S83,"Green",IF(L83<=T83,"Yellow","Red")),"Manual Review")))) -> Green | N83: Transcripts Report | O83: Monthly | R83: Higher is Better | S83: 0.85 | T83: 0.7
A84: Cindi C Putnam | B84: Planning Coordinator | C84: Records, Registration, Support | D84: Degree planning escalation case resolution rate | E84: Operational Outcomes | F84: Speed | G84: Data in report | H84: Resolution Rate < 5 Days | I84: 6-10 days | J84: Above 10 Day | K84: Not Tracking | M84: =IF(K84="Not Tracking","Not Tracked",IF(L84="","No Data",IF(R84="Higher is Better",IF(L84>=S84,"Green",IF(L84>=T84,"Yellow","Red")),IF(R84="Lower is Better",IF(L84<=S84,"Green",IF(L84<=T84,"Yellow","Red")),"Manual Review")))) -> Not Tracked | N84: https://app.powerbi.com/groups/me/apps/edf61692-3af5-4aba-af7e-ef1de76ce451/reports/70c7e184-e400-4cac-9500-f8ec201a252b/ReportSection9394f2e53928728d117e?ctid=61e6eeb3-5fd7-4aaa-ae3c-61e8deb09b79&experience=power-bi | O84: Monthly | Q84: Needs Improvement | R84: Lower is Better | S84: 5 | T84: 10
A85: Cindi C Putnam | B85: Planning Coordinator | C85: Records, Registration, Support | D85: Degree planning escalation case CSAT | E85: Operational Outcomes | F85: Quality | G85: Data in report | H85: 85-100% | I85: 70-84% | J85: Below 70% | K85: Tracking | L85: 0.8 | M85: =IF(K85="Not Tracking","Not Tracked",IF(L85="","No Data",IF(R85="Higher is Better",IF(L85>=S85,"Green",IF(L85>=T85,"Yellow","Red")),IF(R85="Lower is Better",IF(L85<=S85,"Green",IF(L85<=T85,"Yellow","Red")),"Manual Review")))) -> Yellow | N85: https://app.powerbi.com/groups/4f9c84ba-b5d3-4eda-a86b-41fbb3b3bc4a/reports/af9ba6b3-8092-4e0c-bb52-4f8903b1b861/77b2e5ed1050bc711c70?experience=power-bi | O85: Monthly | P85: 46223 | R85: Higher is Better | S85: 0.85 | T85: 0.7
A86: Cindi C Putnam | B86: Planning Coordinator | C86: Records, Registration, Support | D86: Degree planning escalation case QA | E86: Operational Outcomes | F86: Quality | G86: Data in report | H86: 85-100% | I86: 70-84% | J86: Below 70% | K86: Tracking | L86: 0.956 | M86: =IF(K86="Not Tracking","Not Tracked",IF(L86="","No Data",IF(R86="Higher is Better",IF(L86>=S86,"Green",IF(L86>=T86,"Yellow","Red")),IF(R86="Lower is Better",IF(L86<=S86,"Green",IF(L86<=T86,"Yellow","Red")),"Manual Review")))) -> Green | N86: https://app.powerbi.com/groups/me/apps/edf61692-3af5-4aba-af7e-ef1de76ce451/reports/7f263ef8-0c4e-4dbd-8c84-2d5d029a1085/e5ac827acf52df1bdc6a?ctid=61e6eeb3-5fd7-4aaa-ae3c-61e8deb09b79&experience=power-bi | O86: Monthly | P86: 46223 | R86: Higher is Better | S86: 0.85 | T86: 0.7
A87: Nikki Jane Chambers | B87: Enrollment Verification Specialist | C87: Records, Registration, Support | D87: Enrollment verification completion rate | E87: Operational Outcomes | F87: Speed | G87: Data available | H87: < 5 days | I87: 6-10 Days | J87: Above 10 Days | K87: Tracking | L87: 4.5 | M87: =IF(K87="Not Tracking","Not Tracked",IF(L87="","No Data",IF(R87="Higher is Better",IF(L87>=S87,"Green",IF(L87>=T87,"Yellow","Red")),IF(R87="Lower is Better",IF(L87<=S87,"Green",IF(L87<=T87,"Yellow","Red")),"Manual Review")))) -> Green | N87: https://cne-101008.crm.dynamics.com/main.aspx?appid=155f9667-c2f7-ed11-8847-000d3a358523 | O87: Monthly | R87: Lower is Better | S87: 5 | T87: 10
A88: Nikki Jane Chambers | B88: Enrollment Verification Specialist | C88: Records, Registration, Support | D88: Apostille completion rate | E88: Operational Outcomes | F88: Speed | G88: Data available | H88: <10 Days | I88: 11-14 days | J88: Above 14 days | K88: Tracking | L88: 29 | M88: =IF(K88="Not Tracking","Not Tracked",IF(L88="","No Data",IF(R88="Higher is Better",IF(L88>=S88,"Green",IF(L88>=T88,"Yellow","Red")),IF(R88="Lower is Better",IF(L88<=S88,"Green",IF(L88<=T88,"Yellow","Red")),"Manual Review")))) -> Red | N88: https://cne-101008.crm.dynamics.com/main.aspx?appid=155f9667-c2f7-ed11-8847-000d3a358523 | O88: Monthly | R88: Lower is Better | S88: 10 | T88: 14
A89: Nikki Jane Chambers | B89: Enrollment Verification Specialist | C89: Records, Registration, Support | D89: Enrollment verification QA | E89: Operational Outcomes | F89: Quality | G89: Data in report | H89: 85-100% | I89: 70-84% | J89: Below 70% | K89: Tracking | L89: 0.963 | M89: =IF(K89="Not Tracking","Not Tracked",IF(L89="","No Data",IF(R89="Higher is Better",IF(L89>=S89,"Green",IF(L89>=T89,"Yellow","Red")),IF(R89="Lower is Better",IF(L89<=S89,"Green",IF(L89<=T89,"Yellow","Red")),"Manual Review")))) -> Green | N89: https://app.powerbi.com/groups/4f9c84ba-b5d3-4eda-a86b-41fbb3b3bc4a/reports/af9ba6b3-8092-4e0c-bb52-4f8903b1b861/1afb91a1da6d47c71041?experience=power-bi | O89: Monthly | R89: Higher is Better | S89: 0.85 | T89: 0.7
A90: Nikki Jane Chambers | B90: Enrollment Verification Specialist | C90: Records, Registration, Support | D90: Apostille QA | E90: Operational Outcomes | F90: Quality | G90: No data | H90: NA | I90: NA | J90: NA | K90: Not Tracking | M90: =IF(K90="Not Tracking","Not Tracked",IF(L90="","No Data",IF(R90="Higher is Better",IF(L90>=S90,"Green",IF(L90>=T90,"Yellow","Red")),IF(R90="Lower is Better",IF(L90<=S90,"Green",IF(L90<=T90,"Yellow","Red")),"Manual Review")))) -> Not Tracked | O90: Monthly | R90: Manual
A91: Nikki Jane Chambers | B91: Enrollment Verification Specialist | C91: Records, Registration, Support | D91: Enrollment verification CSAT | E91: Operational Outcomes | F91: Quality | G91: Data in report | H91: 85-100% | I91: 70-84% | J91: Below 70% | K91: Tracking | L91: 0.8846 | M91: =IF(K91="Not Tracking","Not Tracked",IF(L91="","No Data",IF(R91="Higher is Better",IF(L91>=S91,"Green",IF(L91>=T91,"Yellow","Red")),IF(R91="Lower is Better",IF(L91<=S91,"Green",IF(L91<=T91,"Yellow","Red")),"Manual Review")))) -> Green | N91: https://app.powerbi.com/groups/4f9c84ba-b5d3-4eda-a86b-41fbb3b3bc4a/reports/af9ba6b3-8092-4e0c-bb52-4f8903b1b861/1afb91a1da6d47c71041?experience=power-bi | O91: Monthly | R91: Higher is Better | S91: 0.85 | T91: 0.7
A92: Nikki Jane Chambers | B92: Enrollment Verification Specialist | C92: Records, Registration, Support | D92: Apostille C-Sat | E92: Operational Outcomes | F92: Quality | G92: No data | H92: NA | I92: NA | J92: NA | K92: Not Tracking | M92: =IF(K92="Not Tracking","Not Tracked",IF(L92="","No Data",IF(R92="Higher is Better",IF(L92>=S92,"Green",IF(L92>=T92,"Yellow","Red")),IF(R92="Lower is Better",IF(L92<=S92,"Green",IF(L92<=T92,"Yellow","Red")),"Manual Review")))) -> Not Tracked | O92: Monthly | R92: Manual
A93: Daniel Zago | B93: Registration Specialist | C93: Records, Registration, Support | D93: Registration issue case resolution rate | E93: Operational Outcomes | F93: Speed | G93: Data in report | H93: Resolution Rate < 24 hours | I93: < 3 days | J93: Above 3 Days | K93: Not Tracking | M93: =IF(K93="Not Tracking","Not Tracked",IF(L93="","No Data",IF(R93="Higher is Better",IF(L93>=S93,"Green",IF(L93>=T93,"Yellow","Red")),IF(R93="Lower is Better",IF(L93<=S93,"Green",IF(L93<=T93,"Yellow","Red")),"Manual Review")))) -> Not Tracked | N93: https://app.powerbi.com/groups/me/apps/edf61692-3af5-4aba-af7e-ef1de76ce451/reports/fd36c261-899f-4645-aef4-d7302ec76d79/ReportSection9394f2e53928728d117e?ctid=61e6eeb3-5fd7-4aaa-ae3c-61e8deb09b79&experience=power-bi | O93: Monthly | R93: Higher is Better | S93: 24 | T93: 3
A94: Daniel Zago | B94: Registration Specialist | C94: Records, Registration, Support | D94: Registration issue case QA | E94: Operational Outcomes | F94: Quality | G94: Data in report | H94: 85-100% | I94: 70-84% | J94: Below 70% | K94: Tracking | L94: 0.9526 | M94: =IF(K94="Not Tracking","Not Tracked",IF(L94="","No Data",IF(R94="Higher is Better",IF(L94>=S94,"Green",IF(L94>=T94,"Yellow","Red")),IF(R94="Lower is Better",IF(L94<=S94,"Green",IF(L94<=T94,"Yellow","Red")),"Manual Review")))) -> Green | N94: https://app.powerbi.com/groups/me/apps/edf61692-3af5-4aba-af7e-ef1de76ce451/reports/7f263ef8-0c4e-4dbd-8c84-2d5d029a1085/185501d1d1107d800e43?ctid=61e6eeb3-5fd7-4aaa-ae3c-61e8deb09b79&experience=power-bi | O94: Monthly | P94: 46223 | R94: Higher is Better | S94: 0.85 | T94: 0.7
A95: Daniel Zago | B95: Registration Specialist | C95: Records, Registration, Support | D95: Registration issue case CSAT | E95: Operational Outcomes | F95: Quality | G95: Data in report | H95: 85-100% | I95: 70-84% | J95: Below 70% | K95: Tracking | L95: 0.933 | M95: =IF(K95="Not Tracking","Not Tracked",IF(L95="","No Data",IF(R95="Higher is Better",IF(L95>=S95,"Green",IF(L95>=T95,"Yellow","Red")),IF(R95="Lower is Better",IF(L95<=S95,"Green",IF(L95<=T95,"Yellow","Red")),"Manual Review")))) -> Green | N95: https://app.powerbi.com/groups/4f9c84ba-b5d3-4eda-a86b-41fbb3b3bc4a/reports/af9ba6b3-8092-4e0c-bb52-4f8903b1b861/77b2e5ed1050bc711c70?experience=power-bi | O95: Monthly | P95: 46223 | R95: Higher is Better | S95: 0.85 | T95: 0.7
A96: Jacob Adams | B96: =_xlfn.XLOOKUP(A96,'Digital Ops'!$A$3:$A$12,'Digital Ops'!$B$3:$B$12) -> Director of Digital Operations | C96: Digital Operations | D96: Overall Stakeholder CSAT | E96: Operational Outcomes | F96: Quality | G96: Data available | H96: 85-100% | I96: 75-84% | J96: <75% | K96: Not Tracking | M96: =IF(K96="Not Tracking","Not Tracked",IF(L96="","No Data",IF(R96="Higher is Better",IF(L96>=S96,"Green",IF(L96>=T96,"Yellow","Red")),IF(R96="Lower is Better",IF(L96<=S96,"Green",IF(L96<=T96,"Yellow","Red")),"Manual Review")))) -> Not Tracked | O96: Monthly | R96: Higher is Better | S96: 0.85 | T96: 0.75
A97: Jacob Adams | B97: =_xlfn.XLOOKUP(A97,'Digital Ops'!$A$3:$A$12,'Digital Ops'!$B$3:$B$12) -> Director of Digital Operations | C97: Digital Operations | D97: Digital Ops budget | E97: Operational Outcomes | F97: Cost | G97: Data available | H97: $ | I97: $ | J97: $ | K97: Not Tracking | M97: =IF(K97="Not Tracking","Not Tracked",IF(L97="","No Data",IF(R97="Higher is Better",IF(L97>=S97,"Green",IF(L97>=T97,"Yellow","Red")),IF(R97="Lower is Better",IF(L97<=S97,"Green",IF(L97<=T97,"Yellow","Red")),"Manual Review")))) -> Not Tracked | O97: Monthly | R97: Manual
A98: Jacob Adams | B98: =_xlfn.XLOOKUP(A98,'Digital Ops'!$A$3:$A$12,'Digital Ops'!$B$3:$B$12) -> Director of Digital Operations | C98: Digital Operations | D98: Costs saved by customers due to Digital Ops technologies (secondary) | E98: Operational Outcomes | F98: Cost | G98: Data available | H98: $ | I98: $ | J98: $ | K98: Not Tracking | M98: =IF(K98="Not Tracking","Not Tracked",IF(L98="","No Data",IF(R98="Higher is Better",IF(L98>=S98,"Green",IF(L98>=T98,"Yellow","Red")),IF(R98="Lower is Better",IF(L98<=S98,"Green",IF(L98<=T98,"Yellow","Red")),"Manual Review")))) -> Not Tracked | O98: Monthly | R98: Manual
A99: Jacob Adams | B99: =_xlfn.XLOOKUP(A99,'Digital Ops'!$A$3:$A$12,'Digital Ops'!$B$3:$B$12) -> Director of Digital Operations | C99: Digital Operations | D99: Overall student autonomy (secondary) | E99: Student Outcomes | F99: Student Autonomy | G99: Data in report | H99: 80-100% | I99: 65-79% | J99: <65% | K99: Tracking | L99: 0.704 | M99: =IF(K99="Not Tracking","Not Tracked",IF(L99="","No Data",IF(R99="Higher is Better",IF(L99>=S99,"Green",IF(L99>=T99,"Yellow","Red")),IF(R99="Lower is Better",IF(L99<=S99,"Green",IF(L99<=T99,"Yellow","Red")),"Manual Review")))) -> Yellow | N99: https://app.powerbi.com/Redirect?action=OpenReport&appId=d4fe7f49-1b93-41aa-9e7d-6ee6d5ec3eb0&reportObjectId=be2cacf8-fa52-4ce4-abf5-f9ee28fa66a6&ctid=61e6eeb3-5fd7-4aaa-ae3c-61e8deb09b79&reportPage=90333e1e71861247c683&pbi_source=appShareLink&portalSessionId=78f4edc2-9814-43bc-bc67-b03ff6a08911 | O99: Term | R99: Higher is Better | S99: 0.8 | T99: 0.65
A100: Jacob Adams | B100: =_xlfn.XLOOKUP(A100,'Digital Ops'!$A$3:$A$12,'Digital Ops'!$B$3:$B$12) -> Director of Digital Operations | C100: Digital Operations | D100: Overall student satisfaction (secondary) | E100: Student Outcomes | F100: Student Satisfaction | G100: Data in report | H100: 80-100% | I100: 65-79% | J100: <65% | K100: Tracking | L100: 0.8261 | M100: =IF(K100="Not Tracking","Not Tracked",IF(L100="","No Data",IF(R100="Higher is Better",IF(L100>=S100,"Green",IF(L100>=T100,"Yellow","Red")),IF(R100="Lower is Better",IF(L100<=S100,"Green",IF(L100<=T100,"Yellow","Red")),"Manual Review")))) -> Green | N100: https://app.powerbi.com/Redirect?action=OpenReport&appId=d4fe7f49-1b93-41aa-9e7d-6ee6d5ec3eb0&reportObjectId=58eb3239-b972-4ee8-8645-fcf195f36c96&ctid=61e6eeb3-5fd7-4aaa-ae3c-61e8deb09b79&reportPage=02d230574060475bc0e4&pbi_source=appShareLink&portalSessionId=78f4edc2-9814-43bc-bc67-b03ff6a08911 | O100: Term | R100: Higher is Better | S100: 0.8 | T100: 0.65
...

Sheet Sheet1
A1: {=_xlfn.UNIQUE('KPI ScoreCard'!A3:A155)} -> Steven K. Thomas | D1: Aitana Toscano
A2: 0 | D2: Alison Cundiff
A3: Anne Marie Clark | D3: Alyssa Burrell
A4: Katelyn Ray | D4: Ana De Castro
A5: Sandra Wurttele | D5: Angie Holt
A6: Ana De Castro | D6: Anne E. Owen
A7: Helen Reboucas | D7: Anne Marie Clark
A8: Joseph Bentum | D8: Brad Lester
A9: Mark Gefrom | D9: Cindi C Putnam
A10: Brad Lester | D10: Colby Warner
A11: Alyssa Burrell | D11: Daniel Zago
A12: Hilary Bagley | D12: David Peck
A13: Kira Hayes | D13: Ely Zmolek
A14: Matthew Smith | D14: Helen Reboucas
... A16: Kari Johnson | D16: Jacob Adams
A17: Kim Overdiek | D17: Joanna Relkin | H17: https://app.powerbi.com/groups/me/apps/edf61692-3af5-4aba-af7e-ef1de76ce451/reports/7f263ef8-0c4e-4dbd-8c84-2d5d029a1085/e5ac827acf52df1bdc6a?ctid=61e6eeb3-5fd7-4aaa-ae3c-61e8deb09b79&experience=power-bi / https://app.powerbi.com/groups/me/apps/edf61692-3af5-4aba-af7e-ef1de76ce451/reports/7f263ef8-0c4e-4dbd-8c84-2d5d029a1085/185501d1d1107d800e43?ctid=61e6eeb3-5fd7-4aaa-ae3c-61e8deb09b79&experience=power-bi
A18: Tyson Bell | D18: John Ayinde
A19: Angie Holt | D19: Joseph Bentum
A20: Anne E. Owen | D20: Joshua Stafford Hadden
A21: Cindi C Putnam | D21: Kari Johnson
A22: Nikki Jane Chambers | D22: Katelyn Graf
A23: Daniel Zago | D23: Katelyn Ray
A24: Jacob Adams | D24: Kelley Richardson
A25: Ricky Kailiponi Jr. | D25: Kim Overdiek
A26: Joshua Stafford Hadden | D26: Kimarie Howard
A27: David Peck | D27: Kira Hayes
A28: Pelenatita Neiufi | D28: Mandy Schwab
A29: Victor Lamôni Calado Ferreira | D29: Mark Gefrom
... A42: Shaunasee Janette James | D42: Victor Lamôni Calado Ferreira
A43: Ely Zmolek
